Workbook

Sheet Cover
B1: Project Lodestone — Centerra Gold / Ero Copper
B2: Hypothetical buy-side merger analysis. Public information only. Not investment advice. Not affiliated with any bank. See DISCLAIMER.md.
B4: Tab | C4: Contents
B5: Inputs | C5: Price deck, FX, price-case selectors, discount rates
B6: Market | C6: yfinance snapshot: prices, shares, balance sheet, TTM metrics
B7: MtMilligan … Xavantina | C7: One life-of-mine NAV model per asset
B8: Corporate_NAV | C8: NAV roll-up, NAV per share, P/NAV and 2027–28E financial summary
B9: Comps | C9: Peer trading multiples (written by scripts/build_comps.py)
B10: Precedents | C10: Copper and gold M&A precedents: premiums, P/NAV, value per reserve ounce
B11: Synergies | C11: US$155M run-rate synergy case, phase-in and NPV
B12: Merger | C12: Offer, exchange ratio, funding, ownership, accretion/dilution to EPS, CFPS and NAVPS
B13: Contribution | C13: Contribution analysis versus pro forma ownership
B14: Scenarios | C14: Outputs under each price case (filled by scripts/run_scenarios.py)
B15: Sensitivity | C15: Premium vs copper price; synergies vs consideration mix
... B26: Market snapshot | C26: 20261025T0009Z

Sheet Inputs
B1: Inputs
B2: Price deck, FX, price-case selectors and discount rates. Edit blue cells (or the CSVs under data/ and rebuild).
B4: Spot market (yfinance snapshot 20261025T0009Z)
B5: Copper spot (COMEX HG) | C5: 6.476 | D5: US$/lb | E5: Source: MKT-YF (data/market/latest_macro.csv)
B6: Gold spot (COMEX GC) | C6: 4007.8999 | D6: US$/oz | E6: Source: MKT-YF (data/market/latest_macro.csv)
B7: CAD/USD spot | C7: 0.7141 | D7: US$ per C$ | E7: Source: MKT-YF (data/market/latest_macro.csv)
B9: Price case selectors (1 = analyst deck, 2 = spot held flat, 3 = custom flat)
B10: Copper price case | C10: 1
B11: Gold price case | C11: 1
B12: Custom copper price (US$/lb) | C12: 4.5
B13: Custom gold price (US$/oz) | C13: 3000
B15: Price deck | E15: Source | F15: 2027 | G15: 2028 | H15: 2029 | I15: 2030 | J15: 2031 | K15: 2032 | L15: 2033 | M15: 2034 | N15: 2035 | O15: 2036 | P15: 2037 | Q15: 2038 | R15: 2039 | S15: 2040 | T15: 2041 | U15: 2042 | V15: 2043 | W15: 2044 | X15: 2045 | Y15: 2046 | Z15: 2047 | AA15: 2048 | AB15: 2049 | AC15: 2050
B16: Copper deck (US$/lb) | E16: data/price_deck.csv; last deck year held flat | F16: 6 | G16: 5.5 | H16: 5 | I16: 5 | J16: 5 | K16: 5 | L16: 5 | M16: 5 | N16: 5 | O16: 5 | P16: 5 | Q16: 5 | R16: 5 | S16: 5 | T16: 5 | U16: 5 | V16: 5 | W16: 5 | X16: 5 | Y16: 5 | Z16: 5 | AA16: 5 | AB16: 5 | AC16: 5
B17: Gold deck (US$/oz) | E17: data/price_deck.csv; last deck year held flat | F17: 3900 | G17: 3600 | H17: 3300 | I17: 3300 | J17: 3300 | K17: 3300 | L17: 3300 | M17: 3300 | N17: 3300 | O17: 3300 | P17: 3300 | Q17: 3300 | R17: 3300 | S17: 3300 | T17: 3300 | U17: 3300 | V17: 3300 | W17: 3300 | X17: 3300 | Y17: 3300 | Z17: 3300 | AA17: 3300 | AB17: 3300 | AC17: 3300
B18: Copper price used in model (US$/lb) | E18: CHOOSE(case, deck, spot, custom) | F18: =CHOOSE($C$10,F16,$C$5,$C$12) -> 6 | G18: =CHOOSE($C$10,G16,$C$5,$C$12) -> 5.5 | H18: =CHOOSE($C$10,H16,$C$5,$C$12) -> 5 | I18: =CHOOSE($C$10,I16,$C$5,$C$12) -> 5 | J18: =CHOOSE($C$10,J16,$C$5,$C$12) -> 5 | K18: =CHOOSE($C$10,K16,$C$5,$C$12) -> 5 | L18: =CHOOSE($C$10,L16,$C$5,$C$12) -> 5 | M18: =CHOOSE($C$10,M16,$C$5,$C$12) -> 5 | ... AC18: =CHOOSE($C$10,AC16,$C$5,$C$12) -> 5
B19: Gold price used in model (US$/oz) | E19: CHOOSE(case, deck, spot, custom) | F19: =CHOOSE($C$11,F17,$C$6,$C$13) -> 3900 | G19: =CHOOSE($C$11,G17,$C$6,$C$13) -> 3600 | H19: =CHOOSE($C$11,H17,$C$6,$C$13) -> 3300 | I19: =CHOOSE($C$11,I17,$C$6,$C$13) -> 3300 | J19: =CHOOSE($C$11,J17,$C$6,$C$13) -> 3300 | K19: =CHOOSE($C$11,K17,$C$6,$C$13) -> 3300 | L19: =CHOOSE($C$11,L17,$C$6,$C$13) -> 3300 | M19: =CHOOSE($C$11,M17,$C$6,$C$13) -> 3300 | ... AC19: =CHOOSE($C$11,AC17,$C$6,$C$13) -> 3300
B21: Discount rate (real) | C21: Rate | E21: Rationale
B22: Mount Milligan | C22: 0.065 | E22: Blended: roughly 50/50 gold/copper revenue after the Royal Gold stream, midway between 5% gold and 8% copper conventions
B23: Öksüt | C23: 0.05 | E23: Gold heap leach; sell-side gold convention (5% real)
B24: Goldfield | C24: 0.05 | E24: Gold heap leach development in Nevada; 5% real gold convention
B25: Caraíba | C25: 0.08 | E25: Copper concentrator; sell-side copper convention (8% real)
B26: Tucumã | C26: 0.08 | E26: Copper concentrator; sell-side copper convention (8% real)
B27: Xavantina | C27: 0.05 | E27: Underground gold; 5% real gold convention
B29: Corporate
B30: G&A capitalisation (years) | C30: 10
B31: G&A discount rate | C31: 0.05

Sheet Market
B1: Market data
B2: yfinance snapshot 20261025T0009Z (scripts/fetch_market_data.py). Balance sheet and TTM figures converted to US$M.
B4: Ticker | C4: Company | D4: Price (C$) | E4: Shares (M) | F4: Mkt cap (US$M) | G4: Cash (US$M) | H4: Debt (US$M) | I4: EV (US$M) | J4: EBITDA TTM (US$M) | K4: CFO TTM (US$M) | L4: EPS TTM (US$) | M4: 52w low (C$) | N4: 52w high (C$) | O4: Target low (C$) | P4: Target mean (C$) | Q4: Target high (C$)
B5: CG.TO | C5: Centerra Gold | D5: 28.32 | E5: 198.59506 | F5: 4016.1465 | G5: 453.10301 | H5: 45.762 | I5: 3608.8055 | J5: 859.96064 | K5: 450.99002 | L5: 4.35 | M5: 14.65 | N5: 33.94 | O5: 22.522635 | P5: 33.624023 | Q5: 44.73018
B6: ERO.TO | C6: Ero Copper | D6: 42.03 | E6: 104.30263 | F6: 3130.4194 | G6: 101.742 | H6: 573.35501 | I6: 3602.0324 | J6: 517.02598 | K6: 470.05901 | L6: 4.08 | M6: 27.22 | N6: 56.62 | O6: 47 | P6: 56.83312 | Q6: 68
B7: CS.TO | C7: Capstone Copper | D7: 11.19 | E7: 763.94934 | F7: 6104.3934 | G7: 371.16899 | H7: 1567.668 | I7: 7300.8924 | J7: 985.72403 | K7: 827.24698 | L7: 0.84 | M7: 9.3 | N7: 18.04 | O7: 15 | P7: 18.009 | Q7: 22
B8: TXG.TO | C8: Torex Gold | D8: 67.14 | E8: 92.594592 | F8: 4439.3034 | G8: 169.4 | H8: 99.4 | I8: 4369.3034 | J8: 1063.4 | K8: 808.49997 | L8: 9 | M8: 51.4 | N8: 85 | O8: 85 | P8: 95.3 | Q8: 105
B9: OGC.TO | C9: OceanaGold | D9: 34.67 | E9: 222.44752 | F9: 5507.1802 | G9: 654.8 | H9: 50.1 | I9: 4902.4802 | J9: 1436.5 | K9: 1280.8 | L9: 5.21 | M9: 29.52 | N9: 59.2 | O9: 44.856213 | P9: 56.97794 | Q9: 72.56313
B10: SSRM.TO | C10: SSR Mining | D10: 39.75 | E10: 207.49107 | F10: 5889.5812 | G10: 1833.964 | H10: 2.3 | I10: 4057.9172 | J10: 863.728 | K10: 596.752 | L10: 4.12 | M10: 25.83 | N10: 54.5 | O10: 51.834408 | P10: 58.111282 | Q10: 67.59311
B11: HBM.TO | C11: Hudbay Minerals | D11: 30.76 | E11: 444.14476 | F11: 9755.7069 | G11: 890.89997 | H11: 1044.5 | I11: 9909.3069 | J11: 1146.5999 | K11: 830.89997 | L11: 2.36 | M11: 20.26 | N11: 44.48 | O11: 39.33584 | P11: 45.203106 | Q11: 51.834408
B12: LUN.TO | C12: Lundin Mining | D12: 29.5 | E12: 851.35956 | F12: 17934.237 | G12: 265.8 | H12: 388.6 | I12: 18057.037 | J12: 2177.9999 | K12: 1781.9 | L12: 2.16 | M12: 21.2 | N12: 45.74 | O12: 32.529892 | P12: 42.956738 | Q12: 53.215202
B13: ELD.TO | C13: Eldorado Gold | D13: 44.32 | E13: 260.81033 | F13: 8254.1511 | G13: 554.56198 | H13: 1763.135 | I13: 9462.7241 | J13: 1151.0159 | K13: 744.20301 | L13: 3.97 | M13: 34.25 | N13: 69.46 | O13: 44.856213 | P13: 65.56697 | Q13: 77.53315
B14: DPM.TO | C14: DPM Metals | D14: 56.02 | E14: 219.36865 | F14: 8775.372 | G14: 761.20902 | H14: 8.413 | I14: 8022.576 | J14: 859.67898 | K14: 768.27501 | L14: 4.27 | M14: 29.12 | N14: 72.54 | O14: 59.8699 | P14: 69.76349 | Q14: 81.50888
B15: IMG.TO | C15: IAMGOLD | D15: 22.72 | E15: 571 | F15: 9263.8669 | G15: 502.4 | H15: 539.8 | I15: 9301.2669 | J15: 2051.0001 | K15: 1997.5 | L15: 2.74 | M15: 15.3 | N15: 34.09 | O15: 31.185507 | P15: 33.98911 | Q15: 35.92026
B16: EQX.TO | C16: Equinox Gold | D16: 14.13 | E16: 1167.4598 | F16: 11779.639 | G16: 481.57798 | H16: 839.05498 | I16: 12137.116 | J16: 1689.365 | K16: 1071.262 | L16: 0.66 | M16: 11.91 | N16: 25.87 | O16: 19.305916 | P16: 24.473698 | Q16: 30.691168
B18: Source: MKT-YF. Values are hardcoded inputs refreshed by the pipeline.

Sheet MtMilligan
B1: Mount Milligan — asset NAV (CG, Canada (BC))
B2: Reserve-constrained life-of-mine model. Blue = input (data/assets.csv), green = link, black = formula. US$M real unless noted.
B4: Input | C4: Value | D4: Unit | F4: Source / status
B5: Ownership | C5: 1 | D5: % | F5: Source IDs: CG-MRMR-2025;CG-MTM-PFS-2025;CG-Q2-2026;CG-RGLD-STREAM (see Sources tab)
B6: P&P reserve (at effective date) | C6: 470.332 | D6: Mt | F6: [verified] reserve_mt|au_gpt: Year-end 2025 P&P 470.3 Mt @ 0.28 g/t Au (CG-MRMR-2025)
B7: Depletion to 1 Jan 2027 | C7: 21.5 | D7: Mt | F7: [estimate] cu_grade_pct: Copper grade not captured from the MRMR table; 0.16% Cu calibrated to 50–60 Mlb/yr 2026 guidance
B8: Copper grade | C8: 0.0016 | D8: % Cu | F8: [verified] expansion_mtpa|expansion_year|growth_capex_usd_m: PFS: ~10% throughput increase in 2029 and US$186M growth capital
B9: Gold grade | C9: 0.28 | D9: g/t Au | F9: [calibrated] recoveries|opex_usd_t|sustaining_usd_m: Set so 2027 AISC lands in the US$1.2–1.3k/oz guidance range
B10: Copper recovery | C10: 0.8 | D10: % | F10: [verified] stream_*: Royal Gold stream: 35% of gold at US$435/oz; 18.75% of copper at 15% of spot
B11: Gold recovery | C11: 0.64 | D11: % | F11: [estimate] depleted_mt: 2026 ore processed (~59 ktpd)
B12: Copper payable | C12: 0.965 | D12: %
B13: Gold payable | C13: 0.97 | D13: %
B14: Throughput | C14: 21.5 | D14: Mtpa
B15: Throughput after expansion | C15: 23.65 | D15: Mtpa
B16: Expansion year | C16: 2029 | D16: year
B17: First production year | C17: 2027 | D17: year
B18: Site operating cost | C18: 13.5 | D18: US$/t milled
B19: TC/RC and freight | C19: 0.45 | D19: US$/lb Cu
B20: Sustaining capex | C20: 90 | D20: US$M/yr
B21: Growth capex (total) | C21: 186 | D21: US$M
B22: Growth capex start | C22: 2027 | D22: year
B23: Growth capex years | C23: 3 | D23: years
... B30: Stream copper price received | C30: 0.15 | D30: % of spot
B31: Discount rate (real) | C31: =Inputs!$C$22 -> 0.065 | D31: Inputs tab
B34: US$M unless noted | C34: Unit | D34: LOM / NPV | F34: 2027 | G34: 2028 | H34: 2029 | I34: 2030 | J34: 2031 | K34: 2032 | L34: 2033 | M34: 2034 | N34: 2035 | O34: 2036 | P34: 2037 | Q34: 2038 | R34: 2039 | S34: 2040 | T34: 2041 | U34: 2042 | V34: 2043 | W34: 2044 | X34: 2045 | Y34: 2046 | Z34: 2047 | AA34: 2048 | AB34: 2049 | AC34: 2050
B35: Period | F35: =F$34-2027+1 -> 1 | G35: =G$34-2027+1 -> 2 | H35: =H$34-2027+1 -> 3 | I35: =I$34-2027+1 -> 4 | J35: =J$34-2027+1 -> 5 | K35: =K$34-2027+1 -> 6 | L35: =L$34-2027+1 -> 7 | M35: =M$34-2027+1 -> 8 | ... AC35: =AC$34-2027+1 -> 24
B36: Copper price | C36: US$/lb | F36: =Inputs!F$18 -> 6 | G36: =Inputs!G$18 -> 5.5 | H36: =Inputs!H$18 -> 5 | I36: =Inputs!I$18 -> 5 | J36: =Inputs!J$18 -> 5 | K36: =Inputs!K$18 -> 5 | L36: =Inputs!L$18 -> 5 | M36: =Inputs!M$18 -> 5 | ... AC36: =Inputs!AC$18 -> 5
B37: Gold price | C37: US$/oz | F37: =Inputs!F$19 -> 3900 | G37: =Inputs!G$19 -> 3600 | H37: =Inputs!H$19 -> 3300 | I37: =Inputs!I$19 -> 3300 | J37: =Inputs!J$19 -> 3300 | K37: =Inputs!K$19 -> 3300 | L37: =Inputs!L$19 -> 3300 | M37: =Inputs!M$19 -> 3300 | ... AC37: =Inputs!AC$19 -> 3300
B38: Mill capacity | C38: Mt | F38: =IF(F$34<$C$17,0,IF(F$34>=$C$16,$C$15,$C$14)) -> 21.5 | G38: =IF(G$34<$C$17,0,IF(G$34>=$C$16,$C$15,$C$14)) -> 21.5 | H38: =IF(H$34<$C$17,0,IF(H$34>=$C$16,$C$15,$C$14)) -> 23.65 | I38: =IF(I$34<$C$17,0,IF(I$34>=$C$16,$C$15,$C$14)) -> 23.65 | J38: =IF(J$34<$C$17,0,IF(J$34>=$C$16,$C$15,$C$14)) -> 23.65 | K38: =IF(K$34<$C$17,0,IF(K$34>=$C$16,$C$15,$C$14)) -> 23.65 | L38: =IF(L$34<$C$17,0,IF(L$34>=$C$16,$C$15,$C$14)) -> 23.65 | M38: =IF(M$34<$C$17,0,IF(M$34>=$C$16,$C$15,$C$14)) -> 23.65 | ... AC38: =IF(AC$34<$C$17,0,IF(AC$34>=$C$16,$C$15,$C$14)) -> 23.65
B39: Opening reserve | C39: Mt | F39: =$C$6-$C$7 -> 448.832 | G39: =F41 -> 427.332 | H39: =G41 -> 405.832 | I39: =H41 -> 382.182 | J39: =I41 -> 358.532 | K39: =J41 -> 334.882 | L39: =K41 -> 311.232 | M39: =L41 -> 287.582 | N39: =M41 -> 263.932 | ... AC39: =AB41 -> 0
B40: Ore processed | C40: Mt | D40: =SUM(F40:AC40) -> 448.832 | F40: =MAX(0,MIN(F38,F39)) -> 21.5 | G40: =MAX(0,MIN(G38,G39)) -> 21.5 | H40: =MAX(0,MIN(H38,H39)) -> 23.65 | I40: =MAX(0,MIN(I38,I39)) -> 23.65 | J40: =MAX(0,MIN(J38,J39)) -> 23.65 | K40: =MAX(0,MIN(K38,K39)) -> 23.65 | L40: =MAX(0,MIN(L38,L39)) -> 23.65 | M40: =MAX(0,MIN(M38,M39)) -> 23.65 | ... AC40: =MAX(0,MIN(AC38,AC39)) -> 0
B41: Closing reserve | C41: Mt | F41: =F39-F40 -> 427.332 | G41: =G39-G40 -> 405.832 | H41: =H39-H40 -> 382.182 | I41: =I39-I40 -> 358.532 | J41: =J39-J40 -> 334.882 | K41: =K39-K40 -> 311.232 | L41: =L39-L40 -> 287.582 | M41: =M39-M40 -> 263.932 | ... AC41: =AC39-AC40 -> 0
B42: Payable copper | C42: Mlb | D42: =SUM(F42:AC42) -> 1222.2353 | F42: =F40*$C$8*$C$10*$C$12*2204.62 -> 58.547652 | G42: =G40*$C$8*$C$10*$C$12*2204.62 -> 58.547652 | H42: =H40*$C$8*$C$10*$C$12*2204.62 -> 64.402418 | I42: =I40*$C$8*$C$10*$C$12*2204.62 -> 64.402418 | J42: =J40*$C$8*$C$10*$C$12*2204.62 -> 64.402418 | K42: =K40*$C$8*$C$10*$C$12*2204.62 -> 64.402418 | L42: =L40*$C$8*$C$10*$C$12*2204.62 -> 64.402418 | M42: =M40*$C$8*$C$10*$C$12*2204.62 -> 64.402418 | ... AC42: =AC40*$C$8*$C$10*$C$12*2204.62 -> 0
B43: Payable gold | C43: koz | D43: =SUM(F43:AC43) -> 2508.3278 | F43: =F40*$C$9*$C$11*$C$13*1000/31.1035 -> 120.15419 | G43: =G40*$C$9*$C$11*$C$13*1000/31.1035 -> 120.15419 | H43: =H40*$C$9*$C$11*$C$13*1000/31.1035 -> 132.16961 | I43: =I40*$C$9*$C$11*$C$13*1000/31.1035 -> 132.16961 | J43: =J40*$C$9*$C$11*$C$13*1000/31.1035 -> 132.16961 | K43: =K40*$C$9*$C$11*$C$13*1000/31.1035 -> 132.16961 | L43: =L40*$C$9*$C$11*$C$13*1000/31.1035 -> 132.16961 | M43: =M40*$C$9*$C$11*$C$13*1000/31.1035 -> 132.16961 | ... AC43: =AC40*$C$9*$C$11*$C$13*1000/31.1035 -> 0
B44: Realised copper price (after stream) | C44: US$/lb | F44: =F36*(1-$C$29)+F36*$C$29*$C$30 -> 5.04375 | G44: =G36*(1-$C$29)+G36*$C$29*$C$30 -> 4.6234375 | H44: =H36*(1-$C$29)+H36*$C$29*$C$30 -> 4.203125 | I44: =I36*(1-$C$29)+I36*$C$29*$C$30 -> 4.203125 | J44: =J36*(1-$C$29)+J36*$C$29*$C$30 -> 4.203125 | K44: =K36*(1-$C$29)+K36*$C$29*$C$30 -> 4.203125 | L44: =L36*(1-$C$29)+L36*$C$29*$C$30 -> 4.203125 | M44: =M36*(1-$C$29)+M36*$C$29*$C$30 -> 4.203125 | ... AC44: =AC36*(1-$C$29)+AC36*$C$29*$C$30 -> 4.203125
B45: Realised gold price (after stream) | C45: US$/oz | F45: =F37*(1-$C$27)+$C$27*$C$28 -> 2687.25 | G45: =G37*(1-$C$27)+$C$27*$C$28 -> 2492.25 | H45: =H37*(1-$C$27)+$C$27*$C$28 -> 2297.25 | I45: =I37*(1-$C$27)+$C$27*$C$28 -> 2297.25 | J45: =J37*(1-$C$27)+$C$27*$C$28 -> 2297.25 | K45: =K37*(1-$C$27)+$C$27*$C$28 -> 2297.25 | L45: =L37*(1-$C$27)+$C$27*$C$28 -> 2297.25 | M45: =M37*(1-$C$27)+$C$27*$C$28 -> 2297.25 | ... AC45: =AC37*(1-$C$27)+$C$27*$C$28 -> 2297.25
B46: Copper revenue | C46: US$M | D46: =SUM(F46:AC46) -> 5211.0329 | F46: =F42*F44 -> 295.29972 | G46: =G42*G44 -> 270.69141 | H46: =H42*H44 -> 270.69141 | I46: =I42*I44 -> 270.69141 | J46: =J42*J44 -> 270.69141 | K46: =K42*K44 -> 270.69141 | L46: =L42*L44 -> 270.69141 | M46: =M42*M44 -> 270.69141 | ... AC46: =AC42*AC44 -> 0
B47: Gold revenue | C47: US$M | D47: =SUM(F47:AC47) -> 5832.5462 | F47: =F43*F45/1000 -> 322.88436 | G47: =G43*G45/1000 -> 299.45429 | H47: =H43*H45/1000 -> 303.62665 | I47: =I43*I45/1000 -> 303.62665 | J47: =J43*J45/1000 -> 303.62665 | K47: =K43*K45/1000 -> 303.62665 | L47: =L43*L45/1000 -> 303.62665 | M47: =M43*M45/1000 -> 303.62665 | ... AC47: =AC43*AC45/1000 -> 0
B48: Total revenue | C48: US$M | D48: =SUM(F48:AC48) -> 11043.579 | F48: =F46+F47 -> 618.18408 | G48: =G46+G47 -> 570.1457 | H48: =H46+H47 -> 574.31806 | I48: =I46+I47 -> 574.31806 | J48: =J46+J47 -> 574.31806 | K48: =K46+K47 -> 574.31806 | L48: =L46+L47 -> 574.31806 | M48: =M46+M47 -> 574.31806 | ... AC48: =AC46+AC47 -> 0
B49: TC/RC and freight | C49: US$M | D49: =SUM(F49:AC49) -> -550.00591 | F49: =-F42*$C$19 -> -26.346444 | G49: =-G42*$C$19 -> -26.346444 | H49: =-H42*$C$19 -> -28.981088 | I49: =-I42*$C$19 -> -28.981088 | J49: =-J42*$C$19 -> -28.981088 | K49: =-K42*$C$19 -> -28.981088 | L49: =-L42*$C$19 -> -28.981088 | M49: =-M42*$C$19 -> -28.981088 | ... AC49: =-AC42*$C$19 -> 0
B50: Royalties | C50: US$M | D50: =SUM(F50:AC50) -> 0 | F50: =-F48*$C$25 -> 0 | G50: =-G48*$C$25 -> 0 | H50: =-H48*$C$25 -> 0 | I50: =-I48*$C$25 -> 0 | J50: =-J48*$C$25 -> 0 | K50: =-K48*$C$25 -> 0 | L50: =-L48*$C$25 -> 0 | M50: =-M48*$C$25 -> 0 | ... AC50: =-AC48*$C$25 -> 0
B51: Site operating costs | C51: US$M | D51: =SUM(F51:AC51) -> -6059.232 | F51: =-F40*$C$18 -> -290.25 | G51: =-G40*$C$18 -> -290.25 | H51: =-H40*$C$18 -> -319.275 | I51: =-I40*$C$18 -> -319.275 | J51: =-J40*$C$18 -> -319.275 | K51: =-K40*$C$18 -> -319.275 | L51: =-L40*$C$18 -> -319.275 | M51: =-M40*$C$18 -> -319.275 | ... AC51: =-AC40*$C$18 -> 0
B52: Mine EBITDA | C52: US$M | D52: =SUM(F52:AC52) -> 4434.3412 | F52: =SUM(F48:F51) -> 301.58764 | G52: =SUM(G48:G51) -> 253.54926 | H52: =SUM(H48:H51) -> 226.06197 | I52: =SUM(I48:I51) -> 226.06197 | J52: =SUM(J48:J51) -> 226.06197 | K52: =SUM(K48:K51) -> 226.06197 | L52: =SUM(L48:L51) -> 226.06197 | M52: =SUM(M48:M51) -> 226.06197 | ... AC52: =SUM(AC48:AC51) -> 0
B53: Sustaining capex | C53: US$M | D53: =SUM(F53:AC53) -> -1800 | F53: =-IF(F40>0,$C$20,0) -> -90 | G53: =-IF(G40>0,$C$20,0) -> -90 | H53: =-IF(H40>0,$C$20,0) -> -90 | I53: =-IF(I40>0,$C$20,0) -> -90 | J53: =-IF(J40>0,$C$20,0) -> -90 | K53: =-IF(K40>0,$C$20,0) -> -90 | L53: =-IF(L40>0,$C$20,0) -> -90 | M53: =-IF(M40>0,$C$20,0) -> -90 | ... AC53: =-IF(AC40>0,$C$20,0) -> 0
B54: Growth capex | C54: US$M | D54: =SUM(F54:AC54) -> -186 | F54: =-IF(AND(F$34>=$C$22,F$34<$C$22+$C$23),$C$21/$C$23,0) -> -62 | G54: =-IF(AND(G$34>=$C$22,G$34<$C$22+$C$23),$C$21/$C$23,0) -> -62 | H54: =-IF(AND(H$34>=$C$22,H$34<$C$22+$C$23),$C$21/$C$23,0) -> -62 | I54: =-IF(AND(I$34>=$C$22,I$34<$C$22+$C$23),$C$21/$C$23,0) -> 0 | J54: =-IF(AND(J$34>=$C$22,J$34<$C$22+$C$23),$C$21/$C$23,0) -> 0 | K54: =-IF(AND(K$34>=$C$22,K$34<$C$22+$C$23),$C$21/$C$23,0) -> 0 | L54: =-IF(AND(L$34>=$C$22,L$34<$C$22+$C$23),$C$21/$C$23,0) -> 0 | M54: =-IF(AND(M$34>=$C$22,M$34<$C$22+$C$23),$C$21/$C$23,0) -> 0 | ... AC54: =-IF(AND(AC$34>=$C$22,AC$34<$C$22+$C$23),$C$21/$C$23,0) -> 0
B55: Closure and reclamation | C55: US$M | D55: =SUM(F55:AC55) -> -120 | F55: =0 -> 0 | G55: =-IF(AND(G40=0,F40>0),$C$24,0) -> 0 | H55: =-IF(AND(H40=0,G40>0),$C$24,0) -> 0 | I55: =-IF(AND(I40=0,H40>0),$C$24,0) -> 0 | J55: =-IF(AND(J40=0,I40>0),$C$24,0) -> 0 | K55: =-IF(AND(K40=0,J40>0),$C$24,0) -> 0 | L55: =-IF(AND(L40=0,K40>0),$C$24,0) -> 0 | M55: =-IF(AND(M40=0,L40>0),$C$24,0) -> 0 | N55: =-IF(AND(N40=0,M40>0),$C$24,0) -> 0 | ... AC55: =-IF(AND(AC40=0,AB40>0),$C$24,0) -> 0
B56: Cash taxes | C56: US$M | D56: =SUM(F56:AC56) -> -800.70093 | F56: =-MAX(0,(F52+F53+F54)*$C$26) -> -47.868044 | G56: =-MAX(0,(G52+G53+G54)*$C$26) -> -32.495763 | H56: =-MAX(0,(H52+H53+H54)*$C$26) -> -23.699831 | I56: =-MAX(0,(I52+I53+I54)*$C$26) -> -43.539831 | J56: =-MAX(0,(J52+J53+J54)*$C$26) -> -43.539831 | K56: =-MAX(0,(K52+K53+K54)*$C$26) -> -43.539831 | L56: =-MAX(0,(L52+L53+L54)*$C$26) -> -43.539831 | M56: =-MAX(0,(M52+M53+M54)*$C$26) -> -43.539831 | ... AC56: =-MAX(0,(AC52+AC53+AC54)*$C$26) -> 0
B57: Unlevered free cash flow | C57: US$M | D57: =SUM(F57:AC57) -> 1527.6403 | F57: =SUM(F52:F56) -> 101.71959 | G57: =SUM(G52:G56) -> 69.053497 | H57: =SUM(H52:H56) -> 50.36214 | I57: =SUM(I52:I56) -> 92.52214 | J57: =SUM(J52:J56) -> 92.52214 | K57: =SUM(K52:K56) -> 92.52214 | L57: =SUM(L52:L56) -> 92.52214 | M57: =SUM(M52:M56) -> 92.52214 | ... AC57: =SUM(AC52:AC56) -> 0
B58: Discount factor (mid-year) | F58: =1/(1+$C$31)^(F35-0.5) -> 0.96900317 | G58: =1/(1+$C$31)^(G35-0.5) -> 0.90986213 | H58: =1/(1+$C$31)^(H35-0.5) -> 0.85433064 | I58: =1/(1+$C$31)^(I35-0.5) -> 0.80218839 | J58: =1/(1+$C$31)^(J35-0.5) -> 0.75322854 | K58: =1/(1+$C$31)^(K35-0.5) -> 0.70725684 | L58: =1/(1+$C$31)^(L35-0.5) -> 0.66409093 | M58: =1/(1+$C$31)^(M35-0.5) -> 0.62355956 | ... AC58: =1/(1+$C$31)^(AC35-0.5) -> 0.22765868
B59: PV of free cash flow | C59: US$M | D59: =SUM(F59:AC59) -> 927.73859 | F59: =F57*F58 -> 98.566609 | G59: =G57*G58 -> 62.829162 | H59: =H57*H58 -> 43.025919 | I59: =I57*I58 -> 74.220186 | J59: =J57*J58 -> 69.690316 | K59: =K57*K58 -> 65.436916 | L59: =L57*L58 -> 61.443114 | M59: =M57*M58 -> 57.693065 | ... AC59: =AC57*AC58 -> 0
B61: Asset summary
B62: NPV (100% basis) | C62: =SUM(F59:AC59) -> 927.73859 | D62: US$M
B63: Attributable NAV | C63: =C62*$C$5 -> 927.73859 | D63: US$M
B64: Remaining mine life | C64: =COUNTIF(F40:AC40,">0") -> 20 | D64: years
B65: AISC 2027, by-product | C65: =IFERROR((-(F49+F50+F51+F53)-F46)/F43*1000,0) -> 926.28245 | D65: US$/oz Au
B66: AISC life of mine, by-product | C66: =IFERROR((-(D49+D50+D51+D53)-D46)/D43*1000,0) -> 1275.0347 | D66: US$/oz Au

Sheet Oksut
B1: Öksüt — asset NAV (CG, Türkiye)
B2: Reserve-constrained life-of-mine model. Blue = input (data/assets.csv), green = link, black = formula. US$M real unless noted.
B4: Input | C4: Value | D4: Unit | F4: Source / status
B5: Ownership | C5: 1 | D5: % | F5: Source IDs: CG-MRMR-2025;CG-Q2-2026 (see Sources tab)
B6: P&P reserve (at effective date) | C6: 15.355 | D6: Mt | F6: [verified] reserve_mt|au_gpt: Year-end 2025 P&P 15.4 Mt @ 1.02 g/t Au
B7: Depletion to 1 Jan 2027 | C7: 5 | D7: Mt | F7: [calibrated] nsr_royalty|opex_usd_t: Set so AISC lands in the US$1,850–1,950/oz 2026 guidance range (includes state royalty)
B8: Copper grade | C8: 0 | D8: % Cu
B9: Gold grade | C9: 1.02 | D9: g/t Au
B10: Copper recovery | C10: 0 | D10: %
B11: Gold recovery | C11: 0.78 | D11: %
B12: Copper payable | C12: 0 | D12: %
B13: Gold payable | C13: 0.999 | D13: %
B14: Throughput | C14: 4.5 | D14: Mtpa
B15: Throughput after expansion | C15: 4.5 | D15: Mtpa
B16: Expansion year | C16: 2027 | D16: year
B17: First production year | C17: 2027 | D17: year
B18: Site operating cost | C18: 36 | D18: US$/t milled
B19: TC/RC and freight | C19: 0 | D19: US$/lb Cu
... B30: Stream copper price received | C30: 0 | D30: % of spot
B31: Discount rate (real) | C31: =Inputs!$C$23 -> 0.05 | D31: Inputs tab
B34: US$M unless noted | C34: Unit | D34: LOM / NPV | F34: 2027 | G34: 2028 | H34: 2029 | I34: 2030 | J34: 2031 | K34: 2032 | L34: 2033 | M34: 2034 | N34: 2035 | O34: 2036 | P34: 2037 | Q34: 2038 | R34: 2039 | S34: 2040 | T34: 2041 | U34: 2042 | V34: 2043 | W34: 2044 | X34: 2045 | Y34: 2046 | Z34: 2047 | AA34: 2048 | AB34: 2049 | AC34: 2050
B35: Period | F35: =F$34-2027+1 -> 1 | G35: =G$34-2027+1 -> 2 | H35: =H$34-2027+1 -> 3 | I35: =I$34-2027+1 -> 4 | J35: =J$34-2027+1 -> 5 | K35: =K$34-2027+1 -> 6 | L35: =L$34-2027+1 -> 7 | M35: =M$34-2027+1 -> 8 | ... AC35: =AC$34-2027+1 -> 24
B36: Copper price | C36: US$/lb | F36: =Inputs!F$18 -> 6 | G36: =Inputs!G$18 -> 5.5 | H36: =Inputs!H$18 -> 5 | I36: =Inputs!I$18 -> 5 | J36: =Inputs!J$18 -> 5 | K36: =Inputs!K$18 -> 5 | L36: =Inputs!L$18 -> 5 | M36: =Inputs!M$18 -> 5 | ... AC36: =Inputs!AC$18 -> 5
B37: Gold price | C37: US$/oz | F37: =Inputs!F$19 -> 3900 | G37: =Inputs!G$19 -> 3600 | H37: =Inputs!H$19 -> 3300 | I37: =Inputs!I$19 -> 3300 | J37: =Inputs!J$19 -> 3300 | K37: =Inputs!K$19 -> 3300 | L37: =Inputs!L$19 -> 3300 | M37: =Inputs!M$19 -> 3300 | ... AC37: =Inputs!AC$19 -> 3300
B38: Mill capacity | C38: Mt | F38: =IF(F$34<$C$17,0,IF(F$34>=$C$16,$C$15,$C$14)) -> 4.5 | G38: =IF(G$34<$C$17,0,IF(G$34>=$C$16,$C$15,$C$14)) -> 4.5 | H38: =IF(H$34<$C$17,0,IF(H$34>=$C$16,$C$15,$C$14)) -> 4.5 | I38: =IF(I$34<$C$17,0,IF(I$34>=$C$16,$C$15,$C$14)) -> 4.5 | J38: =IF(J$34<$C$17,0,IF(J$34>=$C$16,$C$15,$C$14)) -> 4.5 | K38: =IF(K$34<$C$17,0,IF(K$34>=$C$16,$C$15,$C$14)) -> 4.5 | L38: =IF(L$34<$C$17,0,IF(L$34>=$C$16,$C$15,$C$14)) -> 4.5 | M38: =IF(M$34<$C$17,0,IF(M$34>=$C$16,$C$15,$C$14)) -> 4.5 | ... AC38: =IF(AC$34<$C$17,0,IF(AC$34>=$C$16,$C$15,$C$14)) -> 4.5
B39: Opening reserve | C39: Mt | F39: =$C$6-$C$7 -> 10.355 | G39: =F41 -> 5.855 | H39: =G41 -> 1.355 | I39: =H41 -> 0 | J39: =I41 -> 0 | K39: =J41 -> 0 | L39: =K41 -> 0 | M39: =L41 -> 0 | N39: =M41 -> 0 | ... AC39: =AB41 -> 0
B40: Ore processed | C40: Mt | D40: =SUM(F40:AC40) -> 10.355 | F40: =MAX(0,MIN(F38,F39)) -> 4.5 | G40: =MAX(0,MIN(G38,G39)) -> 4.5 | H40: =MAX(0,MIN(H38,H39)) -> 1.355 | I40: =MAX(0,MIN(I38,I39)) -> 0 | J40: =MAX(0,MIN(J38,J39)) -> 0 | K40: =MAX(0,MIN(K38,K39)) -> 0 | L40: =MAX(0,MIN(L38,L39)) -> 0 | M40: =MAX(0,MIN(M38,M39)) -> 0 | ... AC40: =MAX(0,MIN(AC38,AC39)) -> 0
B41: Closing reserve | C41: Mt | F41: =F39-F40 -> 5.855 | G41: =G39-G40 -> 1.355 | H41: =H39-H40 -> 0 | I41: =I39-I40 -> 0 | J41: =J39-J40 -> 0 | K41: =K39-K40 -> 0 | L41: =L39-L40 -> 0 | M41: =M39-M40 -> 0 | ... AC41: =AC39-AC40 -> 0
B42: Payable copper | C42: Mlb | D42: =SUM(F42:AC42) -> 0 | F42: =F40*$C$8*$C$10*$C$12*2204.62 -> 0 | G42: =G40*$C$8*$C$10*$C$12*2204.62 -> 0 | H42: =H40*$C$8*$C$10*$C$12*2204.62 -> 0 | I42: =I40*$C$8*$C$10*$C$12*2204.62 -> 0 | J42: =J40*$C$8*$C$10*$C$12*2204.62 -> 0 | K42: =K40*$C$8*$C$10*$C$12*2204.62 -> 0 | L42: =L40*$C$8*$C$10*$C$12*2204.62 -> 0 | M42: =M40*$C$8*$C$10*$C$12*2204.62 -> 0 | ... AC42: =AC40*$C$8*$C$10*$C$12*2204.62 -> 0
B43: Payable gold | C43: koz | D43: =SUM(F43:AC43) -> 264.60686 | F43: =F40*$C$9*$C$11*$C$13*1000/31.1035 -> 114.99091 | G43: =G40*$C$9*$C$11*$C$13*1000/31.1035 -> 114.99091 | H43: =H40*$C$9*$C$11*$C$13*1000/31.1035 -> 34.625041 | I43: =I40*$C$9*$C$11*$C$13*1000/31.1035 -> 0 | J43: =J40*$C$9*$C$11*$C$13*1000/31.1035 -> 0 | K43: =K40*$C$9*$C$11*$C$13*1000/31.1035 -> 0 | L43: =L40*$C$9*$C$11*$C$13*1000/31.1035 -> 0 | M43: =M40*$C$9*$C$11*$C$13*1000/31.1035 -> 0 | ... AC43: =AC40*$C$9*$C$11*$C$13*1000/31.1035 -> 0
B44: Realised copper price (after stream) | C44: US$/lb | F44: =F36*(1-$C$29)+F36*$C$29*$C$30 -> 6 | G44: =G36*(1-$C$29)+G36*$C$29*$C$30 -> 5.5 | H44: =H36*(1-$C$29)+H36*$C$29*$C$30 -> 5 | I44: =I36*(1-$C$29)+I36*$C$29*$C$30 -> 5 | J44: =J36*(1-$C$29)+J36*$C$29*$C$30 -> 5 | K44: =K36*(1-$C$29)+K36*$C$29*$C$30 -> 5 | L44: =L36*(1-$C$29)+L36*$C$29*$C$30 -> 5 | M44: =M36*(1-$C$29)+M36*$C$29*$C$30 -> 5 | ... AC44: =AC36*(1-$C$29)+AC36*$C$29*$C$30 -> 5
B45: Realised gold price (after stream) | C45: US$/oz | F45: =F37*(1-$C$27)+$C$27*$C$28 -> 3900 | G45: =G37*(1-$C$27)+$C$27*$C$28 -> 3600 | H45: =H37*(1-$C$27)+$C$27*$C$28 -> 3300 | I45: =I37*(1-$C$27)+$C$27*$C$28 -> 3300 | J45: =J37*(1-$C$27)+$C$27*$C$28 -> 3300 | K45: =K37*(1-$C$27)+$C$27*$C$28 -> 3300 | L45: =L37*(1-$C$27)+$C$27*$C$28 -> 3300 | M45: =M37*(1-$C$27)+$C$27*$C$28 -> 3300 | ... AC45: =AC37*(1-$C$27)+$C$27*$C$28 -> 3300
B46: Copper revenue | C46: US$M | D46: =SUM(F46:AC46) -> 0 | F46: =F42*F44 -> 0 | G46: =G42*G44 -> 0 | H46: =H42*H44 -> 0 | I46: =I42*I44 -> 0 | J46: =J42*J44 -> 0 | K46: =K42*K44 -> 0 | L46: =L42*L44 -> 0 | M46: =M42*M44 -> 0 | ... AC46: =AC42*AC44 -> 0
B47: Gold revenue | C47: US$M | D47: =SUM(F47:AC47) -> 976.69447 | F47: =F43*F45/1000 -> 448.46455 | G47: =G43*G45/1000 -> 413.96728 | H47: =H43*H45/1000 -> 114.26264 | I47: =I43*I45/1000 -> 0 | J47: =J43*J45/1000 -> 0 | K47: =K43*K45/1000 -> 0 | L47: =L43*L45/1000 -> 0 | M47: =M43*M45/1000 -> 0 | ... AC47: =AC43*AC45/1000 -> 0
B48: Total revenue | C48: US$M | D48: =SUM(F48:AC48) -> 976.69447 | F48: =F46+F47 -> 448.46455 | G48: =G46+G47 -> 413.96728 | H48: =H46+H47 -> 114.26264 | I48: =I46+I47 -> 0 | J48: =J46+J47 -> 0 | K48: =K46+K47 -> 0 | L48: =L46+L47 -> 0 | M48: =M46+M47 -> 0 | ... AC48: =AC46+AC47 -> 0
B49: TC/RC and freight | C49: US$M | D49: =SUM(F49:AC49) -> 0 | F49: =-F42*$C$19 -> 0 | G49: =-G42*$C$19 -> 0 | H49: =-H42*$C$19 -> 0 | I49: =-I42*$C$19 -> 0 | J49: =-J42*$C$19 -> 0 | K49: =-K42*$C$19 -> 0 | L49: =-L42*$C$19 -> 0 | M49: =-M42*$C$19 -> 0 | ... AC49: =-AC42*$C$19 -> 0
B50: Royalties | C50: US$M | D50: =SUM(F50:AC50) -> -78.135557 | F50: =-F48*$C$25 -> -35.877164 | G50: =-G48*$C$25 -> -33.117382 | H50: =-H48*$C$25 -> -9.1410108 | I50: =-I48*$C$25 -> 0 | J50: =-J48*$C$25 -> 0 | K50: =-K48*$C$25 -> 0 | L50: =-L48*$C$25 -> 0 | M50: =-M48*$C$25 -> 0 | ... AC50: =-AC48*$C$25 -> 0
B51: Site operating costs | C51: US$M | D51: =SUM(F51:AC51) -> -372.78 | F51: =-F40*$C$18 -> -162 | G51: =-G40*$C$18 -> -162 | H51: =-H40*$C$18 -> -48.78 | I51: =-I40*$C$18 -> 0 | J51: =-J40*$C$18 -> 0 | K51: =-K40*$C$18 -> 0 | L51: =-L40*$C$18 -> 0 | M51: =-M40*$C$18 -> 0 | ... AC51: =-AC40*$C$18 -> 0
B52: Mine EBITDA | C52: US$M | D52: =SUM(F52:AC52) -> 525.77891 | F52: =SUM(F48:F51) -> 250.58739 | G52: =SUM(G48:G51) -> 218.8499 | H52: =SUM(H48:H51) -> 56.341624 | I52: =SUM(I48:I51) -> 0 | J52: =SUM(J48:J51) -> 0 | K52: =SUM(K48:K51) -> 0 | L52: =SUM(L48:L51) -> 0 | M52: =SUM(M48:M51) -> 0 | ... AC52: =SUM(AC48:AC51) -> 0
B53: Sustaining capex | C53: US$M | D53: =SUM(F53:AC53) -> -60 | F53: =-IF(F40>0,$C$20,0) -> -20 | G53: =-IF(G40>0,$C$20,0) -> -20 | H53: =-IF(H40>0,$C$20,0) -> -20 | I53: =-IF(I40>0,$C$20,0) -> 0 | J53: =-IF(J40>0,$C$20,0) -> 0 | K53: =-IF(K40>0,$C$20,0) -> 0 | L53: =-IF(L40>0,$C$20,0) -> 0 | M53: =-IF(M40>0,$C$20,0) -> 0 | ... AC53: =-IF(AC40>0,$C$20,0) -> 0
B54: Growth capex | C54: US$M | D54: =SUM(F54:AC54) -> 0 | F54: =-IF(AND(F$34>=$C$22,F$34<$C$22+$C$23),$C$21/$C$23,0) -> 0 | G54: =-IF(AND(G$34>=$C$22,G$34<$C$22+$C$23),$C$21/$C$23,0) -> 0 | H54: =-IF(AND(H$34>=$C$22,H$34<$C$22+$C$23),$C$21/$C$23,0) -> 0 | I54: =-IF(AND(I$34>=$C$22,I$34<$C$22+$C$23),$C$21/$C$23,0) -> 0 | J54: =-IF(AND(J$34>=$C$22,J$34<$C$22+$C$23),$C$21/$C$23,0) -> 0 | K54: =-IF(AND(K$34>=$C$22,K$34<$C$22+$C$23),$C$21/$C$23,0) -> 0 | L54: =-IF(AND(L$34>=$C$22,L$34<$C$22+$C$23),$C$21/$C$23,0) -> 0 | M54: =-IF(AND(M$34>=$C$22,M$34<$C$22+$C$23),$C$21/$C$23,0) -> 0 | ... AC54: =-IF(AND(AC$34>=$C$22,AC$34<$C$22+$C$23),$C$21/$C$23,0) -> 0
B55: Closure and reclamation | C55: US$M | D55: =SUM(F55:AC55) -> -40 | F55: =0 -> 0 | G55: =-IF(AND(G40=0,F40>0),$C$24,0) -> 0 | H55: =-IF(AND(H40=0,G40>0),$C$24,0) -> 0 | I55: =-IF(AND(I40=0,H40>0),$C$24,0) -> -40 | J55: =-IF(AND(J40=0,I40>0),$C$24,0) -> 0 | K55: =-IF(AND(K40=0,J40>0),$C$24,0) -> 0 | L55: =-IF(AND(L40=0,K40>0),$C$24,0) -> 0 | M55: =-IF(AND(M40=0,L40>0),$C$24,0) -> 0 | N55: =-IF(AND(N40=0,M40>0),$C$24,0) -> 0 | ... AC55: =-IF(AND(AC40=0,AB40>0),$C$24,0) -> 0
B56: Cash taxes | C56: US$M | D56: =SUM(F56:AC56) -> -116.44473 | F56: =-MAX(0,(F52+F53+F54)*$C$26) -> -57.646847 | G56: =-MAX(0,(G52+G53+G54)*$C$26) -> -49.712474 | H56: =-MAX(0,(H52+H53+H54)*$C$26) -> -9.0854061 | I56: =-MAX(0,(I52+I53+I54)*$C$26) -> 0 | J56: =-MAX(0,(J52+J53+J54)*$C$26) -> 0 | K56: =-MAX(0,(K52+K53+K54)*$C$26) -> 0 | L56: =-MAX(0,(L52+L53+L54)*$C$26) -> 0 | M56: =-MAX(0,(M52+M53+M54)*$C$26) -> 0 | ... AC56: =-MAX(0,(AC52+AC53+AC54)*$C$26) -> 0
B57: Unlevered free cash flow | C57: US$M | D57: =SUM(F57:AC57) -> 309.33418 | F57: =SUM(F52:F56) -> 172.94054 | G57: =SUM(G52:G56) -> 149.13742 | H57: =SUM(H52:H56) -> 27.256218 | I57: =SUM(I52:I56) -> -40 | J57: =SUM(J52:J56) -> 0 | K57: =SUM(K52:K56) -> 0 | L57: =SUM(L52:L56) -> 0 | M57: =SUM(M52:M56) -> 0 | ... AC57: =SUM(AC52:AC56) -> 0
B58: Discount factor (mid-year) | F58: =1/(1+$C$31)^(F35-0.5) -> 0.97590007 | G58: =1/(1+$C$31)^(G35-0.5) -> 0.92942864 | H58: =1/(1+$C$31)^(H35-0.5) -> 0.88517013 | I58: =1/(1+$C$31)^(I35-0.5) -> 0.84301918 | J58: =1/(1+$C$31)^(J35-0.5) -> 0.80287541 | K58: =1/(1+$C$31)^(K35-0.5) -> 0.76464324 | L58: =1/(1+$C$31)^(L35-0.5) -> 0.72823166 | M58: =1/(1+$C$31)^(M35-0.5) -> 0.69355396 | ... AC58: =1/(1+$C$31)^(AC35-0.5) -> 0.31772506
B59: PV of free cash flow | C59: US$M | D59: =SUM(F59:AC59) -> 297.7909 | F59: =F57*F58 -> 168.77269 | G59: =G57*G58 -> 138.61259 | H59: =H57*H58 -> 24.12639 | I59: =I57*I58 -> -33.720767 | J59: =J57*J58 -> 0 | K59: =K57*K58 -> 0 | L59: =L57*L58 -> 0 | M59: =M57*M58 -> 0 | ... AC59: =AC57*AC58 -> 0
B61: Asset summary
B62: NPV (100% basis) | C62: =SUM(F59:AC59) -> 297.7909 | D62: US$M
B63: Attributable NAV | C63: =C62*$C$5 -> 297.7909 | D63: US$M
B64: Remaining mine life | C64: =COUNTIF(F40:AC40,">0") -> 3 | D64: years
B65: AISC 2027, by-product | C65: =IFERROR((-(F49+F50+F51+F53)-F46)/F43*1000,0) -> 1894.7338 | D65: US$/oz Au
B66: AISC life of mine, by-product | C66: =IFERROR((-(D49+D50+D51+D53)-D46)/D43*1000,0) -> 1930.8477 | D66: US$/oz Au

Sheet Goldfield
B1: Goldfield — asset NAV (CG, US (Nevada))
B2: Reserve-constrained life-of-mine model. Blue = input (data/assets.csv), green = link, black = formula. US$M real unless noted.
B4: Input | C4: Value | D4: Unit | F4: Source / status
B5: Ownership | C5: 1 | D5: % | F5: Source IDs: CG-MRMR-2025 (see Sources tab)
B6: P&P reserve (at effective date) | C6: 33.348 | D6: Mt | F6: [verified] reserve_mt|au_gpt: Year-end 2025 P&P 33.3 Mt @ 0.66 g/t Au (maiden reserve)
B7: Depletion to 1 Jan 2027 | C7: 0 | D7: Mt | F7: [estimate] growth_capex_usd_m|start_year|throughput_mtpa: Development schedule and capex are analyst estimates pending a construction decision
B8: Copper grade | C8: 0 | D8: % Cu
B9: Gold grade | C9: 0.66 | D9: g/t Au
B10: Copper recovery | C10: 0 | D10: %
B11: Gold recovery | C11: 0.72 | D11: %
B12: Copper payable | C12: 0 | D12: %
B13: Gold payable | C13: 0.999 | D13: %
B14: Throughput | C14: 4.5 | D14: Mtpa
B15: Throughput after expansion | C15: 4.5 | D15: Mtpa
B16: Expansion year | C16: 2029 | D16: year
B17: First production year | C17: 2029 | D17: year
B18: Site operating cost | C18: 19 | D18: US$/t milled
B19: TC/RC and freight | C19: 0 | D19: US$/lb Cu
... B30: Stream copper price received | C30: 0 | D30: % of spot
B31: Discount rate (real) | C31: =Inputs!$C$24 -> 0.05 | D31: Inputs tab
B34: US$M unless noted | C34: Unit | D34: LOM / NPV | F34: 2027 | G34: 2028 | H34: 2029 | I34: 2030 | J34: 2031 | K34: 2032 | L34: 2033 | M34: 2034 | N34: 2035 | O34: 2036 | P34: 2037 | Q34: 2038 | R34: 2039 | S34: 2040 | T34: 2041 | U34: 2042 | V34: 2043 | W34: 2044 | X34: 2045 | Y34: 2046 | Z34: 2047 | AA34: 2048 | AB34: 2049 | AC34: 2050
B35: Period | F35: =F$34-2027+1 -> 1 | G35: =G$34-2027+1 -> 2 | H35: =H$34-2027+1 -> 3 | I35: =I$34-2027+1 -> 4 | J35: =J$34-2027+1 -> 5 | K35: =K$34-2027+1 -> 6 | L35: =L$34-2027+1 -> 7 | M35: =M$34-2027+1 -> 8 | ... AC35: =AC$34-2027+1 -> 24
B36: Copper price | C36: US$/lb | F36: =Inputs!F$18 -> 6 | G36: =Inputs!G$18 -> 5.5 | H36: =Inputs!H$18 -> 5 | I36: =Inputs!I$18 -> 5 | J36: =Inputs!J$18 -> 5 | K36: =Inputs!K$18 -> 5 | L36: =Inputs!L$18 -> 5 | M36: =Inputs!M$18 -> 5 | ... AC36: =Inputs!AC$18 -> 5
B37: Gold price | C37: US$/oz | F37: =Inputs!F$19 -> 3900 | G37: =Inputs!G$19 -> 3600 | H37: =Inputs!H$19 -> 3300 | I37: =Inputs!I$19 -> 3300 | J37: =Inputs!J$19 -> 3300 | K37: =Inputs!K$19 -> 3300 | L37: =Inputs!L$19 -> 3300 | M37: =Inputs!M$19 -> 3300 | ... AC37: =Inputs!AC$19 -> 3300
B38: Mill capacity | C38: Mt | F38: =IF(F$34<$C$17,0,IF(F$34>=$C$16,$C$15,$C$14)) -> 0 | G38: =IF(G$34<$C$17,0,IF(G$34>=$C$16,$C$15,$C$14)) -> 0 | H38: =IF(H$34<$C$17,0,IF(H$34>=$C$16,$C$15,$C$14)) -> 4.5 | I38: =IF(I$34<$C$17,0,IF(I$34>=$C$16,$C$15,$C$14)) -> 4.5 | J38: =IF(J$34<$C$17,0,IF(J$34>=$C$16,$C$15,$C$14)) -> 4.5 | K38: =IF(K$34<$C$17,0,IF(K$34>=$C$16,$C$15,$C$14)) -> 4.5 | L38: =IF(L$34<$C$17,0,IF(L$34>=$C$16,$C$15,$C$14)) -> 4.5 | M38: =IF(M$34<$C$17,0,IF(M$34>=$C$16,$C$15,$C$14)) -> 4.5 | ... AC38: =IF(AC$34<$C$17,0,IF(AC$34>=$C$16,$C$15,$C$14)) -> 4.5
B39: Opening reserve | C39: Mt | F39: =$C$6-$C$7 -> 33.348 | G39: =F41 -> 33.348 | H39: =G41 -> 33.348 | I39: =H41 -> 28.848 | J39: =I41 -> 24.348 | K39: =J41 -> 19.848 | L39: =K41 -> 15.348 | M39: =L41 -> 10.848 | N39: =M41 -> 6.348 | ... AC39: =AB41 -> 0
B40: Ore processed | C40: Mt | D40: =SUM(F40:AC40) -> 33.348 | F40: =MAX(0,MIN(F38,F39)) -> 0 | G40: =MAX(0,MIN(G38,G39)) -> 0 | H40: =MAX(0,MIN(H38,H39)) -> 4.5 | I40: =MAX(0,MIN(I38,I39)) -> 4.5 | J40: =MAX(0,MIN(J38,J39)) -> 4.5 | K40: =MAX(0,MIN(K38,K39)) -> 4.5 | L40: =MAX(0,MIN(L38,L39)) -> 4.5 | M40: =MAX(0,MIN(M38,M39)) -> 4.5 | ... AC40: =MAX(0,MIN(AC38,AC39)) -> 0
B41: Closing reserve | C41: Mt | F41: =F39-F40 -> 33.348 | G41: =G39-G40 -> 33.348 | H41: =H39-H40 -> 28.848 | I41: =I39-I40 -> 24.348 | J41: =J39-J40 -> 19.848 | K41: =K39-K40 -> 15.348 | L41: =L39-L40 -> 10.848 | M41: =M39-M40 -> 6.348 | ... AC41: =AC39-AC40 -> 0
B42: Payable copper | C42: Mlb | D42: =SUM(F42:AC42) -> 0 | F42: =F40*$C$8*$C$10*$C$12*2204.62 -> 0 | G42: =G40*$C$8*$C$10*$C$12*2204.62 -> 0 | H42: =H40*$C$8*$C$10*$C$12*2204.62 -> 0 | I42: =I40*$C$8*$C$10*$C$12*2204.62 -> 0 | J42: =J40*$C$8*$C$10*$C$12*2204.62 -> 0 | K42: =K40*$C$8*$C$10*$C$12*2204.62 -> 0 | L42: =L40*$C$8*$C$10*$C$12*2204.62 -> 0 | M42: =M40*$C$8*$C$10*$C$12*2204.62 -> 0 | ... AC42: =AC40*$C$8*$C$10*$C$12*2204.62 -> 0
B43: Payable gold | C43: koz | D43: =SUM(F43:AC43) -> 508.98203 | F43: =F40*$C$9*$C$11*$C$13*1000/31.1035 -> 0 | G43: =G40*$C$9*$C$11*$C$13*1000/31.1035 -> 0 | H43: =H40*$C$9*$C$11*$C$13*1000/31.1035 -> 68.682354 | I43: =I40*$C$9*$C$11*$C$13*1000/31.1035 -> 68.682354 | J43: =J40*$C$9*$C$11*$C$13*1000/31.1035 -> 68.682354 | K43: =K40*$C$9*$C$11*$C$13*1000/31.1035 -> 68.682354 | L43: =L40*$C$9*$C$11*$C$13*1000/31.1035 -> 68.682354 | M43: =M40*$C$9*$C$11*$C$13*1000/31.1035 -> 68.682354 | ... AC43: =AC40*$C$9*$C$11*$C$13*1000/31.1035 -> 0
B44: Realised copper price (after stream) | C44: US$/lb | F44: =F36*(1-$C$29)+F36*$C$29*$C$30 -> 6 | G44: =G36*(1-$C$29)+G36*$C$29*$C$30 -> 5.5 | H44: =H36*(1-$C$29)+H36*$C$29*$C$30 -> 5 | I44: =I36*(1-$C$29)+I36*$C$29*$C$30 -> 5 | J44: =J36*(1-$C$29)+J36*$C$29*$C$30 -> 5 | K44: =K36*(1-$C$29)+K36*$C$29*$C$30 -> 5 | L44: =L36*(1-$C$29)+L36*$C$29*$C$30 -> 5 | M44: =M36*(1-$C$29)+M36*$C$29*$C$30 -> 5 | ... AC44: =AC36*(1-$C$29)+AC36*$C$29*$C$30 -> 5
B45: Realised gold price (after stream) | C45: US$/oz | F45: =F37*(1-$C$27)+$C$27*$C$28 -> 3900 | G45: =G37*(1-$C$27)+$C$27*$C$28 -> 3600 | H45: =H37*(1-$C$27)+$C$27*$C$28 -> 3300 | I45: =I37*(1-$C$27)+$C$27*$C$28 -> 3300 | J45: =J37*(1-$C$27)+$C$27*$C$28 -> 3300 | K45: =K37*(1-$C$27)+$C$27*$C$28 -> 3300 | L45: =L37*(1-$C$27)+$C$27*$C$28 -> 3300 | M45: =M37*(1-$C$27)+$C$27*$C$28 -> 3300 | ... AC45: =AC37*(1-$C$27)+$C$27*$C$28 -> 3300
B46: Copper revenue | C46: US$M | D46: =SUM(F46:AC46) -> 0 | F46: =F42*F44 -> 0 | G46: =G42*G44 -> 0 | H46: =H42*H44 -> 0 | I46: =I42*I44 -> 0 | J46: =J42*J44 -> 0 | K46: =K42*K44 -> 0 | L46: =L42*L44 -> 0 | M46: =M42*M44 -> 0 | ... AC46: =AC42*AC44 -> 0
B47: Gold revenue | C47: US$M | D47: =SUM(F47:AC47) -> 1679.6407 | F47: =F43*F45/1000 -> 0 | G47: =G43*G45/1000 -> 0 | H47: =H43*H45/1000 -> 226.65177 | I47: =I43*I45/1000 -> 226.65177 | J47: =J43*J45/1000 -> 226.65177 | K47: =K43*K45/1000 -> 226.65177 | L47: =L43*L45/1000 -> 226.65177 | M47: =M43*M45/1000 -> 226.65177 | ... AC47: =AC43*AC45/1000 -> 0
B48: Total revenue | C48: US$M | D48: =SUM(F48:AC48) -> 1679.6407 | F48: =F46+F47 -> 0 | G48: =G46+G47 -> 0 | H48: =H46+H47 -> 226.65177 | I48: =I46+I47 -> 226.65177 | J48: =J46+J47 -> 226.65177 | K48: =K46+K47 -> 226.65177 | L48: =L46+L47 -> 226.65177 | M48: =M46+M47 -> 226.65177 | ... AC48: =AC46+AC47 -> 0
B49: TC/RC and freight | C49: US$M | D49: =SUM(F49:AC49) -> 0 | F49: =-F42*$C$19 -> 0 | G49: =-G42*$C$19 -> 0 | H49: =-H42*$C$19 -> 0 | I49: =-I42*$C$19 -> 0 | J49: =-J42*$C$19 -> 0 | K49: =-K42*$C$19 -> 0 | L49: =-L42*$C$19 -> 0 | M49: =-M42*$C$19 -> 0 | ... AC49: =-AC42*$C$19 -> 0
B50: Royalties | C50: US$M | D50: =SUM(F50:AC50) -> -41.991018 | F50: =-F48*$C$25 -> 0 | G50: =-G48*$C$25 -> 0 | H50: =-H48*$C$25 -> -5.6662942 | I50: =-I48*$C$25 -> -5.6662942 | J50: =-J48*$C$25 -> -5.6662942 | K50: =-K48*$C$25 -> -5.6662942 | L50: =-L48*$C$25 -> -5.6662942 | M50: =-M48*$C$25 -> -5.6662942 | ... AC50: =-AC48*$C$25 -> 0
B51: Site operating costs | C51: US$M | D51: =SUM(F51:AC51) -> -633.612 | F51: =-F40*$C$18 -> 0 | G51: =-G40*$C$18 -> 0 | H51: =-H40*$C$18 -> -85.5 | I51: =-I40*$C$18 -> -85.5 | J51: =-J40*$C$18 -> -85.5 | K51: =-K40*$C$18 -> -85.5 | L51: =-L40*$C$18 -> -85.5 | M51: =-M40*$C$18 -> -85.5 | ... AC51: =-AC40*$C$18 -> 0
B52: Mine EBITDA | C52: US$M | D52: =SUM(F52:AC52) -> 1004.0377 | F52: =SUM(F48:F51) -> 0 | G52: =SUM(G48:G51) -> 0 | H52: =SUM(H48:H51) -> 135.48547 | I52: =SUM(I48:I51) -> 135.48547 | J52: =SUM(J48:J51) -> 135.48547 | K52: =SUM(K48:K51) -> 135.48547 | L52: =SUM(L48:L51) -> 135.48547 | M52: =SUM(M48:M51) -> 135.48547 | ... AC52: =SUM(AC48:AC51) -> 0
B53: Sustaining capex | C53: US$M | D53: =SUM(F53:AC53) -> -120 | F53: =-IF(F40>0,$C$20,0) -> 0 | G53: =-IF(G40>0,$C$20,0) -> 0 | H53: =-IF(H40>0,$C$20,0) -> -15 | I53: =-IF(I40>0,$C$20,0) -> -15 | J53: =-IF(J40>0,$C$20,0) -> -15 | K53: =-IF(K40>0,$C$20,0) -> -15 | L53: =-IF(L40>0,$C$20,0) -> -15 | M53: =-IF(M40>0,$C$20,0) -> -15 | ... AC53: =-IF(AC40>0,$C$20,0) -> 0
B54: Growth capex | C54: US$M | D54: =SUM(F54:AC54) -> -260 | F54: =-IF(AND(F$34>=$C$22,F$34<$C$22+$C$23),$C$21/$C$23,0) -> -130 | G54: =-IF(AND(G$34>=$C$22,G$34<$C$22+$C$23),$C$21/$C$23,0) -> -130 | H54: =-IF(AND(H$34>=$C$22,H$34<$C$22+$C$23),$C$21/$C$23,0) -> 0 | I54: =-IF(AND(I$34>=$C$22,I$34<$C$22+$C$23),$C$21/$C$23,0) -> 0 | J54: =-IF(AND(J$34>=$C$22,J$34<$C$22+$C$23),$C$21/$C$23,0) -> 0 | K54: =-IF(AND(K$34>=$C$22,K$34<$C$22+$C$23),$C$21/$C$23,0) -> 0 | L54: =-IF(AND(L$34>=$C$22,L$34<$C$22+$C$23),$C$21/$C$23,0) -> 0 | M54: =-IF(AND(M$34>=$C$22,M$34<$C$22+$C$23),$C$21/$C$23,0) -> 0 | ... AC54: =-IF(AND(AC$34>=$C$22,AC$34<$C$22+$C$23),$C$21/$C$23,0) -> 0
B55: Closure and reclamation | C55: US$M | D55: =SUM(F55:AC55) -> -30 | F55: =0 -> 0 | G55: =-IF(AND(G40=0,F40>0),$C$24,0) -> 0 | H55: =-IF(AND(H40=0,G40>0),$C$24,0) -> 0 | I55: =-IF(AND(I40=0,H40>0),$C$24,0) -> 0 | J55: =-IF(AND(J40=0,I40>0),$C$24,0) -> 0 | K55: =-IF(AND(K40=0,J40>0),$C$24,0) -> 0 | L55: =-IF(AND(L40=0,K40>0),$C$24,0) -> 0 | M55: =-IF(AND(M40=0,L40>0),$C$24,0) -> 0 | N55: =-IF(AND(N40=0,M40>0),$C$24,0) -> 0 | ... AC55: =-IF(AND(AC40=0,AB40>0),$C$24,0) -> 0
B56: Cash taxes | C56: US$M | D56: =SUM(F56:AC56) -> -221.00942 | F56: =-MAX(0,(F52+F53+F54)*$C$26) -> 0 | G56: =-MAX(0,(G52+G53+G54)*$C$26) -> 0 | H56: =-MAX(0,(H52+H53+H54)*$C$26) -> -30.121369 | I56: =-MAX(0,(I52+I53+I54)*$C$26) -> -30.121369 | J56: =-MAX(0,(J52+J53+J54)*$C$26) -> -30.121369 | K56: =-MAX(0,(K52+K53+K54)*$C$26) -> -30.121369 | L56: =-MAX(0,(L52+L53+L54)*$C$26) -> -30.121369 | M56: =-MAX(0,(M52+M53+M54)*$C$26) -> -30.121369 | ... AC56: =-MAX(0,(AC52+AC53+AC54)*$C$26) -> 0
B57: Unlevered free cash flow | C57: US$M | D57: =SUM(F57:AC57) -> 373.02827 | F57: =SUM(F52:F56) -> -130 | G57: =SUM(G52:G56) -> -130 | H57: =SUM(H52:H56) -> 90.364106 | I57: =SUM(I52:I56) -> 90.364106 | J57: =SUM(J52:J56) -> 90.364106 | K57: =SUM(K52:K56) -> 90.364106 | L57: =SUM(L52:L56) -> 90.364106 | M57: =SUM(M52:M56) -> 90.364106 | ... AC57: =SUM(AC52:AC56) -> 0
B58: Discount factor (mid-year) | F58: =1/(1+$C$31)^(F35-0.5) -> 0.97590007 | G58: =1/(1+$C$31)^(G35-0.5) -> 0.92942864 | H58: =1/(1+$C$31)^(H35-0.5) -> 0.88517013 | I58: =1/(1+$C$31)^(I35-0.5) -> 0.84301918 | J58: =1/(1+$C$31)^(J35-0.5) -> 0.80287541 | K58: =1/(1+$C$31)^(K35-0.5) -> 0.76464324 | L58: =1/(1+$C$31)^(L35-0.5) -> 0.72823166 | M58: =1/(1+$C$31)^(M35-0.5) -> 0.69355396 | ... AC58: =1/(1+$C$31)^(AC35-0.5) -> 0.31772506
B59: PV of free cash flow | C59: US$M | D59: =SUM(F59:AC59) -> 239.48767 | F59: =F57*F58 -> -126.86701 | G59: =G57*G58 -> -120.82572 | H59: =H57*H58 -> 79.987608 | I59: =I57*I58 -> 76.178674 | J59: =J57*J58 -> 72.551118 | K59: =K57*K58 -> 69.096303 | L59: =L57*L58 -> 65.806003 | M59: =M57*M58 -> 62.672384 | ... AC59: =AC57*AC58 -> 0
B61: Asset summary
B62: NPV (100% basis) | C62: =SUM(F59:AC59) -> 239.48767 | D62: US$M
B63: Attributable NAV | C63: =C62*$C$5 -> 239.48767 | D63: US$M
B64: Remaining mine life | C64: =COUNTIF(F40:AC40,">0") -> 8 | D64: years
B65: AISC 2027, by-product | C65: =IFERROR((-(F49+F50+F51+F53)-F46)/F43*1000,0) -> 0 | D65: US$/oz Au
B66: AISC life of mine, by-product | C66: =IFERROR((-(D49+D50+D51+D53)-D46)/D43*1000,0) -> 1563.1259 | D66: US$/oz Au

Sheet Caraiba
B1: Caraíba — asset NAV (ERO, Brazil (Bahia))
B2: Reserve-constrained life-of-mine model. Blue = input (data/assets.csv), green = link, black = formula. US$M real unless noted.
B4: Input | C4: Value | D4: Unit | F4: Source / status
B5: Ownership | C5: 1 | D5: % | F5: Source IDs: ERO-CARAIBA-OPS;ERO-MDA-2025Q4;ERO-AIF-2025 (see Sources tab)
B6: P&P reserve (at effective date) | C6: 73.058 | D6: Mt | F6: [verified] reserve_mt|cu_grade_pct: Dec 2024 P&P: UG 30.9 Mt @ 1.38% + OP 42.2 Mt @ 0.54% = 73.1 Mt @ 0.90% Cu
B7: Depletion to 1 Jan 2027 | C7: 3.9 | D7: Mt | F7: [estimate] depleted_mt: 2025 processed 3.66 Mt (verified); 2026 assumed ~3.9 Mt; 2025 depletion netted against grade conservatism
B8: Copper grade | C8: 0.00895 | D8: % Cu | F8: [calibrated] opex_usd_t|tcrc_usd_lb: Set so C1 lands near the US$2.30–2.50/lb 2026 guidance
B9: Gold grade | C9: 0 | D9: g/t Au | F9: [calibrated] sustaining_usd_m: Set so AISC lands near US$3.25/lb (C1 plus sustaining capex and royalties)
B10: Copper recovery | C10: 0.91 | D10: %
B11: Gold recovery | C11: 0 | D11: %
B12: Copper payable | C12: 0.965 | D12: %
B13: Gold payable | C13: 0 | D13: %
B14: Throughput | C14: 4.2 | D14: Mtpa
B15: Throughput after expansion | C15: 4.2 | D15: Mtpa
B16: Expansion year | C16: 2027 | D16: year
B17: First production year | C17: 2027 | D17: year
B18: Site operating cost | C18: 37 | D18: US$/t milled
B19: TC/RC and freight | C19: 0.35 | D19: US$/lb Cu
B20: Sustaining capex | C20: 55 | D20: US$M/yr
B21: Growth capex (total) | C21: 60 | D21: US$M
... B30: Stream copper price received | C30: 0 | D30: % of spot
B31: Discount rate (real) | C31: =Inputs!$C$25 -> 0.08 | D31: Inputs tab
B34: US$M unless noted | C34: Unit | D34: LOM / NPV | F34: 2027 | G34: 2028 | H34: 2029 | I34: 2030 | J34: 2031 | K34: 2032 | L34: 2033 | M34: 2034 | N34: 2035 | O34: 2036 | P34: 2037 | Q34: 2038 | R34: 2039 | S34: 2040 | T34: 2041 | U34: 2042 | V34: 2043 | W34: 2044 | X34: 2045 | Y34: 2046 | Z34: 2047 | AA34: 2048 | AB34: 2049 | AC34: 2050
B35: Period | F35: =F$34-2027+1 -> 1 | G35: =G$34-2027+1 -> 2 | H35: =H$34-2027+1 -> 3 | I35: =I$34-2027+1 -> 4 | J35: =J$34-2027+1 -> 5 | K35: =K$34-2027+1 -> 6 | L35: =L$34-2027+1 -> 7 | M35: =M$34-2027+1 -> 8 | ... AC35: =AC$34-2027+1 -> 24
B36: Copper price | C36: US$/lb | F36: =Inputs!F$18 -> 6 | G36: =Inputs!G$18 -> 5.5 | H36: =Inputs!H$18 -> 5 | I36: =Inputs!I$18 -> 5 | J36: =Inputs!J$18 -> 5 | K36: =Inputs!K$18 -> 5 | L36: =Inputs!L$18 -> 5 | M36: =Inputs!M$18 -> 5 | ... AC36: =Inputs!AC$18 -> 5
B37: Gold price | C37: US$/oz | F37: =Inputs!F$19 -> 3900 | G37: =Inputs!G$19 -> 3600 | H37: =Inputs!H$19 -> 3300 | I37: =Inputs!I$19 -> 3300 | J37: =Inputs!J$19 -> 3300 | K37: =Inputs!K$19 -> 3300 | L37: =Inputs!L$19 -> 3300 | M37: =Inputs!M$19 -> 3300 | ... AC37: =Inputs!AC$19 -> 3300
B38: Mill capacity | C38: Mt | F38: =IF(F$34<$C$17,0,IF(F$34>=$C$16,$C$15,$C$14)) -> 4.2 | G38: =IF(G$34<$C$17,0,IF(G$34>=$C$16,$C$15,$C$14)) -> 4.2 | H38: =IF(H$34<$C$17,0,IF(H$34>=$C$16,$C$15,$C$14)) -> 4.2 | I38: =IF(I$34<$C$17,0,IF(I$34>=$C$16,$C$15,$C$14)) -> 4.2 | J38: =IF(J$34<$C$17,0,IF(J$34>=$C$16,$C$15,$C$14)) -> 4.2 | K38: =IF(K$34<$C$17,0,IF(K$34>=$C$16,$C$15,$C$14)) -> 4.2 | L38: =IF(L$34<$C$17,0,IF(L$34>=$C$16,$C$15,$C$14)) -> 4.2 | M38: =IF(M$34<$C$17,0,IF(M$34>=$C$16,$C$15,$C$14)) -> 4.2 | ... AC38: =IF(AC$34<$C$17,0,IF(AC$34>=$C$16,$C$15,$C$14)) -> 4.2
B39: Opening reserve | C39: Mt | F39: =$C$6-$C$7 -> 69.158 | G39: =F41 -> 64.958 | H39: =G41 -> 60.758 | I39: =H41 -> 56.558 | J39: =I41 -> 52.358 | K39: =J41 -> 48.158 | L39: =K41 -> 43.958 | M39: =L41 -> 39.758 | N39: =M41 -> 35.558 | ... AC39: =AB41 -> 0
B40: Ore processed | C40: Mt | D40: =SUM(F40:AC40) -> 69.158 | F40: =MAX(0,MIN(F38,F39)) -> 4.2 | G40: =MAX(0,MIN(G38,G39)) -> 4.2 | H40: =MAX(0,MIN(H38,H39)) -> 4.2 | I40: =MAX(0,MIN(I38,I39)) -> 4.2 | J40: =MAX(0,MIN(J38,J39)) -> 4.2 | K40: =MAX(0,MIN(K38,K39)) -> 4.2 | L40: =MAX(0,MIN(L38,L39)) -> 4.2 | M40: =MAX(0,MIN(M38,M39)) -> 4.2 | ... AC40: =MAX(0,MIN(AC38,AC39)) -> 0
B41: Closing reserve | C41: Mt | F41: =F39-F40 -> 64.958 | G41: =G39-G40 -> 60.758 | H41: =H39-H40 -> 56.558 | I41: =I39-I40 -> 52.358 | J41: =J39-J40 -> 48.158 | K41: =K39-K40 -> 43.958 | L41: =L39-L40 -> 39.758 | M41: =M39-M40 -> 35.558 | ... AC41: =AC39-AC40 -> 0
B42: Payable copper | C42: Mlb | D42: =SUM(F42:AC42) -> 1198.3065 | F42: =F40*$C$8*$C$10*$C$12*2204.62 -> 72.773753 | G42: =G40*$C$8*$C$10*$C$12*2204.62 -> 72.773753 | H42: =H40*$C$8*$C$10*$C$12*2204.62 -> 72.773753 | I42: =I40*$C$8*$C$10*$C$12*2204.62 -> 72.773753 | J42: =J40*$C$8*$C$10*$C$12*2204.62 -> 72.773753 | K42: =K40*$C$8*$C$10*$C$12*2204.62 -> 72.773753 | L42: =L40*$C$8*$C$10*$C$12*2204.62 -> 72.773753 | M42: =M40*$C$8*$C$10*$C$12*2204.62 -> 72.773753 | ... AC42: =AC40*$C$8*$C$10*$C$12*2204.62 -> 0
B43: Payable gold | C43: koz | D43: =SUM(F43:AC43) -> 0 | F43: =F40*$C$9*$C$11*$C$13*1000/31.1035 -> 0 | G43: =G40*$C$9*$C$11*$C$13*1000/31.1035 -> 0 | H43: =H40*$C$9*$C$11*$C$13*1000/31.1035 -> 0 | I43: =I40*$C$9*$C$11*$C$13*1000/31.1035 -> 0 | J43: =J40*$C$9*$C$11*$C$13*1000/31.1035 -> 0 | K43: =K40*$C$9*$C$11*$C$13*1000/31.1035 -> 0 | L43: =L40*$C$9*$C$11*$C$13*1000/31.1035 -> 0 | M43: =M40*$C$9*$C$11*$C$13*1000/31.1035 -> 0 | ... AC43: =AC40*$C$9*$C$11*$C$13*1000/31.1035 -> 0
B44: Realised copper price (after stream) | C44: US$/lb | F44: =F36*(1-$C$29)+F36*$C$29*$C$30 -> 6 | G44: =G36*(1-$C$29)+G36*$C$29*$C$30 -> 5.5 | H44: =H36*(1-$C$29)+H36*$C$29*$C$30 -> 5 | I44: =I36*(1-$C$29)+I36*$C$29*$C$30 -> 5 | J44: =J36*(1-$C$29)+J36*$C$29*$C$30 -> 5 | K44: =K36*(1-$C$29)+K36*$C$29*$C$30 -> 5 | L44: =L36*(1-$C$29)+L36*$C$29*$C$30 -> 5 | M44: =M36*(1-$C$29)+M36*$C$29*$C$30 -> 5 | ... AC44: =AC36*(1-$C$29)+AC36*$C$29*$C$30 -> 5
B45: Realised gold price (after stream) | C45: US$/oz | F45: =F37*(1-$C$27)+$C$27*$C$28 -> 3900 | G45: =G37*(1-$C$27)+$C$27*$C$28 -> 3600 | H45: =H37*(1-$C$27)+$C$27*$C$28 -> 3300 | I45: =I37*(1-$C$27)+$C$27*$C$28 -> 3300 | J45: =J37*(1-$C$27)+$C$27*$C$28 -> 3300 | K45: =K37*(1-$C$27)+$C$27*$C$28 -> 3300 | L45: =L37*(1-$C$27)+$C$27*$C$28 -> 3300 | M45: =M37*(1-$C$27)+$C$27*$C$28 -> 3300 | ... AC45: =AC37*(1-$C$27)+$C$27*$C$28 -> 3300
B46: Copper revenue | C46: US$M | D46: =SUM(F46:AC46) -> 6100.693 | F46: =F42*F44 -> 436.64252 | G46: =G42*G44 -> 400.25564 | H46: =H42*H44 -> 363.86877 | I46: =I42*I44 -> 363.86877 | J46: =J42*J44 -> 363.86877 | K46: =K42*K44 -> 363.86877 | L46: =L42*L44 -> 363.86877 | M46: =M42*M44 -> 363.86877 | ... AC46: =AC42*AC44 -> 0
B47: Gold revenue | C47: US$M | D47: =SUM(F47:AC47) -> 0 | F47: =F43*F45/1000 -> 0 | G47: =G43*G45/1000 -> 0 | H47: =H43*H45/1000 -> 0 | I47: =I43*I45/1000 -> 0 | J47: =J43*J45/1000 -> 0 | K47: =K43*K45/1000 -> 0 | L47: =L43*L45/1000 -> 0 | M47: =M43*M45/1000 -> 0 | ... AC47: =AC43*AC45/1000 -> 0
B48: Total revenue | C48: US$M | D48: =SUM(F48:AC48) -> 6100.693 | F48: =F46+F47 -> 436.64252 | G48: =G46+G47 -> 400.25564 | H48: =H46+H47 -> 363.86877 | I48: =I46+I47 -> 363.86877 | J48: =J46+J47 -> 363.86877 | K48: =K46+K47 -> 363.86877 | L48: =L46+L47 -> 363.86877 | M48: =M46+M47 -> 363.86877 | ... AC48: =AC46+AC47 -> 0
B49: TC/RC and freight | C49: US$M | D49: =SUM(F49:AC49) -> -419.40727 | F49: =-F42*$C$19 -> -25.470814 | G49: =-G42*$C$19 -> -25.470814 | H49: =-H42*$C$19 -> -25.470814 | I49: =-I42*$C$19 -> -25.470814 | J49: =-J42*$C$19 -> -25.470814 | K49: =-K42*$C$19 -> -25.470814 | L49: =-L42*$C$19 -> -25.470814 | M49: =-M42*$C$19 -> -25.470814 | ... AC49: =-AC42*$C$19 -> 0
B50: Royalties | C50: US$M | D50: =SUM(F50:AC50) -> -122.01386 | F50: =-F48*$C$25 -> -8.7328504 | G50: =-G48*$C$25 -> -8.0051129 | H50: =-H48*$C$25 -> -7.2773753 | I50: =-I48*$C$25 -> -7.2773753 | J50: =-J48*$C$25 -> -7.2773753 | K50: =-K48*$C$25 -> -7.2773753 | L50: =-L48*$C$25 -> -7.2773753 | M50: =-M48*$C$25 -> -7.2773753 | ... AC50: =-AC48*$C$25 -> 0
B51: Site operating costs | C51: US$M | D51: =SUM(F51:AC51) -> -2558.846 | F51: =-F40*$C$18 -> -155.4 | G51: =-G40*$C$18 -> -155.4 | H51: =-H40*$C$18 -> -155.4 | I51: =-I40*$C$18 -> -155.4 | J51: =-J40*$C$18 -> -155.4 | K51: =-K40*$C$18 -> -155.4 | L51: =-L40*$C$18 -> -155.4 | M51: =-M40*$C$18 -> -155.4 | ... AC51: =-AC40*$C$18 -> 0
B52: Mine EBITDA | C52: US$M | D52: =SUM(F52:AC52) -> 3000.4259 | F52: =SUM(F48:F51) -> 247.03886 | G52: =SUM(G48:G51) -> 211.37972 | H52: =SUM(H48:H51) -> 175.72058 | I52: =SUM(I48:I51) -> 175.72058 | J52: =SUM(J48:J51) -> 175.72058 | K52: =SUM(K48:K51) -> 175.72058 | L52: =SUM(L48:L51) -> 175.72058 | M52: =SUM(M48:M51) -> 175.72058 | ... AC52: =SUM(AC48:AC51) -> 0
B53: Sustaining capex | C53: US$M | D53: =SUM(F53:AC53) -> -935 | F53: =-IF(F40>0,$C$20,0) -> -55 | G53: =-IF(G40>0,$C$20,0) -> -55 | H53: =-IF(H40>0,$C$20,0) -> -55 | I53: =-IF(I40>0,$C$20,0) -> -55 | J53: =-IF(J40>0,$C$20,0) -> -55 | K53: =-IF(K40>0,$C$20,0) -> -55 | L53: =-IF(L40>0,$C$20,0) -> -55 | M53: =-IF(M40>0,$C$20,0) -> -55 | ... AC53: =-IF(AC40>0,$C$20,0) -> 0
B54: Growth capex | C54: US$M | D54: =SUM(F54:AC54) -> -60 | F54: =-IF(AND(F$34>=$C$22,F$34<$C$22+$C$23),$C$21/$C$23,0) -> -60 | G54: =-IF(AND(G$34>=$C$22,G$34<$C$22+$C$23),$C$21/$C$23,0) -> 0 | H54: =-IF(AND(H$34>=$C$22,H$34<$C$22+$C$23),$C$21/$C$23,0) -> 0 | I54: =-IF(AND(I$34>=$C$22,I$34<$C$22+$C$23),$C$21/$C$23,0) -> 0 | J54: =-IF(AND(J$34>=$C$22,J$34<$C$22+$C$23),$C$21/$C$23,0) -> 0 | K54: =-IF(AND(K$34>=$C$22,K$34<$C$22+$C$23),$C$21/$C$23,0) -> 0 | L54: =-IF(AND(L$34>=$C$22,L$34<$C$22+$C$23),$C$21/$C$23,0) -> 0 | M54: =-IF(AND(M$34>=$C$22,M$34<$C$22+$C$23),$C$21/$C$23,0) -> 0 | ... AC54: =-IF(AND(AC$34>=$C$22,AC$34<$C$22+$C$23),$C$21/$C$23,0) -> 0
B55: Closure and reclamation | C55: US$M | D55: =SUM(F55:AC55) -> -50 | F55: =0 -> 0 | G55: =-IF(AND(G40=0,F40>0),$C$24,0) -> 0 | H55: =-IF(AND(H40=0,G40>0),$C$24,0) -> 0 | I55: =-IF(AND(I40=0,H40>0),$C$24,0) -> 0 | J55: =-IF(AND(J40=0,I40>0),$C$24,0) -> 0 | K55: =-IF(AND(K40=0,J40>0),$C$24,0) -> 0 | L55: =-IF(AND(L40=0,K40>0),$C$24,0) -> 0 | M55: =-IF(AND(M40=0,L40>0),$C$24,0) -> 0 | N55: =-IF(AND(N40=0,M40>0),$C$24,0) -> 0 | ... AC55: =-IF(AND(AC40=0,AB40>0),$C$24,0) -> 0
B56: Cash taxes | C56: US$M | D56: =SUM(F56:AC56) -> -305.82745 | F56: =-MAX(0,(F52+F53+F54)*$C$26) -> -20.135926 | G56: =-MAX(0,(G52+G53+G54)*$C$26) -> -23.847907 | H56: =-MAX(0,(H52+H53+H54)*$C$26) -> -18.409888 | I56: =-MAX(0,(I52+I53+I54)*$C$26) -> -18.409888 | J56: =-MAX(0,(J52+J53+J54)*$C$26) -> -18.409888 | K56: =-MAX(0,(K52+K53+K54)*$C$26) -> -18.409888 | L56: =-MAX(0,(L52+L53+L54)*$C$26) -> -18.409888 | M56: =-MAX(0,(M52+M53+M54)*$C$26) -> -18.409888 | ... AC56: =-MAX(0,(AC52+AC53+AC54)*$C$26) -> 0
B57: Unlevered free cash flow | C57: US$M | D57: =SUM(F57:AC57) -> 1649.5985 | F57: =SUM(F52:F56) -> 111.90293 | G57: =SUM(G52:G56) -> 132.53181 | H57: =SUM(H52:H56) -> 102.31069 | I57: =SUM(I52:I56) -> 102.31069 | J57: =SUM(J52:J56) -> 102.31069 | K57: =SUM(K52:K56) -> 102.31069 | L57: =SUM(L52:L56) -> 102.31069 | M57: =SUM(M52:M56) -> 102.31069 | ... AC57: =SUM(AC52:AC56) -> 0
B58: Discount factor (mid-year) | F58: =1/(1+$C$31)^(F35-0.5) -> 0.96225045 | G58: =1/(1+$C$31)^(G35-0.5) -> 0.89097264 | H58: =1/(1+$C$31)^(H35-0.5) -> 0.82497466 | I58: =1/(1+$C$31)^(I35-0.5) -> 0.76386543 | J58: =1/(1+$C$31)^(J35-0.5) -> 0.70728281 | K58: =1/(1+$C$31)^(K35-0.5) -> 0.65489149 | L58: =1/(1+$C$31)^(L35-0.5) -> 0.60638101 | M58: =1/(1+$C$31)^(M35-0.5) -> 0.56146389 | ... AC58: =1/(1+$C$31)^(AC35-0.5) -> 0.16388596
B59: PV of free cash flow | C59: US$M | D59: =SUM(F59:AC59) -> 970.67724 | F59: =F57*F58 -> 107.67864 | G59: =G57*G58 -> 118.08222 | H59: =H57*H58 -> 84.403727 | I59: =I57*I58 -> 78.151599 | J59: =J57*J58 -> 72.362592 | K59: =K57*K58 -> 67.0024 | L59: =L57*L58 -> 62.039259 | M59: =M57*M58 -> 57.443758 | ... AC59: =AC57*AC58 -> 0
B61: Asset summary
B62: NPV (100% basis) | C62: =SUM(F59:AC59) -> 970.67724 | D62: US$M
B63: Attributable NAV | C63: =C62*$C$5 -> 970.67724 | D63: US$M
B64: Remaining mine life | C64: =COUNTIF(F40:AC40,">0") -> 17 | D64: years
B65: AISC 2027, by-product | C65: =IFERROR((-(F49+F50+F51+F53)-F47)/F42,0) -> 3.3611522 | D65: US$/lb Cu
B66: AISC life of mine, by-product | C66: =IFERROR((-(D49+D50+D51+D53)-D47)/D42,0) -> 3.367475 | D66: US$/lb Cu

Sheet Tucuma
B1: Tucumã — asset NAV (ERO, Brazil (Pará))
B2: Reserve-constrained life-of-mine model. Blue = input (data/assets.csv), green = link, black = formula. US$M real unless noted.
B4: Input | C4: Value | D4: Unit | F4: Source / status
B5: Ownership | C5: 1 | D5: % | F5: Source IDs: ERO-TUCUMA-TR;ERO-MDA-2025Q4;ERO-Q2-2026 (see Sources tab)
B6: P&P reserve (at effective date) | C6: 43.052 | D6: Mt | F6: [verified] reserve_mt|cu_grade_pct: Sep 2021 P&P 43.1 Mt @ 0.83% Cu (pre-production)
B7: Depletion to 1 Jan 2027 | C7: 6.6 | D7: Mt | F7: [estimate] depleted_mt: 2024–2026 ore processed (2025 verified at 1.81 Mt)
B8: Copper grade | C8: 0.0083 | D8: % Cu | F8: [calibrated] opex_usd_t: Set so C1 lands near the US$1.95–2.15/lb 2026 guidance
B9: Gold grade | C9: 0 | D9: g/t Au | F9: [estimate] expansion_mtpa|sustaining_usd_m: 4.4 Mtpa from 2027 reflects plant throughput upgrades due Q4 2026 (ERO-Q2-2026); sustaining capex is an analyst estimate
B10: Copper recovery | C10: 0.9 | D10: %
B11: Gold recovery | C11: 0 | D11: %
B12: Copper payable | C12: 0.965 | D12: %
B13: Gold payable | C13: 0 | D13: %
B14: Throughput | C14: 4 | D14: Mtpa
B15: Throughput after expansion | C15: 4.4 | D15: Mtpa
B16: Expansion year | C16: 2027 | D16: year
B17: First production year | C17: 2027 | D17: year
B18: Site operating cost | C18: 28 | D18: US$/t milled
B19: TC/RC and freight | C19: 0.35 | D19: US$/lb Cu
B20: Sustaining capex | C20: 25 | D20: US$M/yr
B21: Growth capex (total) | C21: 0 | D21: US$M
... B30: Stream copper price received | C30: 0 | D30: % of spot
B31: Discount rate (real) | C31: =Inputs!$C$26 -> 0.08 | D31: Inputs tab
B34: US$M unless noted | C34: Unit | D34: LOM / NPV | F34: 2027 | G34: 2028 | H34: 2029 | I34: 2030 | J34: 2031 | K34: 2032 | L34: 2033 | M34: 2034 | N34: 2035 | O34: 2036 | P34: 2037 | Q34: 2038 | R34: 2039 | S34: 2040 | T34: 2041 | U34: 2042 | V34: 2043 | W34: 2044 | X34: 2045 | Y34: 2046 | Z34: 2047 | AA34: 2048 | AB34: 2049 | AC34: 2050
B35: Period | F35: =F$34-2027+1 -> 1 | G35: =G$34-2027+1 -> 2 | H35: =H$34-2027+1 -> 3 | I35: =I$34-2027+1 -> 4 | J35: =J$34-2027+1 -> 5 | K35: =K$34-2027+1 -> 6 | L35: =L$34-2027+1 -> 7 | M35: =M$34-2027+1 -> 8 | ... AC35: =AC$34-2027+1 -> 24
B36: Copper price | C36: US$/lb | F36: =Inputs!F$18 -> 6 | G36: =Inputs!G$18 -> 5.5 | H36: =Inputs!H$18 -> 5 | I36: =Inputs!I$18 -> 5 | J36: =Inputs!J$18 -> 5 | K36: =Inputs!K$18 -> 5 | L36: =Inputs!L$18 -> 5 | M36: =Inputs!M$18 -> 5 | ... AC36: =Inputs!AC$18 -> 5
B37: Gold price | C37: US$/oz | F37: =Inputs!F$19 -> 3900 | G37: =Inputs!G$19 -> 3600 | H37: =Inputs!H$19 -> 3300 | I37: =Inputs!I$19 -> 3300 | J37: =Inputs!J$19 -> 3300 | K37: =Inputs!K$19 -> 3300 | L37: =Inputs!L$19 -> 3300 | M37: =Inputs!M$19 -> 3300 | ... AC37: =Inputs!AC$19 -> 3300
B38: Mill capacity | C38: Mt | F38: =IF(F$34<$C$17,0,IF(F$34>=$C$16,$C$15,$C$14)) -> 4.4 | G38: =IF(G$34<$C$17,0,IF(G$34>=$C$16,$C$15,$C$14)) -> 4.4 | H38: =IF(H$34<$C$17,0,IF(H$34>=$C$16,$C$15,$C$14)) -> 4.4 | I38: =IF(I$34<$C$17,0,IF(I$34>=$C$16,$C$15,$C$14)) -> 4.4 | J38: =IF(J$34<$C$17,0,IF(J$34>=$C$16,$C$15,$C$14)) -> 4.4 | K38: =IF(K$34<$C$17,0,IF(K$34>=$C$16,$C$15,$C$14)) -> 4.4 | L38: =IF(L$34<$C$17,0,IF(L$34>=$C$16,$C$15,$C$14)) -> 4.4 | M38: =IF(M$34<$C$17,0,IF(M$34>=$C$16,$C$15,$C$14)) -> 4.4 | ... AC38: =IF(AC$34<$C$17,0,IF(AC$34>=$C$16,$C$15,$C$14)) -> 4.4
B39: Opening reserve | C39: Mt | F39: =$C$6-$C$7 -> 36.452 | G39: =F41 -> 32.052 | H39: =G41 -> 27.652 | I39: =H41 -> 23.252 | J39: =I41 -> 18.852 | K39: =J41 -> 14.452 | L39: =K41 -> 10.052 | M39: =L41 -> 5.652 | N39: =M41 -> 1.252 | ... AC39: =AB41 -> 0
B40: Ore processed | C40: Mt | D40: =SUM(F40:AC40) -> 36.452 | F40: =MAX(0,MIN(F38,F39)) -> 4.4 | G40: =MAX(0,MIN(G38,G39)) -> 4.4 | H40: =MAX(0,MIN(H38,H39)) -> 4.4 | I40: =MAX(0,MIN(I38,I39)) -> 4.4 | J40: =MAX(0,MIN(J38,J39)) -> 4.4 | K40: =MAX(0,MIN(K38,K39)) -> 4.4 | L40: =MAX(0,MIN(L38,L39)) -> 4.4 | M40: =MAX(0,MIN(M38,M39)) -> 4.4 | ... AC40: =MAX(0,MIN(AC38,AC39)) -> 0
B41: Closing reserve | C41: Mt | F41: =F39-F40 -> 32.052 | G41: =G39-G40 -> 27.652 | H41: =H39-H40 -> 23.252 | I41: =I39-I40 -> 18.852 | J41: =J39-J40 -> 14.452 | K41: =K39-K40 -> 10.052 | L41: =L39-L40 -> 5.652 | M41: =M39-M40 -> 1.252 | ... AC41: =AC39-AC40 -> 0
B42: Payable copper | C42: Mlb | D42: =SUM(F42:AC42) -> 579.29932 | F42: =F40*$C$8*$C$10*$C$12*2204.62 -> 69.925299 | G42: =G40*$C$8*$C$10*$C$12*2204.62 -> 69.925299 | H42: =H40*$C$8*$C$10*$C$12*2204.62 -> 69.925299 | I42: =I40*$C$8*$C$10*$C$12*2204.62 -> 69.925299 | J42: =J40*$C$8*$C$10*$C$12*2204.62 -> 69.925299 | K42: =K40*$C$8*$C$10*$C$12*2204.62 -> 69.925299 | L42: =L40*$C$8*$C$10*$C$12*2204.62 -> 69.925299 | M42: =M40*$C$8*$C$10*$C$12*2204.62 -> 69.925299 | ... AC42: =AC40*$C$8*$C$10*$C$12*2204.62 -> 0
B43: Payable gold | C43: koz | D43: =SUM(F43:AC43) -> 0 | F43: =F40*$C$9*$C$11*$C$13*1000/31.1035 -> 0 | G43: =G40*$C$9*$C$11*$C$13*1000/31.1035 -> 0 | H43: =H40*$C$9*$C$11*$C$13*1000/31.1035 -> 0 | I43: =I40*$C$9*$C$11*$C$13*1000/31.1035 -> 0 | J43: =J40*$C$9*$C$11*$C$13*1000/31.1035 -> 0 | K43: =K40*$C$9*$C$11*$C$13*1000/31.1035 -> 0 | L43: =L40*$C$9*$C$11*$C$13*1000/31.1035 -> 0 | M43: =M40*$C$9*$C$11*$C$13*1000/31.1035 -> 0 | ... AC43: =AC40*$C$9*$C$11*$C$13*1000/31.1035 -> 0
B44: Realised copper price (after stream) | C44: US$/lb | F44: =F36*(1-$C$29)+F36*$C$29*$C$30 -> 6 | G44: =G36*(1-$C$29)+G36*$C$29*$C$30 -> 5.5 | H44: =H36*(1-$C$29)+H36*$C$29*$C$30 -> 5 | I44: =I36*(1-$C$29)+I36*$C$29*$C$30 -> 5 | J44: =J36*(1-$C$29)+J36*$C$29*$C$30 -> 5 | K44: =K36*(1-$C$29)+K36*$C$29*$C$30 -> 5 | L44: =L36*(1-$C$29)+L36*$C$29*$C$30 -> 5 | M44: =M36*(1-$C$29)+M36*$C$29*$C$30 -> 5 | ... AC44: =AC36*(1-$C$29)+AC36*$C$29*$C$30 -> 5
B45: Realised gold price (after stream) | C45: US$/oz | F45: =F37*(1-$C$27)+$C$27*$C$28 -> 3900 | G45: =G37*(1-$C$27)+$C$27*$C$28 -> 3600 | H45: =H37*(1-$C$27)+$C$27*$C$28 -> 3300 | I45: =I37*(1-$C$27)+$C$27*$C$28 -> 3300 | J45: =J37*(1-$C$27)+$C$27*$C$28 -> 3300 | K45: =K37*(1-$C$27)+$C$27*$C$28 -> 3300 | L45: =L37*(1-$C$27)+$C$27*$C$28 -> 3300 | M45: =M37*(1-$C$27)+$C$27*$C$28 -> 3300 | ... AC45: =AC37*(1-$C$27)+$C$27*$C$28 -> 3300
B46: Copper revenue | C46: US$M | D46: =SUM(F46:AC46) -> 3001.3846 | F46: =F42*F44 -> 419.5518 | G46: =G42*G44 -> 384.58915 | H46: =H42*H44 -> 349.6265 | I46: =I42*I44 -> 349.6265 | J46: =J42*J44 -> 349.6265 | K46: =K42*K44 -> 349.6265 | L46: =L42*L44 -> 349.6265 | M46: =M42*M44 -> 349.6265 | ... AC46: =AC42*AC44 -> 0
B47: Gold revenue | C47: US$M | D47: =SUM(F47:AC47) -> 0 | F47: =F43*F45/1000 -> 0 | G47: =G43*G45/1000 -> 0 | H47: =H43*H45/1000 -> 0 | I47: =I43*I45/1000 -> 0 | J47: =J43*J45/1000 -> 0 | K47: =K43*K45/1000 -> 0 | L47: =L43*L45/1000 -> 0 | M47: =M43*M45/1000 -> 0 | ... AC47: =AC43*AC45/1000 -> 0
B48: Total revenue | C48: US$M | D48: =SUM(F48:AC48) -> 3001.3846 | F48: =F46+F47 -> 419.5518 | G48: =G46+G47 -> 384.58915 | H48: =H46+H47 -> 349.6265 | I48: =I46+I47 -> 349.6265 | J48: =J46+J47 -> 349.6265 | K48: =K46+K47 -> 349.6265 | L48: =L46+L47 -> 349.6265 | M48: =M46+M47 -> 349.6265 | ... AC48: =AC46+AC47 -> 0
B49: TC/RC and freight | C49: US$M | D49: =SUM(F49:AC49) -> -202.75476 | F49: =-F42*$C$19 -> -24.473855 | G49: =-G42*$C$19 -> -24.473855 | H49: =-H42*$C$19 -> -24.473855 | I49: =-I42*$C$19 -> -24.473855 | J49: =-J42*$C$19 -> -24.473855 | K49: =-K42*$C$19 -> -24.473855 | L49: =-L42*$C$19 -> -24.473855 | M49: =-M42*$C$19 -> -24.473855 | ... AC49: =-AC42*$C$19 -> 0
B50: Royalties | C50: US$M | D50: =SUM(F50:AC50) -> -60.027691 | F50: =-F48*$C$25 -> -8.3910359 | G50: =-G48*$C$25 -> -7.6917829 | H50: =-H48*$C$25 -> -6.9925299 | I50: =-I48*$C$25 -> -6.9925299 | J50: =-J48*$C$25 -> -6.9925299 | K50: =-K48*$C$25 -> -6.9925299 | L50: =-L48*$C$25 -> -6.9925299 | M50: =-M48*$C$25 -> -6.9925299 | ... AC50: =-AC48*$C$25 -> 0
B51: Site operating costs | C51: US$M | D51: =SUM(F51:AC51) -> -1020.656 | F51: =-F40*$C$18 -> -123.2 | G51: =-G40*$C$18 -> -123.2 | H51: =-H40*$C$18 -> -123.2 | I51: =-I40*$C$18 -> -123.2 | J51: =-J40*$C$18 -> -123.2 | K51: =-K40*$C$18 -> -123.2 | L51: =-L40*$C$18 -> -123.2 | M51: =-M40*$C$18 -> -123.2 | ... AC51: =-AC40*$C$18 -> 0
B52: Mine EBITDA | C52: US$M | D52: =SUM(F52:AC52) -> 1717.9461 | F52: =SUM(F48:F51) -> 263.48691 | G52: =SUM(G48:G51) -> 229.22351 | H52: =SUM(H48:H51) -> 194.96011 | I52: =SUM(I48:I51) -> 194.96011 | J52: =SUM(J48:J51) -> 194.96011 | K52: =SUM(K48:K51) -> 194.96011 | L52: =SUM(L48:L51) -> 194.96011 | M52: =SUM(M48:M51) -> 194.96011 | ... AC52: =SUM(AC48:AC51) -> 0
B53: Sustaining capex | C53: US$M | D53: =SUM(F53:AC53) -> -225 | F53: =-IF(F40>0,$C$20,0) -> -25 | G53: =-IF(G40>0,$C$20,0) -> -25 | H53: =-IF(H40>0,$C$20,0) -> -25 | I53: =-IF(I40>0,$C$20,0) -> -25 | J53: =-IF(J40>0,$C$20,0) -> -25 | K53: =-IF(K40>0,$C$20,0) -> -25 | L53: =-IF(L40>0,$C$20,0) -> -25 | M53: =-IF(M40>0,$C$20,0) -> -25 | ... AC53: =-IF(AC40>0,$C$20,0) -> 0
B54: Growth capex | C54: US$M | D54: =SUM(F54:AC54) -> 0 | F54: =-IF(AND(F$34>=$C$22,F$34<$C$22+$C$23),$C$21/$C$23,0) -> 0 | G54: =-IF(AND(G$34>=$C$22,G$34<$C$22+$C$23),$C$21/$C$23,0) -> 0 | H54: =-IF(AND(H$34>=$C$22,H$34<$C$22+$C$23),$C$21/$C$23,0) -> 0 | I54: =-IF(AND(I$34>=$C$22,I$34<$C$22+$C$23),$C$21/$C$23,0) -> 0 | J54: =-IF(AND(J$34>=$C$22,J$34<$C$22+$C$23),$C$21/$C$23,0) -> 0 | K54: =-IF(AND(K$34>=$C$22,K$34<$C$22+$C$23),$C$21/$C$23,0) -> 0 | L54: =-IF(AND(L$34>=$C$22,L$34<$C$22+$C$23),$C$21/$C$23,0) -> 0 | M54: =-IF(AND(M$34>=$C$22,M$34<$C$22+$C$23),$C$21/$C$23,0) -> 0 | ... AC54: =-IF(AND(AC$34>=$C$22,AC$34<$C$22+$C$23),$C$21/$C$23,0) -> 0
B55: Closure and reclamation | C55: US$M | D55: =SUM(F55:AC55) -> -40 | F55: =0 -> 0 | G55: =-IF(AND(G40=0,F40>0),$C$24,0) -> 0 | H55: =-IF(AND(H40=0,G40>0),$C$24,0) -> 0 | I55: =-IF(AND(I40=0,H40>0),$C$24,0) -> 0 | J55: =-IF(AND(J40=0,I40>0),$C$24,0) -> 0 | K55: =-IF(AND(K40=0,J40>0),$C$24,0) -> 0 | L55: =-IF(AND(L40=0,K40>0),$C$24,0) -> 0 | M55: =-IF(AND(M40=0,L40>0),$C$24,0) -> 0 | N55: =-IF(AND(N40=0,M40>0),$C$24,0) -> 0 | ... AC55: =-IF(AND(AC40=0,AB40>0),$C$24,0) -> 0
B56: Cash taxes | C56: US$M | D56: =SUM(F56:AC56) -> -227.67428 | F56: =-MAX(0,(F52+F53+F54)*$C$26) -> -36.369253 | G56: =-MAX(0,(G52+G53+G54)*$C$26) -> -31.144085 | H56: =-MAX(0,(H52+H53+H54)*$C$26) -> -25.918917 | I56: =-MAX(0,(I52+I53+I54)*$C$26) -> -25.918917 | J56: =-MAX(0,(J52+J53+J54)*$C$26) -> -25.918917 | K56: =-MAX(0,(K52+K53+K54)*$C$26) -> -25.918917 | L56: =-MAX(0,(L52+L53+L54)*$C$26) -> -25.918917 | M56: =-MAX(0,(M52+M53+M54)*$C$26) -> -25.918917 | ... AC56: =-MAX(0,(AC52+AC53+AC54)*$C$26) -> 0
B57: Unlevered free cash flow | C57: US$M | D57: =SUM(F57:AC57) -> 1225.2718 | F57: =SUM(F52:F56) -> 202.11765 | G57: =SUM(G52:G56) -> 173.07942 | H57: =SUM(H52:H56) -> 144.0412 | I57: =SUM(I52:I56) -> 144.0412 | J57: =SUM(J52:J56) -> 144.0412 | K57: =SUM(K52:K56) -> 144.0412 | L57: =SUM(L52:L56) -> 144.0412 | M57: =SUM(M52:M56) -> 144.0412 | ... AC57: =SUM(AC52:AC56) -> 0
B58: Discount factor (mid-year) | F58: =1/(1+$C$31)^(F35-0.5) -> 0.96225045 | G58: =1/(1+$C$31)^(G35-0.5) -> 0.89097264 | H58: =1/(1+$C$31)^(H35-0.5) -> 0.82497466 | I58: =1/(1+$C$31)^(I35-0.5) -> 0.76386543 | J58: =1/(1+$C$31)^(J35-0.5) -> 0.70728281 | K58: =1/(1+$C$31)^(K35-0.5) -> 0.65489149 | L58: =1/(1+$C$31)^(L35-0.5) -> 0.60638101 | M58: =1/(1+$C$31)^(M35-0.5) -> 0.56146389 | ... AC58: =1/(1+$C$31)^(AC35-0.5) -> 0.16388596
B59: PV of free cash flow | C59: US$M | D59: =SUM(F59:AC59) -> 936.15474 | F59: =F57*F58 -> 194.4878 | G59: =G57*G58 -> 154.20903 | H59: =H57*H58 -> 118.83034 | I59: =I57*I58 -> 110.02809 | J59: =J57*J58 -> 101.87786 | K59: =K57*K58 -> 94.331352 | L59: =L57*L58 -> 87.343845 | M59: =M57*M58 -> 80.87393 | ... AC59: =AC57*AC58 -> 0
B61: Asset summary
B62: NPV (100% basis) | C62: =SUM(F59:AC59) -> 936.15474 | D62: US$M
B63: Attributable NAV | C63: =C62*$C$5 -> 936.15474 | D63: US$M
B64: Remaining mine life | C64: =COUNTIF(F40:AC40,">0") -> 9 | D64: years
B65: AISC 2027, by-product | C65: =IFERROR((-(F49+F50+F51+F53)-F47)/F42,0) -> 2.5894046 | D65: US$/lb Cu
B66: AISC life of mine, by-product | C66: =IFERROR((-(D49+D50+D51+D53)-D47)/D42,0) -> 2.6039016 | D66: US$/lb Cu

Sheet Xavantina
B1: Xavantina — asset NAV (ERO, Brazil (Mato Grosso))
B2: Reserve-constrained life-of-mine model. Blue = input (data/assets.csv), green = link, black = formula. US$M real unless noted.
B4: Input | C4: Value | D4: Unit | F4: Source / status
B5: Ownership | C5: 0.976 | D5: % | F5: Source IDs: ERO-XAV-2025;ERO-MDA-2025Q4;ERO-Q2-2026 (see Sources tab)
B6: P&P reserve (at effective date) | C6: 1.1 | D6: Mt | F6: [estimate] reserve_mt|au_gpt: Back-solved from 2025 production (172 kt processed; 37.3 koz) and 40–50 koz/yr guidance; replace with the 2025 reserve update table
B7: Depletion to 1 Jan 2027 | C7: 0.18 | D7: Mt | F7: [calibrated] opex_usd_t|sustaining_usd_m: Set so AISC lands in the revised US$2,200–2,700/oz guidance range
B8: Copper grade | C8: 0 | D8: % Cu
B9: Gold grade | C9: 6.8 | D9: g/t Au
B10: Copper recovery | C10: 0 | D10: %
B11: Gold recovery | C11: 0.92 | D11: %
B12: Copper payable | C12: 0 | D12: %
B13: Gold payable | C13: 0.999 | D13: %
B14: Throughput | C14: 0.2 | D14: Mtpa
B15: Throughput after expansion | C15: 0.2 | D15: Mtpa
B16: Expansion year | C16: 2027 | D16: year
B17: First production year | C17: 2027 | D17: year
B18: Site operating cost | C18: 270 | D18: US$/t milled
B19: TC/RC and freight | C19: 0 | D19: US$/lb Cu
... B30: Stream copper price received | C30: 0 | D30: % of spot
B31: Discount rate (real) | C31: =Inputs!$C$27 -> 0.05 | D31: Inputs tab
B34: US$M unless noted | C34: Unit | D34: LOM / NPV | F34: 2027 | G34: 2028 | H34: 2029 | I34: 2030 | J34: 2031 | K34: 2032 | L34: 2033 | M34: 2034 | N34: 2035 | O34: 2036 | P34: 2037 | Q34: 2038 | R34: 2039 | S34: 2040 | T34: 2041 | U34: 2042 | V34: 2043 | W34: 2044 | X34: 2045 | Y34: 2046 | Z34: 2047 | AA34: 2048 | AB34: 2049 | AC34: 2050
B35: Period | F35: =F$34-2027+1 -> 1 | G35: =G$34-2027+1 -> 2 | H35: =H$34-2027+1 -> 3 | I35: =I$34-2027+1 -> 4 | J35: =J$34-2027+1 -> 5 | K35: =K$34-2027+1 -> 6 | L35: =L$34-2027+1 -> 7 | M35: =M$34-2027+1 -> 8 | ... AC35: =AC$34-2027+1 -> 24
B36: Copper price | C36: US$/lb | F36: =Inputs!F$18 -> 6 | G36: =Inputs!G$18 -> 5.5 | H36: =Inputs!H$18 -> 5 | I36: =Inputs!I$18 -> 5 | J36: =Inputs!J$18 -> 5 | K36: =Inputs!K$18 -> 5 | L36: =Inputs!L$18 -> 5 | M36: =Inputs!M$18 -> 5 | ... AC36: =Inputs!AC$18 -> 5
B37: Gold price | C37: US$/oz | F37: =Inputs!F$19 -> 3900 | G37: =Inputs!G$19 -> 3600 | H37: =Inputs!H$19 -> 3300 | I37: =Inputs!I$19 -> 3300 | J37: =Inputs!J$19 -> 3300 | K37: =Inputs!K$19 -> 3300 | L37: =Inputs!L$19 -> 3300 | M37: =Inputs!M$19 -> 3300 | ... AC37: =Inputs!AC$19 -> 3300
B38: Mill capacity | C38: Mt | F38: =IF(F$34<$C$17,0,IF(F$34>=$C$16,$C$15,$C$14)) -> 0.2 | G38: =IF(G$34<$C$17,0,IF(G$34>=$C$16,$C$15,$C$14)) -> 0.2 | H38: =IF(H$34<$C$17,0,IF(H$34>=$C$16,$C$15,$C$14)) -> 0.2 | I38: =IF(I$34<$C$17,0,IF(I$34>=$C$16,$C$15,$C$14)) -> 0.2 | J38: =IF(J$34<$C$17,0,IF(J$34>=$C$16,$C$15,$C$14)) -> 0.2 | K38: =IF(K$34<$C$17,0,IF(K$34>=$C$16,$C$15,$C$14)) -> 0.2 | L38: =IF(L$34<$C$17,0,IF(L$34>=$C$16,$C$15,$C$14)) -> 0.2 | M38: =IF(M$34<$C$17,0,IF(M$34>=$C$16,$C$15,$C$14)) -> 0.2 | ... AC38: =IF(AC$34<$C$17,0,IF(AC$34>=$C$16,$C$15,$C$14)) -> 0.2
B39: Opening reserve | C39: Mt | F39: =$C$6-$C$7 -> 0.92 | G39: =F41 -> 0.72 | H39: =G41 -> 0.52 | I39: =H41 -> 0.32 | J39: =I41 -> 0.12 | K39: =J41 -> 0 | L39: =K41 -> 0 | M39: =L41 -> 0 | N39: =M41 -> 0 | ... AC39: =AB41 -> 0
B40: Ore processed | C40: Mt | D40: =SUM(F40:AC40) -> 0.92 | F40: =MAX(0,MIN(F38,F39)) -> 0.2 | G40: =MAX(0,MIN(G38,G39)) -> 0.2 | H40: =MAX(0,MIN(H38,H39)) -> 0.2 | I40: =MAX(0,MIN(I38,I39)) -> 0.2 | J40: =MAX(0,MIN(J38,J39)) -> 0.12 | K40: =MAX(0,MIN(K38,K39)) -> 0 | L40: =MAX(0,MIN(L38,L39)) -> 0 | M40: =MAX(0,MIN(M38,M39)) -> 0 | ... AC40: =MAX(0,MIN(AC38,AC39)) -> 0
B41: Closing reserve | C41: Mt | F41: =F39-F40 -> 0.72 | G41: =G39-G40 -> 0.52 | H41: =H39-H40 -> 0.32 | I41: =I39-I40 -> 0.12 | J41: =J39-J40 -> 0 | K41: =K39-K40 -> 0 | L41: =L39-L40 -> 0 | M41: =M39-M40 -> 0 | ... AC41: =AC39-AC40 -> 0
B42: Payable copper | C42: Mlb | D42: =SUM(F42:AC42) -> 0 | F42: =F40*$C$8*$C$10*$C$12*2204.62 -> 0 | G42: =G40*$C$8*$C$10*$C$12*2204.62 -> 0 | H42: =H40*$C$8*$C$10*$C$12*2204.62 -> 0 | I42: =I40*$C$8*$C$10*$C$12*2204.62 -> 0 | J42: =J40*$C$8*$C$10*$C$12*2204.62 -> 0 | K42: =K40*$C$8*$C$10*$C$12*2204.62 -> 0 | L42: =L40*$C$8*$C$10*$C$12*2204.62 -> 0 | M42: =M40*$C$8*$C$10*$C$12*2204.62 -> 0 | ... AC42: =AC40*$C$8*$C$10*$C$12*2204.62 -> 0
B43: Payable gold | C43: koz | D43: =SUM(F43:AC43) -> 184.85908 | F43: =F40*$C$9*$C$11*$C$13*1000/31.1035 -> 40.186757 | G43: =G40*$C$9*$C$11*$C$13*1000/31.1035 -> 40.186757 | H43: =H40*$C$9*$C$11*$C$13*1000/31.1035 -> 40.186757 | I43: =I40*$C$9*$C$11*$C$13*1000/31.1035 -> 40.186757 | J43: =J40*$C$9*$C$11*$C$13*1000/31.1035 -> 24.112054 | K43: =K40*$C$9*$C$11*$C$13*1000/31.1035 -> 0 | L43: =L40*$C$9*$C$11*$C$13*1000/31.1035 -> 0 | M43: =M40*$C$9*$C$11*$C$13*1000/31.1035 -> 0 | ... AC43: =AC40*$C$9*$C$11*$C$13*1000/31.1035 -> 0
B44: Realised copper price (after stream) | C44: US$/lb | F44: =F36*(1-$C$29)+F36*$C$29*$C$30 -> 6 | G44: =G36*(1-$C$29)+G36*$C$29*$C$30 -> 5.5 | H44: =H36*(1-$C$29)+H36*$C$29*$C$30 -> 5 | I44: =I36*(1-$C$29)+I36*$C$29*$C$30 -> 5 | J44: =J36*(1-$C$29)+J36*$C$29*$C$30 -> 5 | K44: =K36*(1-$C$29)+K36*$C$29*$C$30 -> 5 | L44: =L36*(1-$C$29)+L36*$C$29*$C$30 -> 5 | M44: =M36*(1-$C$29)+M36*$C$29*$C$30 -> 5 | ... AC44: =AC36*(1-$C$29)+AC36*$C$29*$C$30 -> 5
B45: Realised gold price (after stream) | C45: US$/oz | F45: =F37*(1-$C$27)+$C$27*$C$28 -> 3900 | G45: =G37*(1-$C$27)+$C$27*$C$28 -> 3600 | H45: =H37*(1-$C$27)+$C$27*$C$28 -> 3300 | I45: =I37*(1-$C$27)+$C$27*$C$28 -> 3300 | J45: =J37*(1-$C$27)+$C$27*$C$28 -> 3300 | K45: =K37*(1-$C$27)+$C$27*$C$28 -> 3300 | L45: =L37*(1-$C$27)+$C$27*$C$28 -> 3300 | M45: =M37*(1-$C$27)+$C$27*$C$28 -> 3300 | ... AC45: =AC37*(1-$C$27)+$C$27*$C$28 -> 3300
B46: Copper revenue | C46: US$M | D46: =SUM(F46:AC46) -> 0 | F46: =F42*F44 -> 0 | G46: =G42*G44 -> 0 | H46: =H42*H44 -> 0 | I46: =I42*I44 -> 0 | J46: =J42*J44 -> 0 | K46: =K42*K44 -> 0 | L46: =L42*L44 -> 0 | M46: =M42*M44 -> 0 | ... AC46: =AC42*AC44 -> 0
B47: Gold revenue | C47: US$M | D47: =SUM(F47:AC47) -> 646.20305 | F47: =F43*F45/1000 -> 156.72835 | G47: =G43*G45/1000 -> 144.67233 | H47: =H43*H45/1000 -> 132.6163 | I47: =I43*I45/1000 -> 132.6163 | J47: =J43*J45/1000 -> 79.569779 | K47: =K43*K45/1000 -> 0 | L47: =L43*L45/1000 -> 0 | M47: =M43*M45/1000 -> 0 | ... AC47: =AC43*AC45/1000 -> 0
B48: Total revenue | C48: US$M | D48: =SUM(F48:AC48) -> 646.20305 | F48: =F46+F47 -> 156.72835 | G48: =G46+G47 -> 144.67233 | H48: =H46+H47 -> 132.6163 | I48: =I46+I47 -> 132.6163 | J48: =J46+J47 -> 79.569779 | K48: =K46+K47 -> 0 | L48: =L46+L47 -> 0 | M48: =M46+M47 -> 0 | ... AC48: =AC46+AC47 -> 0
B49: TC/RC and freight | C49: US$M | D49: =SUM(F49:AC49) -> 0 | F49: =-F42*$C$19 -> 0 | G49: =-G42*$C$19 -> 0 | H49: =-H42*$C$19 -> 0 | I49: =-I42*$C$19 -> 0 | J49: =-J42*$C$19 -> 0 | K49: =-K42*$C$19 -> 0 | L49: =-L42*$C$19 -> 0 | M49: =-M42*$C$19 -> 0 | ... AC49: =-AC42*$C$19 -> 0
B50: Royalties | C50: US$M | D50: =SUM(F50:AC50) -> -9.6930458 | F50: =-F48*$C$25 -> -2.3509253 | G50: =-G48*$C$25 -> -2.1700849 | H50: =-H48*$C$25 -> -1.9892445 | I50: =-I48*$C$25 -> -1.9892445 | J50: =-J48*$C$25 -> -1.1935467 | K50: =-K48*$C$25 -> 0 | L50: =-L48*$C$25 -> 0 | M50: =-M48*$C$25 -> 0 | ... AC50: =-AC48*$C$25 -> 0
B51: Site operating costs | C51: US$M | D51: =SUM(F51:AC51) -> -248.4 | F51: =-F40*$C$18 -> -54 | G51: =-G40*$C$18 -> -54 | H51: =-H40*$C$18 -> -54 | I51: =-I40*$C$18 -> -54 | J51: =-J40*$C$18 -> -32.4 | K51: =-K40*$C$18 -> 0 | L51: =-L40*$C$18 -> 0 | M51: =-M40*$C$18 -> 0 | ... AC51: =-AC40*$C$18 -> 0
B52: Mine EBITDA | C52: US$M | D52: =SUM(F52:AC52) -> 388.11001 | F52: =SUM(F48:F51) -> 100.37743 | G52: =SUM(G48:G51) -> 88.502241 | H52: =SUM(H48:H51) -> 76.627054 | I52: =SUM(I48:I51) -> 76.627054 | J52: =SUM(J48:J51) -> 45.976232 | K52: =SUM(K48:K51) -> 0 | L52: =SUM(L48:L51) -> 0 | M52: =SUM(M48:M51) -> 0 | ... AC52: =SUM(AC48:AC51) -> 0
B53: Sustaining capex | C53: US$M | D53: =SUM(F53:AC53) -> -200 | F53: =-IF(F40>0,$C$20,0) -> -40 | G53: =-IF(G40>0,$C$20,0) -> -40 | H53: =-IF(H40>0,$C$20,0) -> -40 | I53: =-IF(I40>0,$C$20,0) -> -40 | J53: =-IF(J40>0,$C$20,0) -> -40 | K53: =-IF(K40>0,$C$20,0) -> 0 | L53: =-IF(L40>0,$C$20,0) -> 0 | M53: =-IF(M40>0,$C$20,0) -> 0 | ... AC53: =-IF(AC40>0,$C$20,0) -> 0
B54: Growth capex | C54: US$M | D54: =SUM(F54:AC54) -> 0 | F54: =-IF(AND(F$34>=$C$22,F$34<$C$22+$C$23),$C$21/$C$23,0) -> 0 | G54: =-IF(AND(G$34>=$C$22,G$34<$C$22+$C$23),$C$21/$C$23,0) -> 0 | H54: =-IF(AND(H$34>=$C$22,H$34<$C$22+$C$23),$C$21/$C$23,0) -> 0 | I54: =-IF(AND(I$34>=$C$22,I$34<$C$22+$C$23),$C$21/$C$23,0) -> 0 | J54: =-IF(AND(J$34>=$C$22,J$34<$C$22+$C$23),$C$21/$C$23,0) -> 0 | K54: =-IF(AND(K$34>=$C$22,K$34<$C$22+$C$23),$C$21/$C$23,0) -> 0 | L54: =-IF(AND(L$34>=$C$22,L$34<$C$22+$C$23),$C$21/$C$23,0) -> 0 | M54: =-IF(AND(M$34>=$C$22,M$34<$C$22+$C$23),$C$21/$C$23,0) -> 0 | ... AC54: =-IF(AND(AC$34>=$C$22,AC$34<$C$22+$C$23),$C$21/$C$23,0) -> 0
B55: Closure and reclamation | C55: US$M | D55: =SUM(F55:AC55) -> -15 | F55: =0 -> 0 | G55: =-IF(AND(G40=0,F40>0),$C$24,0) -> 0 | H55: =-IF(AND(H40=0,G40>0),$C$24,0) -> 0 | I55: =-IF(AND(I40=0,H40>0),$C$24,0) -> 0 | J55: =-IF(AND(J40=0,I40>0),$C$24,0) -> 0 | K55: =-IF(AND(K40=0,J40>0),$C$24,0) -> -15 | L55: =-IF(AND(L40=0,K40>0),$C$24,0) -> 0 | M55: =-IF(AND(M40=0,L40>0),$C$24,0) -> 0 | N55: =-IF(AND(N40=0,M40>0),$C$24,0) -> 0 | ... AC55: =-IF(AND(AC40=0,AB40>0),$C$24,0) -> 0
B56: Cash taxes | C56: US$M | D56: =SUM(F56:AC56) -> -63.957403 | F56: =-MAX(0,(F52+F53+F54)*$C$26) -> -20.528325 | G56: =-MAX(0,(G52+G53+G54)*$C$26) -> -16.490762 | H56: =-MAX(0,(H52+H53+H54)*$C$26) -> -12.453198 | I56: =-MAX(0,(I52+I53+I54)*$C$26) -> -12.453198 | J56: =-MAX(0,(J52+J53+J54)*$C$26) -> -2.031919 | K56: =-MAX(0,(K52+K53+K54)*$C$26) -> 0 | L56: =-MAX(0,(L52+L53+L54)*$C$26) -> 0 | M56: =-MAX(0,(M52+M53+M54)*$C$26) -> 0 | ... AC56: =-MAX(0,(AC52+AC53+AC54)*$C$26) -> 0
B57: Unlevered free cash flow | C57: US$M | D57: =SUM(F57:AC57) -> 109.15261 | F57: =SUM(F52:F56) -> 39.849102 | G57: =SUM(G52:G56) -> 32.011479 | H57: =SUM(H52:H56) -> 24.173856 | I57: =SUM(I52:I56) -> 24.173856 | J57: =SUM(J52:J56) -> 3.9443134 | K57: =SUM(K52:K56) -> -15 | L57: =SUM(L52:L56) -> 0 | M57: =SUM(M52:M56) -> 0 | ... AC57: =SUM(AC52:AC56) -> 0
B58: Discount factor (mid-year) | F58: =1/(1+$C$31)^(F35-0.5) -> 0.97590007 | G58: =1/(1+$C$31)^(G35-0.5) -> 0.92942864 | H58: =1/(1+$C$31)^(H35-0.5) -> 0.88517013 | I58: =1/(1+$C$31)^(I35-0.5) -> 0.84301918 | J58: =1/(1+$C$31)^(J35-0.5) -> 0.80287541 | K58: =1/(1+$C$31)^(K35-0.5) -> 0.76464324 | L58: =1/(1+$C$31)^(L35-0.5) -> 0.72823166 | M58: =1/(1+$C$31)^(M35-0.5) -> 0.69355396 | ... AC58: =1/(1+$C$31)^(AC35-0.5) -> 0.31772506
B59: PV of free cash flow | C59: US$M | D59: =SUM(F59:AC59) -> 102.11527 | F59: =F57*F58 -> 38.888742 | G59: =G57*G58 -> 29.752385 | H59: =H57*H58 -> 21.397975 | I59: =I57*I58 -> 20.379024 | J59: =J57*J58 -> 3.1667922 | K59: =K57*K58 -> -11.469649 | L59: =L57*L58 -> 0 | M59: =M57*M58 -> 0 | ... AC59: =AC57*AC58 -> 0
B61: Asset summary
B62: NPV (100% basis) | C62: =SUM(F59:AC59) -> 102.11527 | D62: US$M
B63: Attributable NAV | C63: =C62*$C$5 -> 99.664503 | D63: US$M
B64: Remaining mine life | C64: =COUNTIF(F40:AC40,">0") -> 5 | D64: years
B65: AISC 2027, by-product | C65: =IFERROR((-(F49+F50+F51+F53)-F46)/F43*1000,0) -> 2397.579 | D65: US$/oz Au
B66: AISC life of mine, by-product | C66: =IFERROR((-(D49+D50+D51+D53)-D46)/D43*1000,0) -> 2478.0662 | D66: US$/oz Au

Sheet Corporate_NAV
B1: Corporate NAV and financial summary
B2: Sum of attributable asset NAVs plus corporate items. P/NAV uses the spot share price and spot CAD/USD.
B4: US$M unless noted | C4: Centerra (CG) | D4: Ero (ERO) | G4: Note
B5: Mount Milligan NAV | C5: =MtMilligan!$C$63 -> 927.73859 | D5: 0
B6: Öksüt NAV | C6: =Oksut!$C$63 -> 297.7909 | D6: 0
B7: Goldfield NAV | C7: =Goldfield!$C$63 -> 239.48767 | D7: 0
B8: Caraíba NAV | C8: 0 | D8: =Caraiba!$C$63 -> 970.67724
B9: Tucumã NAV | C9: 0 | D9: =Tucuma!$C$63 -> 936.15474
B10: Xavantina NAV | C10: 0 | D10: =Xavantina!$C$63 -> 99.664503
B11: Total attributable asset NAV | C11: =SUM(C5:C10) -> 1465.0172 | D11: =SUM(D5:D10) -> 2006.4965
B12: Corporate G&A (capitalised) | C12: =-50*(1-(1+Inputs!$C$31)^-Inputs!$C$30)/Inputs!$C$31 -> -386.08675 | D12: =-40*(1-(1+Inputs!$C$31)^-Inputs!$C$30)/Inputs!$C$31 -> -308.8694 | G12: G&A (US$M/yr, data/corporate.csv) x annuity factor
B13: Other assets and exploration | C13: 200 | D13: 100 | G13: CG: Molybdenum business (Langeloth, Thompson Creek), Kemess and exploration; ERO: Furnas earn-in and regional exploration
B14: Hedge book mark-to-market | C14: 0 | D14: 0 | G14: Neither company has a material hedge book
B15: Cash and equivalents | C15: =Market!$G$5 -> 453.10301 | D15: =Market!$G$6 -> 101.742 | G15: Market tab
B16: Debt | C16: =-Market!$H$5 -> -45.762 | D16: =-Market!$H$6 -> -573.35501 | G16: Market tab
B17: Net asset value | C17: =SUM(C11:C16) -> 1686.2714 | D17: =SUM(D11:D16) -> 1326.0141
B18: Shares outstanding (M) | C18: =Market!$E$5 -> 198.59506 | D18: =Market!$E$6 -> 104.30263 | G18: Basic shares; Market tab
B19: NAV per share (US$) | C19: =C17/C18 -> 8.4910041 | D19: =D17/D18 -> 12.713141
B20: NAV per share (C$) | C20: =C19/Inputs!$C$7 -> 11.890497 | D20: =D19/Inputs!$C$7 -> 17.803026
B21: Share price (C$) | C21: =Market!$D$5 -> 28.32 | D21: =Market!$D$6 -> 42.03
B22: P/NAV | C22: =C21/C20 -> 2.3817339 | D22: =D21/D20 -> 2.3608346
B24: Financial summary (feeds the accretion/dilution analysis)
B25: US$M unless noted | C25: CG 2027E | D25: CG 2028E | E25: ERO 2027E | F25: ERO 2028E
B26: Payable copper (Mlb, attributable) | C26: =MtMilligan!F42*MtMilligan!$C$5+Oksut!F42*Oksut!$C$5+Goldfield!F42*Goldfield!$C$5 -> 58.547652 | D26: =MtMilligan!G42*MtMilligan!$C$5+Oksut!G42*Oksut!$C$5+Goldfield!G42*Goldfield!$C$5 -> 58.547652 | E26: =Caraiba!F42*Caraiba!$C$5+Tucuma!F42*Tucuma!$C$5+Xavantina!F42*Xavantina!$C$5 -> 142.69905 | F26: =Caraiba!G42*Caraiba!$C$5+Tucuma!G42*Tucuma!$C$5+Xavantina!G42*Xavantina!$C$5 -> 142.69905
B27: Payable gold (koz, attributable) | C27: =MtMilligan!F43*MtMilligan!$C$5+Oksut!F43*Oksut!$C$5+Goldfield!F43*Goldfield!$C$5 -> 235.14511 | D27: =MtMilligan!G43*MtMilligan!$C$5+Oksut!G43*Oksut!$C$5+Goldfield!G43*Goldfield!$C$5 -> 235.14511 | E27: =Caraiba!F43*Caraiba!$C$5+Tucuma!F43*Tucuma!$C$5+Xavantina!F43*Xavantina!$C$5 -> 39.222275 | F27: =Caraiba!G43*Caraiba!$C$5+Tucuma!G43*Tucuma!$C$5+Xavantina!G43*Xavantina!$C$5 -> 39.222275
B28: Revenue | C28: =MtMilligan!F48*MtMilligan!$C$5+Oksut!F48*Oksut!$C$5+Goldfield!F48*Goldfield!$C$5 -> 1066.6486 | D28: =MtMilligan!G48*MtMilligan!$C$5+Oksut!G48*Oksut!$C$5+Goldfield!G48*Goldfield!$C$5 -> 984.11298 | E28: =Caraiba!F48*Caraiba!$C$5+Tucuma!F48*Tucuma!$C$5+Xavantina!F48*Xavantina!$C$5 -> 1009.1612 | F28: =Caraiba!G48*Caraiba!$C$5+Tucuma!G48*Tucuma!$C$5+Xavantina!G48*Xavantina!$C$5 -> 926.04498
B29: Mine EBITDA | C29: =MtMilligan!F52*MtMilligan!$C$5+Oksut!F52*Oksut!$C$5+Goldfield!F52*Goldfield!$C$5 -> 552.17503 | D29: =MtMilligan!G52*MtMilligan!$C$5+Oksut!G52*Oksut!$C$5+Goldfield!G52*Goldfield!$C$5 -> 472.39916 | E29: =Caraiba!F52*Caraiba!$C$5+Tucuma!F52*Tucuma!$C$5+Xavantina!F52*Xavantina!$C$5 -> 608.49413 | F29: =Caraiba!G52*Caraiba!$C$5+Tucuma!G52*Tucuma!$C$5+Xavantina!G52*Xavantina!$C$5 -> 526.98141
B30: Corporate G&A | C30: -50 | D30: -50 | E30: -40 | F30: -40
B31: EBITDA | C31: =C29+C30 -> 502.17503 | D31: =D29+D30 -> 422.39916 | E31: =E29+E30 -> 568.49413 | F31: =F29+F30 -> 486.98141
B32: Depreciation and amortisation | C32: -190 | D32: -200 | E32: -175 | F32: -180 | G32: data/corporate.csv (estimate)
B33: Interest expense | C33: =C$16*0.06 -> -2.74572 | D33: =C$16*0.06 -> -2.74572 | E33: =D$16*0.065 -> -37.268076 | F33: =D$16*0.065 -> -37.268076 | G33: Debt x coupon (data/corporate.csv)
B34: Pre-tax income | C34: =C31+C32+C33 -> 309.42931 | D34: =D31+D32+D33 -> 219.65344 | E34: =E31+E32+E33 -> 356.22606 | F34: =F31+F32+F33 -> 269.71334
B35: Income tax | C35: =-MAX(0,C34)*0.28 -> -86.640206 | D35: =-MAX(0,D34)*0.28 -> -61.502962 | E35: =-MAX(0,E34)*0.2 -> -71.245211 | F35: =-MAX(0,F34)*0.2 -> -53.942667 | G35: Book tax at effective rate (data/corporate.csv)
B36: Net income | C36: =C34+C35 -> 222.7891 | D36: =D34+D35 -> 158.15047 | E36: =E34+E35 -> 284.98084 | F36: =F34+F35 -> 215.77067
B37: EPS (US$) | C37: =C36/C$18 -> 1.121826 | D37: =D36/C$18 -> 0.79634649 | E37: =E36/D$18 -> 2.7322498 | F37: =F36/D$18 -> 2.0686982
B38: Cash taxes (asset level) | C38: =MtMilligan!F56*MtMilligan!$C$5+Oksut!F56*Oksut!$C$5+Goldfield!F56*Goldfield!$C$5 -> -105.51489 | D38: =MtMilligan!G56*MtMilligan!$C$5+Oksut!G56*Oksut!$C$5+Goldfield!G56*Goldfield!$C$5 -> -82.208238 | E38: =Caraiba!F56*Caraiba!$C$5+Tucuma!F56*Tucuma!$C$5+Xavantina!F56*Xavantina!$C$5 -> -76.540824 | F38: =Caraiba!G56*Caraiba!$C$5+Tucuma!G56*Tucuma!$C$5+Xavantina!G56*Xavantina!$C$5 -> -71.086975
B39: Operating cash flow | C39: =C31+C33+C38 -> 393.91442 | D39: =D31+D33+D38 -> 337.4452 | E39: =E31+E33+E38 -> 454.68523 | F39: =F31+F33+F38 -> 378.62636
B40: CFPS (US$) | C40: =C39/C$18 -> 1.9835057 | D40: =D39/C$18 -> 1.6991621 | E40: =E39/D$18 -> 4.3592881 | F40: =F39/D$18 -> 3.6300748

Sheet Comps
B1: Trading comparables
B2: Multiples are live formulas on the Market tab. Peer statistics exclude Centerra and Ero. Peer reserves are estimates (data/peer_inputs.csv); P/NAV shown only where a NAV is available.
B4: Ticker | C4: Company | D4: Role | E4: Price (C$) | F4: Mkt cap (US$M) | G4: EV (US$M) | H4: EV / EBITDA (TTM) | I4: P / CF (TTM) | J4: P / NAV | K4: Price / target | L4: P&P reserves (Mt CuEq) | M4: EV / lb CuEq reserve (US$)
B5: CG.TO | C5: =Market!$C$5 -> Centerra Gold | D5: acquirer | E5: =Market!$D$5 -> 28.32 | F5: =Market!$F$5 -> 4016.1465 | G5: =Market!$I$5 -> 3608.8055 | H5: =IFERROR(Market!$I$5/Market!$J$5,"n/a") -> 4.1964775 | I5: =IFERROR(Market!$F$5/Market!$K$5,"n/a") -> 8.9051784 | J5: =CG_PNAV -> 2.3817339 | K5: =IFERROR(Market!$D$5/Market!$P$5,"n/a") -> 0.84225496 | L5: =(MtMilligan!$C$6-MtMilligan!$C$7)*MtMilligan!$C$8+(MtMilligan!$C$6-MtMilligan!$C$7)*MtMilligan!$C$9/31.1035*(Inputs!$AC$17/(Inputs!$AC$16*2204.62))+(Oksut!$C$6-Oksut!$C$7)*Oksut!$C$8+(Oksut!$C$6-Oksut!$C$7)*Oksut!$C$9/31.1035*(Inputs!$AC$17/(Inputs!$AC$16*2204.62))+(Goldfield!$C$6-Goldfield!$C$7)*Goldfield!$C$8+(Goldfield!$C$6-Goldfield!$C$7)*Goldfield!$C$9/31.1035*(Inputs!$AC$17/(Inputs!$AC$16*2204.62)) -> 2.2412375 | M5: =IFERROR(G5/(L5*2204.62),"n/a") -> 0.7303682
B6: ERO.TO | C6: =Market!$C$6 -> Ero Copper | D6: target | E6: =Market!$D$6 -> 42.03 | F6: =Market!$F$6 -> 3130.4194 | G6: =Market!$I$6 -> 3602.0324 | H6: =IFERROR(Market!$I$6/Market!$J$6,"n/a") -> 6.9668306 | I6: =IFERROR(Market!$F$6/Market!$K$6,"n/a") -> 6.6596308 | J6: =ERO_PNAV -> 2.3608346 | K6: =IFERROR(Market!$D$6/Market!$P$6,"n/a") -> 0.73953357 | L6: =(Caraiba!$C$6-Caraiba!$C$7)*Caraiba!$C$8+(Caraiba!$C$6-Caraiba!$C$7)*Caraiba!$C$9/31.1035*(Inputs!$AC$17/(Inputs!$AC$16*2204.62))+(Tucuma!$C$6-Tucuma!$C$7)*Tucuma!$C$8+(Tucuma!$C$6-Tucuma!$C$7)*Tucuma!$C$9/31.1035*(Inputs!$AC$17/(Inputs!$AC$16*2204.62))+(Xavantina!$C$6-Xavantina!$C$7)*Xavantina!$C$8+(Xavantina!$C$6-Xavantina!$C$7)*Xavantina!$C$9/31.1035*(Inputs!$AC$17/(Inputs!$AC$16*2204.62)) -> 0.98172973 | M6: =IFERROR(G6/(L6*2204.62),"n/a") -> 1.6642629
B7: CS.TO | C7: =Market!$C$7 -> Capstone Copper | D7: peer | E7: =Market!$D$7 -> 11.19 | F7: =Market!$F$7 -> 6104.3934 | G7: =Market!$I$7 -> 7300.8924 | H7: =IFERROR(Market!$I$7/Market!$J$7,"n/a") -> 7.4066292 | I7: =IFERROR(Market!$F$7/Market!$K$7,"n/a") -> 7.3791668 | J7: n/a | K7: =IFERROR(Market!$D$7/Market!$P$7,"n/a") -> 0.62135599 | L7: 7 | M7: =IFERROR(G7/(L7*2204.62),"n/a") -> 0.47309043
B8: TXG.TO | C8: =Market!$C$8 -> Torex Gold | D8: peer | E8: =Market!$D$8 -> 67.14 | F8: =Market!$F$8 -> 4439.3034 | G8: =Market!$I$8 -> 4369.3034 | H8: =IFERROR(Market!$I$8/Market!$J$8,"n/a") -> 4.1088052 | I8: =IFERROR(Market!$F$8/Market!$K$8,"n/a") -> 5.4907899 | J8: n/a | K8: =IFERROR(Market!$D$8/Market!$P$8,"n/a") -> 0.70451207 | L8: 1.35 | M8: =IFERROR(G8/(L8*2204.62),"n/a") -> 1.468063
B9: OGC.TO | C9: =Market!$C$9 -> OceanaGold | D9: peer | E9: =Market!$D$9 -> 34.67 | F9: =Market!$F$9 -> 5507.1802 | G9: =Market!$I$9 -> 4902.4802 | H9: =IFERROR(Market!$I$9/Market!$J$9,"n/a") -> 3.4127952 | I9: =IFERROR(Market!$F$9/Market!$K$9,"n/a") -> 4.2997971 | J9: n/a | K9: =IFERROR(Market!$D$9/Market!$P$9,"n/a") -> 0.60848111 | L9: 1.8 | M9: =IFERROR(G9/(L9*2204.62),"n/a") -> 1.2354057
B10: SSRM.TO | C10: =Market!$C$10 -> SSR Mining | D10: peer | E10: =Market!$D$10 -> 39.75 | F10: =Market!$F$10 -> 5889.5812 | G10: =Market!$I$10 -> 4057.9172 | H10: =IFERROR(Market!$I$10/Market!$J$10,"n/a") -> 4.6981425 | I10: =IFERROR(Market!$F$10/Market!$K$10,"n/a") -> 9.869395 | J10: n/a | K10: =IFERROR(Market!$D$10/Market!$P$10,"n/a") -> 0.68403241 | L10: 2.7 | M10: =IFERROR(G10/(L10*2204.62),"n/a") -> 0.68171943
B11: HBM.TO | C11: =Market!$C$11 -> Hudbay Minerals | D11: peer | E11: =Market!$D$11 -> 30.76 | F11: =Market!$F$11 -> 9755.7069 | G11: =Market!$I$11 -> 9909.3069 | H11: =IFERROR(Market!$I$11/Market!$J$11,"n/a") -> 8.6423404 | I11: =IFERROR(Market!$F$11/Market!$K$11,"n/a") -> 11.741133 | J11: n/a | K11: =IFERROR(Market!$D$11/Market!$P$11,"n/a") -> 0.68048421 | L11: 7.5 | M11: =IFERROR(G11/(L11*2204.62),"n/a") -> 0.59930551
B12: LUN.TO | C12: =Market!$C$12 -> Lundin Mining | D12: peer | E12: =Market!$D$12 -> 29.5 | F12: =Market!$F$12 -> 17934.237 | G12: =Market!$I$12 -> 18057.037 | H12: =IFERROR(Market!$I$12/Market!$J$12,"n/a") -> 8.290651 | I12: =IFERROR(Market!$F$12/Market!$K$12,"n/a") -> 10.064671 | J12: n/a | K12: =IFERROR(Market!$D$12/Market!$P$12,"n/a") -> 0.68673743 | L12: 7.5 | M12: =IFERROR(G12/(L12*2204.62),"n/a") -> 1.0920725
B13: ELD.TO | C13: =Market!$C$13 -> Eldorado Gold | D13: peer | E13: =Market!$D$13 -> 44.32 | F13: =Market!$F$13 -> 8254.1511 | G13: =Market!$I$13 -> 9462.7241 | H13: =IFERROR(Market!$I$13/Market!$J$13,"n/a") -> 8.2211929 | I13: =IFERROR(Market!$F$13/Market!$K$13,"n/a") -> 11.091263 | J13: n/a | K13: =IFERROR(Market!$D$13/Market!$P$13,"n/a") -> 0.6759501 | L13: 3.9 | M13: =IFERROR(G13/(L13*2204.62),"n/a") -> 1.1005704
B14: DPM.TO | C14: =Market!$C$14 -> DPM Metals | D14: peer | E14: =Market!$D$14 -> 56.02 | F14: =Market!$F$14 -> 8775.372 | G14: =Market!$I$14 -> 8022.576 | H14: =IFERROR(Market!$I$14/Market!$J$14,"n/a") -> 9.3320603 | I14: =IFERROR(Market!$F$14/Market!$K$14,"n/a") -> 11.422176 | J14: n/a | K14: =IFERROR(Market!$D$14/Market!$P$14,"n/a") -> 0.80299882 | L14: 1.4 | M14: =IFERROR(G14/(L14*2204.62),"n/a") -> 2.599274
B15: IMG.TO | C15: =Market!$C$15 -> IAMGOLD | D15: peer | E15: =Market!$D$15 -> 22.72 | F15: =Market!$F$15 -> 9263.8669 | G15: =Market!$I$15 -> 9301.2669 | H15: =IFERROR(Market!$I$15/Market!$J$15,"n/a") -> 4.534991 | I15: =IFERROR(Market!$F$15/Market!$K$15,"n/a") -> 4.6377305 | J15: n/a | K15: =IFERROR(Market!$D$15/Market!$P$15,"n/a") -> 0.66844939 | L15: 3.9 | M15: =IFERROR(G15/(L15*2204.62),"n/a") -> 1.081792
B16: EQX.TO | C16: =Market!$C$16 -> Equinox Gold | D16: peer | E16: =Market!$D$16 -> 14.13 | F16: =Market!$F$16 -> 11779.639 | G16: =Market!$I$16 -> 12137.116 | H16: =IFERROR(Market!$I$16/Market!$J$16,"n/a") -> 7.1844248 | I16: =IFERROR(Market!$F$16/Market!$K$16,"n/a") -> 10.996039 | J16: n/a | K16: =IFERROR(Market!$D$16/Market!$P$16,"n/a") -> 0.57735451 | L16: 6 | M16: =IFERROR(G16/(L16*2204.62),"n/a") -> 0.91755161
B18: Peer mean | H18: =IFERROR(AVERAGE(H7:H16),"n/a") -> 6.5832032 | I18: =IFERROR(AVERAGE(I7:I16),"n/a") -> 8.699216 | J18: =IFERROR(AVERAGE(J7:J16),"n/a") -> n/a | K18: =IFERROR(AVERAGE(K7:K16),"n/a") -> 0.6710356 | M18: =IFERROR(AVERAGE(M7:M16),"n/a") -> 1.1248845
B19: Peer median | H19: =IFERROR(MEDIAN(H7:H16),"n/a") -> 7.295527 | I19: =IFERROR(MEDIAN(I7:I16),"n/a") -> 9.9670328 | J19: =IFERROR(MEDIAN(J7:J16),"n/a") -> n/a | K19: =IFERROR(MEDIAN(K7:K16),"n/a") -> 0.67821716 | M19: =IFERROR(MEDIAN(M7:M16),"n/a") -> 1.0869322
B20: Peer 25th percentile | H20: =IFERROR(QUARTILE(H7:H16,1),"n/a") -> 4.5757789 | I20: =IFERROR(QUARTILE(I7:I16,1),"n/a") -> 5.9628841 | J20: =IFERROR(QUARTILE(J7:J16,1),"n/a") -> n/a | K20: =IFERROR(QUARTILE(K7:K16,1),"n/a") -> 0.63312934 | M20: =IFERROR(QUARTILE(M7:M16,1),"n/a") -> 0.74067748
B21: Peer 75th percentile | H21: =IFERROR(QUARTILE(H7:H16,3),"n/a") -> 8.2732865 | I21: =IFERROR(QUARTILE(I7:I16,3),"n/a") -> 11.067457 | J21: =IFERROR(QUARTILE(J7:J16,3),"n/a") -> n/a | K21: =IFERROR(QUARTILE(K7:K16,3),"n/a") -> 0.68606118 | M21: =IFERROR(QUARTILE(M7:M16,3),"n/a") -> 1.2016969
B23: Notes
B24: TTM EBITDA and operating cash flow from yfinance (latest reported); EV = market cap + debt - cash.
B25: P/NAV for Centerra and Ero links to the model's reserve-only NAV at the analyst deck (Corporate_NAV).
B26: Peer P/NAV needs a consensus NAV per share in data/peer_inputs.csv; none is published for free, so it shows n/a.
B27: Price / target uses the yfinance mean analyst target as a market-based cross-check.
B28: CuEq converts gold at the long-term deck ratio (gold price / copper price per tonne).

Sheet Precedents
B1: Precedent transactions — copper and gold M&A, 2021–2025
B2: Premium to the target's undisturbed price at announcement, from company press releases. Blank = not disclosed or not yet verified.
B4: Announced | C4: Acquirer | D4: Target | E4: Metal | F4: Consideration | G4: Equity value (US$M) | H4: Premium | I4: P/NAV at ann. | J4: Reserves (Moz AuEq) | K4: Value / reserve oz (US$) | L4: Status
B5: 2025-11-03 | C5: Coeur Mining | D5: New Gold | E5: gold-copper | F5: All-stock | G5: 7000 | H5: 0.16 | K5: =IF(J5>0,G5/J5,"n/a") -> n/a | L5: premium and value as reported in announcement; verify | M5: https://www.coeur.com/investors/news
B6: 2025-05-27 | C6: Harmony Gold | D6: MAC Copper | E6: copper | F6: All-cash | G6: 1030 | H6: 0.31 | I6: 1.26 | K6: =IF(J6>0,G6/J6,"n/a") -> n/a | L6: P/NAV per FactSet; premium as reported; verify | M6: https://insight.factset.com/metals-mining-2025-ma-and-equity-capital-markets-insights
B7: 2025-02-23 | C7: Equinox Gold | D7: Calibre Mining | E7: gold | F7: All-stock | G7: 1800 | H7: 0.31 | K7: =IF(J7>0,G7/J7,"n/a") -> n/a | L7: premium as reported (20-day VWAP basis); verify | M7: https://www.equinoxgold.com/news
B8: 2024-12-02 | C8: Northern Star Resources | D8: De Grey Mining | E8: gold | F8: All-stock | G8: 3300 | H8: 0.37 | J8: 6 | K8: =IF(J8>0,G8/J8,"n/a") -> 550 | L8: premium as reported; reserves = Hemi PFS/DFS; verify | M8: https://www.nsrltd.com/investor-and-media/asx-announcements
B9: 2024-08-12 | C9: Gold Fields | D9: Osisko Mining | E9: gold | F9: All-cash | G9: 1570 | H9: 0.55 | J9: 3.5 | K9: =IF(J9>0,G9/J9,"n/a") -> 448.57143 | L9: premium as reported; reserves = Windfall FS; verify | M9: https://www.goldfields.com/press-releases.php
B10: 2024-07-29 | C10: BHP / Lundin Mining | D10: Filo Corp | E10: copper-gold | F10: Cash and stock | G10: 3250 | H10: 0.32 | K10: =IF(J10>0,G10/J10,"n/a") -> n/a | L10: premium to 30-day VWAP as reported; no reserves at announcement; verify | M10: https://www.lundinmining.com/news
B11: 2023-05-14 | C11: Newmont | D11: Newcrest Mining | E11: gold-copper | F11: All-stock | G11: 19200 | H11: 0.3 | K11: =IF(J11>0,G11/J11,"n/a") -> n/a | L11: premium to undisturbed price as reported; verify | M11: https://www.newmont.com/investors/news-release
B12: 2023-04-13 | C12: Hudbay Minerals | D12: Copper Mountain Mining | E12: copper | F12: All-stock | G12: 439 | H12: 0.23 | K12: =IF(J12>0,G12/J12,"n/a") -> n/a | L12: premium as reported; verify | M12: https://hudbayminerals.com/investors/news
B13: 2021-12-20 | C13: Lundin Mining | D13: Josemaria Resources | E13: copper-gold | F13: Cash and stock | G13: 485 | H13: 0.39 | K13: =IF(J13>0,G13/J13,"n/a") -> n/a | L13: premium as reported; verify | M13: https://www.lundinmining.com/news
B15: Mean | H15: =IFERROR(AVERAGE(H5:H13),"n/a") -> 0.32666667 | I15: =IFERROR(AVERAGE(I5:I13),"n/a") -> 1.26 | K15: =IFERROR(AVERAGE(K5:K13),"n/a") -> 499.28571
B16: Median | H16: =IFERROR(MEDIAN(H5:H13),"n/a") -> 0.31 | I16: =IFERROR(MEDIAN(I5:I13),"n/a") -> 1.26 | K16: =IFERROR(MEDIAN(K5:K13),"n/a") -> 499.28571
B17: 25th percentile | H17: =IFERROR(QUARTILE(H5:H13,1),"n/a") -> 0.3 | I17: =IFERROR(QUARTILE(I5:I13,1),"n/a") -> 1.26 | K17: =IFERROR(QUARTILE(K5:K13,1),"n/a") -> 473.92857
B18: 75th percentile | H18: =IFERROR(QUARTILE(H5:H13,3),"n/a") -> 0.37 | I18: =IFERROR(QUARTILE(I5:I13,3),"n/a") -> 1.26 | K18: =IFERROR(QUARTILE(K5:K13,3),"n/a") -> 524.64286
B20: Benchmarks
B21: FactSet: gold targets acquired in 2025 averaged ~0.73x consensus P/NAV (13 deals); ten-year average ~0.8x.
B22: FactSet: Harmony / MAC Copper implied 1.26x P/NAV and Anglo / Teck 1.22x, the highest since BHP's bid for Anglo.
B23: Source: insight.factset.com/metals-mining-2025-ma-and-equity-capital-markets-insights

Sheet Synergies
B1: Run-rate synergy case
B2: Pre-tax, US$M per year at run-rate. Basis for each line in column E.
B4: Category | C4: Run-rate (US$M) | E4: Basis
B5: Corporate G&A | C5: 45 | E5: One head office, board, listing and IT: removes ~50% of combined US$90M corporate G&A
B6: Procurement and concentrate marketing | C6: 65 | E6: ~6% of the combined ~US$1.1Bn site cash cost and sustaining capex base (reagents, energy, grinding media, freight, smelter terms)
B7: Operational and technical services | C7: 45 | E7: Shared technical services and fleet maintenance practices across six sites; exploration budget rationalisation
B8: Total run-rate synergies | C8: =SUM(C5:C7) -> 155
B10: Phase-in and value | C10: Value | E10: Note
B11: Synergies 2027E (pre-tax) | C11: =SYN_RUNRATE*DEAL_PHASE_Y1 -> 77.5 | E11: Run-rate x year-1 phase-in
B12: Synergies 2028E (pre-tax) | C12: =SYN_RUNRATE*DEAL_PHASE_Y2 -> 155 | E12: Run-rate x year-2 phase-in
B13: One-off integration costs | C13: =SYN_RUNRATE*DEAL_INTEGRATION_X -> 155 | E13: Cost to achieve; excluded from EPS and CFPS, deducted from NAV
B14: NPV of after-tax synergies, net of integration costs | C14: =SYN_RUNRATE*(1-DEAL_TAX)*((1-(1+DEAL_SYN_RATE)^-DEAL_SYN_YEARS)/DEAL_SYN_RATE)*(1+DEAL_SYN_RATE)^0.5-SYN_RUNRATE*(1-DEAL_PHASE_Y1)*(1-DEAL_TAX)/(1+DEAL_SYN_RATE)^0.5-SYN_INTEGRATION -> 629.61464 | E14: Mid-year annuity over the capitalisation period, less the year-1 phase-in shortfall
B15: Capitalised value per pro forma share (US$) | C15: =SYN_NPV/PF_SHARES -> 1.8013605

Sheet Merger
B1: Pro forma merger model — Centerra acquires Ero
B2: Offer structure, funding, pro forma ownership and accretion/dilution to EPS, CFPS and NAVPS.
B4: Deal inputs (data/deal_assumptions.csv) | C4: Value | F4: Note
B5: Offer premium to unaffected price | C5: 0.3 | E5: In line with the 30–31% precedent median
B6: Consideration (1 = all-stock, 2 = cash-and-stock) | C6: 2 | E6: Toggle
B7: Cash portion when cash-and-stock | C7: 0.25 | E7: Applies when consideration_case = 2
B8: Minimum pro forma cash (US$M) | C8: 250 | E8: Minimum pro forma cash balance before drawing new debt
B9: Cost of new acquisition debt | C9: 0.06 | E9: Cost of acquisition debt (term loan / notes)
B10: Yield forgone on cash used | C10: 0.035 | E10: Interest income forgone on cash used
B11: Transaction costs (US$M) | C11: 60 | E11: Advisory, legal and financing fees
B12: Tax rate on synergies and financing | C12: 0.27 | E12: Tax rate applied to synergies and financing effects
B13: Synergy phase-in, 2027E | C13: 0.5 | E13: 2027E
B14: Synergy phase-in, 2028E | C14: 1 | E14: 2028E onward
B15: Integration cost (x run-rate) | C15: 1 | E15: One-off cost to achieve (excluded from EPS)
B16: Synergy capitalisation (years) | C16: 10 | E16: Years of synergies capitalised in pro forma NAV
B17: Synergy discount rate | C17: 0.065 | E17: Blended copper-gold rate
B19: Offer and funding | C19: Value | F19: Note
B20: Ero unaffected share price (C$) | C20: =ERO_PRICE_CAD -> 42.03 | E20: Market tab
B21: Offer price per Ero share (C$) | C21: =DEAL_UNAFFECTED*(1+DEAL_PREMIUM) -> 54.639
B22: Cash portion applied | C22: =IF(DEAL_CASE=1,0,DEAL_CASH_PCT_INPUT) -> 0.25
B23: Cash per Ero share (C$) | C23: =DEAL_OFFER_CAD*DEAL_CASH_PCT -> 13.65975
B24: Exchange ratio (CG shares per Ero share) | C24: =DEAL_OFFER_CAD*(1-DEAL_CASH_PCT)/CG_PRICE_CAD -> 1.4470074 | E24: Fixed at Centerra's unaffected price
B25: New Centerra shares issued (M) | C25: =ERO_SHARES*DEAL_ER -> 150.92668
B26: Equity purchase price (US$M) | C26: =DEAL_OFFER_CAD*ERO_SHARES*FX_SPOT -> 4069.6499 | E26: At spot CAD/USD
B27: of which cash (US$M) | C27: =DEAL_EQUITY_USD*DEAL_CASH_PCT -> 1017.4125
B28: of which stock (US$M) | C28: =DEAL_EQUITY_USD-DEAL_CASH_USD -> 3052.2374
B29: Ero net debt assumed (US$M) | C29: =-(ERO_DEBT+ERO_CASH) -> 471.61301 | E29: Debt less cash
B30: Implied enterprise value (US$M) | C30: =DEAL_EQUITY_USD+DEAL_NET_DEBT -> 4541.2629
B31: Implied P/NAV (offer / Ero NAVPS) | C31: =DEAL_OFFER_CAD/ERO_NAVPS_CAD -> 3.069085 | E31: Reserve-only NAV at the analyst deck
B32: Implied EV / 2027E EBITDA | C32: =DEAL_EV_USD/ERO_EBITDA_2027 -> 7.9882318
B33: Cash required: consideration + costs (US$M) | C33: =DEAL_CASH_USD+DEAL_TXN_COSTS -> 1077.4125
B34: Funded from balance sheet cash (US$M) | C34: =MIN(DEAL_CASH_NEED,MAX(0,CG_CASH+ERO_CASH-DEAL_MIN_CASH)) -> 304.84501 | E34: Combined cash above the minimum balance
B35: Funded from new debt (US$M) | C35: =DEAL_CASH_NEED-DEAL_CASH_USED -> 772.56746
B37: Pro forma ownership | C37: Value
B38: Centerra shares outstanding (M) | C38: =CG_SHARES -> 198.59506
B39: Pro forma shares outstanding (M) | C39: =CG_SHARES+DEAL_NEW_SHARES -> 349.52174
B40: Centerra shareholders | C40: =CG_SHARES/PF_SHARES -> 0.56819085
B41: Ero shareholders | C41: =DEAL_NEW_SHARES/PF_SHARES -> 0.43180915
B43: Accretion / dilution (US$M unless noted) | C43: 2027E | D43: 2028E | F43: Note
B44: Centerra standalone net income | C44: =CG_NI_2027 -> 222.7891 | D44: =CG_NI_2028 -> 158.15047
B45: Ero standalone net income | C45: =ERO_NI_2027 -> 284.98084 | D45: =ERO_NI_2028 -> 215.77067
B46: Pre-tax synergies | C46: =SYN_2027 -> 77.5 | D46: =SYN_2028 -> 155
B47: After-tax synergies | C47: =PF_SYN_2027*(1-DEAL_TAX) -> 56.575 | D47: =PF_SYN_2028*(1-DEAL_TAX) -> 113.15
B48: After-tax interest on new debt | C48: =-DEAL_NEW_DEBT*DEAL_DEBT_RATE*(1-DEAL_TAX) -> -33.838455 | D48: =-DEAL_NEW_DEBT*DEAL_DEBT_RATE*(1-DEAL_TAX) -> -33.838455
B49: After-tax interest forgone on cash | C49: =-DEAL_CASH_USED*DEAL_CASH_YIELD*(1-DEAL_TAX) -> -7.78879 | D49: =-DEAL_CASH_USED*DEAL_CASH_YIELD*(1-DEAL_TAX) -> -7.78879
B50: Pro forma net income | C50: =SA_NI_2027+ERO_NI_2027+PF_SYN_AT_2027+PF_DEBT_COST_2027+PF_CASH_COST_2027 -> 522.7177 | D50: =SA_NI_2028+ERO_NI_2028+PF_SYN_AT_2028+PF_DEBT_COST_2028+PF_CASH_COST_2028 -> 445.4439 | F50: Excludes one-off integration and transaction costs; no purchase price allocation step-up
B51: Centerra standalone EPS (US$) | C51: =CG_EPS_2027 -> 1.121826 | D51: =CG_EPS_2028 -> 0.79634649
B52: Pro forma EPS (US$) | C52: =PF_NI_2027/PF_SHARES -> 1.4955227 | D52: =PF_NI_2028/PF_SHARES -> 1.2744383
B53: EPS accretion / (dilution) | C53: =PF_EPS_2027/CG_EPS_2027-1 -> 0.33311466 | D53: =PF_EPS_2028/CG_EPS_2028-1 -> 0.60035656
B54: Pro forma operating cash flow | C54: =CG_CFO_2027+ERO_CFO_2027+PF_SYN_AT_2027+PF_DEBT_COST_2027+PF_CASH_COST_2027 -> 863.5474 | D54: =CG_CFO_2028+ERO_CFO_2028+PF_SYN_AT_2028+PF_DEBT_COST_2028+PF_CASH_COST_2028 -> 787.59432
B55: Centerra standalone CFPS (US$) | C55: =CG_CFPS_2027 -> 1.9835057 | D55: =CG_CFPS_2028 -> 1.6991621
B56: Pro forma CFPS (US$) | C56: =PF_CFO_2027/PF_SHARES -> 2.4706543 | D56: =PF_CFO_2028/PF_SHARES -> 2.2533486
B57: CFPS accretion / (dilution) | C57: =PF_CFPS_2027/CG_CFPS_2027-1 -> 0.24559985 | D57: =PF_CFPS_2028/CG_CFPS_2028-1 -> 0.32615277
B58: Pro forma EBITDA (incl. synergies) | C58: =CG_EBITDA_2027+ERO_EBITDA_2027+PF_SYN_2027 -> 1148.1692 | D58: =CG_EBITDA_2028+ERO_EBITDA_2028+PF_SYN_2028 -> 1064.3806
B60: NAV per share | C60: Value | F60: Note
B61: Centerra standalone NAV (US$M) | C61: =CG_NAV -> 1686.2714
B62: Ero standalone NAV (US$M) | C62: =ERO_NAV -> 1326.0141
B63: NPV of synergies, net of integration (US$M) | C63: =SYN_NPV -> 629.61464
B64: Less: cash consideration and transaction costs (US$M) | C64: =-DEAL_CASH_NEED -> -1077.4125 | E64: Paid from cash or new debt; either way it reduces NAV
B65: Pro forma NAV (US$M) | C65: =CG_NAV+ERO_NAV+SYN_NPV-DEAL_CASH_NEED -> 2564.4877
B66: Pro forma NAV per share (US$) | C66: =PF_NAV/PF_SHARES -> 7.3371336
B67: Centerra standalone NAVPS (US$) | C67: =CG_NAVPS_USD -> 8.4910041
B68: NAVPS accretion / (dilution) | C68: =PF_NAVPS/CG_NAVPS_USD-1 -> -0.1358933 | E68: The metric that matters most for miners
B69: NAVPS accretion before synergies | C69: =(CG_NAV+ERO_NAV-DEAL_CASH_NEED)/PF_SHARES/CG_NAVPS_USD-1 -> -0.34804258
B70: Pro forma net debt (US$M) | C70: =-(CG_CASH+ERO_CASH+CG_DEBT+ERO_DEBT)+DEAL_CASH_NEED -> 1141.6845 | E70: Combined net debt plus cash paid out
B71: Pro forma net debt / 2027E EBITDA | C71: =PF_NET_DEBT/PF_EBITDA_2027 -> 0.99435215

Sheet Contribution
B1: Contribution analysis
B2: What each company brings versus what its shareholders receive.
B4: Metric | C4: Centerra | D4: Ero | E4: Centerra % | F4: Ero %
B5: Net asset value (US$M) | C5: =CG_NAV -> 1686.2714 | D5: =ERO_NAV -> 1326.0141 | E5: =C5/(C5+D5) -> 0.55979801 | F5: =D5/(C5+D5) -> 0.44020199
B6: Market capitalisation (US$M) | C6: =CG_SHARES*CG_PRICE_CAD*FX_SPOT -> 4016.2498 | D6: =ERO_SHARES*ERO_PRICE_CAD*FX_SPOT -> 3130.4999 | E6: =C6/(C6+D6) -> 0.56196872 | F6: =D6/(C6+D6) -> 0.43803128
B7: 2027E EBITDA (US$M) | C7: =CG_EBITDA_2027 -> 502.17503 | D7: =ERO_EBITDA_2027 -> 568.49413 | E7: =C7/(C7+D7) -> 0.46902913 | F7: =D7/(C7+D7) -> 0.53097087
B8: 2028E EBITDA (US$M) | C8: =CG_EBITDA_2028 -> 422.39916 | D8: =ERO_EBITDA_2028 -> 486.98141 | E8: =C8/(C8+D8) -> 0.46449107 | F8: =D8/(C8+D8) -> 0.53550893
B9: 2027E operating cash flow (US$M) | C9: =CG_CFO_2027 -> 393.91442 | D9: =ERO_CFO_2027 -> 454.68523 | E9: =C9/(C9+D9) -> 0.46419347 | F9: =D9/(C9+D9) -> 0.53580653
B10: 2027E net income (US$M) | C10: =CG_NI_2027 -> 222.7891 | D10: =ERO_NI_2027 -> 284.98084 | E10: =C10/(C10+D10) -> 0.43875992 | F10: =D10/(C10+D10) -> 0.56124008
B11: 2027E production (koz AuEq) | C11: =Corporate_NAV!$C$27+Corporate_NAV!$C$26*1000/(Inputs!$AC$17/Inputs!$AC$16) -> 323.85367 | D11: =Corporate_NAV!$E$27+Corporate_NAV!$E$26*1000/(Inputs!$AC$17/Inputs!$AC$16) -> 255.43296 | E11: =C11/(C11+D11) -> 0.55905601 | F11: =D11/(C11+D11) -> 0.44094399
B12: P&P reserves (Mt CuEq) | C12: =Comps!L5 -> 2.2412375 | D12: =Comps!L6 -> 0.98172973 | E12: =C12/(C12+D12) -> 0.69539568 | F12: =D12/(C12+D12) -> 0.30460432
B13: Pro forma ownership | E13: =PF_OWN_CG -> 0.56819085 | F13: =PF_OWN_ERO -> 0.43180915
B15: AuEq converts copper at the long-term deck ratio. Centerra % above its ownership means Centerra contributes more than its holders keep.

Sheet Scenarios
B1: Price scenarios
B2: Values produced by scripts/run_scenarios.py, which re-runs this workbook with each price case and records the outputs. Rerun `make model` after changing any input.
B5: Scenario | C5: Cu case | D5: Au case | E5: Custom Cu | F5: CG_NAV | G5: ERO_NAV | H5: CG_NAVPS_CAD | I5: ERO_NAVPS_CAD | J5: CG_PNAV | K5: ERO_PNAV
B6: Deck | C6: 1 | D6: 1 | F6: 1686.2714 | G6: 1326.0141 | H6: 11.890497 | I6: 17.803026 | J6: 2.3817339 | K6: 2.3608346
B7: Spot | C7: 2 | D7: 2 | F7: 2897.3755 | G7: 2568.3398 | H7: 20.430421 | I7: 34.482456 | J7: 1.3861682 | K7: 1.2188807
B8: Cu 4.00 flat | C8: 3 | D8: 1 | E8: 4 | F8: 1234.5393 | G8: 238.01717 | H8: 8.7051738 | I8: 3.1956116 | J8: 3.2532377 | K8: 13.152412
B9: Cu 4.50 flat | C9: 3 | D9: 1 | E9: 4.5 | F9: 1436.5777 | G9: 699.50717 | H9: 10.129819 | I9: 9.3915627 | J9: 2.7957065 | K9: 4.4752935
B10: Cu 5.00 flat | C10: 3 | D10: 1 | E10: 5 | F10: 1638.6162 | G10: 1159.1709 | H10: 11.554463 | I10: 15.562995 | J10: 2.4510009 | K10: 2.700637
B11: Cu 5.50 flat | C11: 3 | D11: 1 | E11: 5.5 | F11: 1840.6546 | G11: 1618.8347 | H11: 12.979108 | I11: 21.734428 | J11: 2.1819681 | K11: 1.9337983
B12: Cu 6.00 flat | C12: 3 | D12: 1 | E12: 6 | F12: 2042.6931 | G12: 2078.4985 | H12: 14.403753 | I12: 27.90586 | J12: 1.9661543 | K12: 1.5061353
B13: Cu 6.50 flat | C13: 3 | D13: 1 | E13: 6.5 | F13: 2244.7316 | G13: 2538.1623 | H13: 15.828398 | I13: 34.077293 | J13: 1.7891893 | K13: 1.2333726

Sheet Sensitivity
B1: Sensitivity tables
B2: Each cell recomputes the deal with the row and column values; everything else stays at the Merger tab inputs.
B4: NAVPS accretion / (dilution): offer premium (rows) vs flat copper price, US$/lb (columns)
B5: Premium \ Copper | C5: 4 | D5: 4.5 | E5: 5 | F5: 5.5 | G5: 6 | H5: 6.5
B6: 0.15 | C6: =IFERROR((Scenarios!$F$8+Scenarios!$G$8+SYN_NPV-(ERO_SHARES*(ERO_PRICE_CAD*(1+$B6))*DEAL_CASH_PCT*FX_SPOT+DEAL_TXN_COSTS))/(CG_SHARES+(ERO_SHARES*(ERO_PRICE_CAD*(1+$B6))*(1-DEAL_CASH_PCT)/CG_PRICE_CAD))/(Scenarios!$F$8/CG_SHARES)-1,"n/a") -> -0.44676535 | D6: =IFERROR((Scenarios!$F$9+Scenarios!$G$9+SYN_NPV-(ERO_SHARES*(ERO_PRICE_CAD*(1+$B6))*DEAL_CASH_PCT*FX_SPOT+DEAL_TXN_COSTS))/(CG_SHARES+(ERO_SHARES*(ERO_PRICE_CAD*(1+$B6))*(1-DEAL_CASH_PCT)/CG_PRICE_CAD))/(Scenarios!$F$9/CG_SHARES)-1,"n/a") -> -0.24837348 | E6: =IFERROR((Scenarios!$F$10+Scenarios!$G$10+SYN_NPV-(ERO_SHARES*(ERO_PRICE_CAD*(1+$B6))*DEAL_CASH_PCT*FX_SPOT+DEAL_TXN_COSTS))/(CG_SHARES+(ERO_SHARES*(ERO_PRICE_CAD*(1+$B6))*(1-DEAL_CASH_PCT)/CG_PRICE_CAD))/(Scenarios!$F$10/CG_SHARES)-1,"n/a") -> -0.099570781 | F6: =IFERROR((Scenarios!$F$11+Scenarios!$G$11+SYN_NPV-(ERO_SHARES*(ERO_PRICE_CAD*(1+$B6))*DEAL_CASH_PCT*FX_SPOT+DEAL_TXN_COSTS))/(CG_SHARES+(ERO_SHARES*(ERO_PRICE_CAD*(1+$B6))*(1-DEAL_CASH_PCT)/CG_PRICE_CAD))/(Scenarios!$F$11/CG_SHARES)-1,"n/a") -> 0.016565421 | G6: =IFERROR((Scenarios!$F$12+Scenarios!$G$12+SYN_NPV-(ERO_SHARES*(ERO_PRICE_CAD*(1+$B6))*DEAL_CASH_PCT*FX_SPOT+DEAL_TXN_COSTS))/(CG_SHARES+(ERO_SHARES*(ERO_PRICE_CAD*(1+$B6))*(1-DEAL_CASH_PCT)/CG_PRICE_CAD))/(Scenarios!$F$12/CG_SHARES)-1,"n/a") -> 0.10972805 | H6: =IFERROR((Scenarios!$F$13+Scenarios!$G$13+SYN_NPV-(ERO_SHARES*(ERO_PRICE_CAD*(1+$B6))*DEAL_CASH_PCT*FX_SPOT+DEAL_TXN_COSTS))/(CG_SHARES+(ERO_SHARES*(ERO_PRICE_CAD*(1+$B6))*(1-DEAL_CASH_PCT)/CG_PRICE_CAD))/(Scenarios!$F$13/CG_SHARES)-1,"n/a") -> 0.18612036
B7: 0.2 | C7: =IFERROR((Scenarios!$F$8+Scenarios!$G$8+SYN_NPV-(ERO_SHARES*(ERO_PRICE_CAD*(1+$B7))*DEAL_CASH_PCT*FX_SPOT+DEAL_TXN_COSTS))/(CG_SHARES+(ERO_SHARES*(ERO_PRICE_CAD*(1+$B7))*(1-DEAL_CASH_PCT)/CG_PRICE_CAD))/(Scenarios!$F$8/CG_SHARES)-1,"n/a") -> -0.47489792 | D7: =IFERROR((Scenarios!$F$9+Scenarios!$G$9+SYN_NPV-(ERO_SHARES*(ERO_PRICE_CAD*(1+$B7))*DEAL_CASH_PCT*FX_SPOT+DEAL_TXN_COSTS))/(CG_SHARES+(ERO_SHARES*(ERO_PRICE_CAD*(1+$B7))*(1-DEAL_CASH_PCT)/CG_PRICE_CAD))/(Scenarios!$F$9/CG_SHARES)-1,"n/a") -> -0.27729423 | E7: =IFERROR((Scenarios!$F$10+Scenarios!$G$10+SYN_NPV-(ERO_SHARES*(ERO_PRICE_CAD*(1+$B7))*DEAL_CASH_PCT*FX_SPOT+DEAL_TXN_COSTS))/(CG_SHARES+(ERO_SHARES*(ERO_PRICE_CAD*(1+$B7))*(1-DEAL_CASH_PCT)/CG_PRICE_CAD))/(Scenarios!$F$10/CG_SHARES)-1,"n/a") -> -0.1290739 | F7: =IFERROR((Scenarios!$F$11+Scenarios!$G$11+SYN_NPV-(ERO_SHARES*(ERO_PRICE_CAD*(1+$B7))*DEAL_CASH_PCT*FX_SPOT+DEAL_TXN_COSTS))/(CG_SHARES+(ERO_SHARES*(ERO_PRICE_CAD*(1+$B7))*(1-DEAL_CASH_PCT)/CG_PRICE_CAD))/(Scenarios!$F$11/CG_SHARES)-1,"n/a") -> -0.013392226 | G7: =IFERROR((Scenarios!$F$12+Scenarios!$G$12+SYN_NPV-(ERO_SHARES*(ERO_PRICE_CAD*(1+$B7))*DEAL_CASH_PCT*FX_SPOT+DEAL_TXN_COSTS))/(CG_SHARES+(ERO_SHARES*(ERO_PRICE_CAD*(1+$B7))*(1-DEAL_CASH_PCT)/CG_PRICE_CAD))/(Scenarios!$F$12/CG_SHARES)-1,"n/a") -> 0.079405793 | H7: =IFERROR((Scenarios!$F$13+Scenarios!$G$13+SYN_NPV-(ERO_SHARES*(ERO_PRICE_CAD*(1+$B7))*DEAL_CASH_PCT*FX_SPOT+DEAL_TXN_COSTS))/(CG_SHARES+(ERO_SHARES*(ERO_PRICE_CAD*(1+$B7))*(1-DEAL_CASH_PCT)/CG_PRICE_CAD))/(Scenarios!$F$13/CG_SHARES)-1,"n/a") -> 0.15549912
B8: 0.25 | C8: =IFERROR((Scenarios!$F$8+Scenarios!$G$8+SYN_NPV-(ERO_SHARES*(ERO_PRICE_CAD*(1+$B8))*DEAL_CASH_PCT*FX_SPOT+DEAL_TXN_COSTS))/(CG_SHARES+(ERO_SHARES*(ERO_PRICE_CAD*(1+$B8))*(1-DEAL_CASH_PCT)/CG_PRICE_CAD))/(Scenarios!$F$8/CG_SHARES)-1,"n/a") -> -0.50208025 | D8: =IFERROR((Scenarios!$F$9+Scenarios!$G$9+SYN_NPV-(ERO_SHARES*(ERO_PRICE_CAD*(1+$B8))*DEAL_CASH_PCT*FX_SPOT+DEAL_TXN_COSTS))/(CG_SHARES+(ERO_SHARES*(ERO_PRICE_CAD*(1+$B8))*(1-DEAL_CASH_PCT)/CG_PRICE_CAD))/(Scenarios!$F$9/CG_SHARES)-1,"n/a") -> -0.30523812 | E8: =IFERROR((Scenarios!$F$10+Scenarios!$G$10+SYN_NPV-(ERO_SHARES*(ERO_PRICE_CAD*(1+$B8))*DEAL_CASH_PCT*FX_SPOT+DEAL_TXN_COSTS))/(CG_SHARES+(ERO_SHARES*(ERO_PRICE_CAD*(1+$B8))*(1-DEAL_CASH_PCT)/CG_PRICE_CAD))/(Scenarios!$F$10/CG_SHARES)-1,"n/a") -> -0.1575805 | F8: =IFERROR((Scenarios!$F$11+Scenarios!$G$11+SYN_NPV-(ERO_SHARES*(ERO_PRICE_CAD*(1+$B8))*DEAL_CASH_PCT*FX_SPOT+DEAL_TXN_COSTS))/(CG_SHARES+(ERO_SHARES*(ERO_PRICE_CAD*(1+$B8))*(1-DEAL_CASH_PCT)/CG_PRICE_CAD))/(Scenarios!$F$11/CG_SHARES)-1,"n/a") -> -0.042337991 | G8: =IFERROR((Scenarios!$F$12+Scenarios!$G$12+SYN_NPV-(ERO_SHARES*(ERO_PRICE_CAD*(1+$B8))*DEAL_CASH_PCT*FX_SPOT+DEAL_TXN_COSTS))/(CG_SHARES+(ERO_SHARES*(ERO_PRICE_CAD*(1+$B8))*(1-DEAL_CASH_PCT)/CG_PRICE_CAD))/(Scenarios!$F$12/CG_SHARES)-1,"n/a") -> 0.050107731 | H8: =IFERROR((Scenarios!$F$13+Scenarios!$G$13+SYN_NPV-(ERO_SHARES*(ERO_PRICE_CAD*(1+$B8))*DEAL_CASH_PCT*FX_SPOT+DEAL_TXN_COSTS))/(CG_SHARES+(ERO_SHARES*(ERO_PRICE_CAD*(1+$B8))*(1-DEAL_CASH_PCT)/CG_PRICE_CAD))/(Scenarios!$F$13/CG_SHARES)-1,"n/a") -> 0.12591218
B9: 0.3 | C9: =IFERROR((Scenarios!$F$8+Scenarios!$G$8+SYN_NPV-(ERO_SHARES*(ERO_PRICE_CAD*(1+$B9))*DEAL_CASH_PCT*FX_SPOT+DEAL_TXN_COSTS))/(CG_SHARES+(ERO_SHARES*(ERO_PRICE_CAD*(1+$B9))*(1-DEAL_CASH_PCT)/CG_PRICE_CAD))/(Scenarios!$F$8/CG_SHARES)-1,"n/a") -> -0.5283597 | D9: =IFERROR((Scenarios!$F$9+Scenarios!$G$9+SYN_NPV-(ERO_SHARES*(ERO_PRICE_CAD*(1+$B9))*DEAL_CASH_PCT*FX_SPOT+DEAL_TXN_COSTS))/(CG_SHARES+(ERO_SHARES*(ERO_PRICE_CAD*(1+$B9))*(1-DEAL_CASH_PCT)/CG_PRICE_CAD))/(Scenarios!$F$9/CG_SHARES)-1,"n/a") -> -0.33225383 | E9: =IFERROR((Scenarios!$F$10+Scenarios!$G$10+SYN_NPV-(ERO_SHARES*(ERO_PRICE_CAD*(1+$B9))*DEAL_CASH_PCT*FX_SPOT+DEAL_TXN_COSTS))/(CG_SHARES+(ERO_SHARES*(ERO_PRICE_CAD*(1+$B9))*(1-DEAL_CASH_PCT)/CG_PRICE_CAD))/(Scenarios!$F$10/CG_SHARES)-1,"n/a") -> -0.18514022 | F9: =IFERROR((Scenarios!$F$11+Scenarios!$G$11+SYN_NPV-(ERO_SHARES*(ERO_PRICE_CAD*(1+$B9))*DEAL_CASH_PCT*FX_SPOT+DEAL_TXN_COSTS))/(CG_SHARES+(ERO_SHARES*(ERO_PRICE_CAD*(1+$B9))*(1-DEAL_CASH_PCT)/CG_PRICE_CAD))/(Scenarios!$F$11/CG_SHARES)-1,"n/a") -> -0.070322292 | G9: =IFERROR((Scenarios!$F$12+Scenarios!$G$12+SYN_NPV-(ERO_SHARES*(ERO_PRICE_CAD*(1+$B9))*DEAL_CASH_PCT*FX_SPOT+DEAL_TXN_COSTS))/(CG_SHARES+(ERO_SHARES*(ERO_PRICE_CAD*(1+$B9))*(1-DEAL_CASH_PCT)/CG_PRICE_CAD))/(Scenarios!$F$12/CG_SHARES)-1,"n/a") -> 0.021782837 | H9: =IFERROR((Scenarios!$F$13+Scenarios!$G$13+SYN_NPV-(ERO_SHARES*(ERO_PRICE_CAD*(1+$B9))*DEAL_CASH_PCT*FX_SPOT+DEAL_TXN_COSTS))/(CG_SHARES+(ERO_SHARES*(ERO_PRICE_CAD*(1+$B9))*(1-DEAL_CASH_PCT)/CG_PRICE_CAD))/(Scenarios!$F$13/CG_SHARES)-1,"n/a") -> 0.097308007
B10: 0.35 | C10: =IFERROR((Scenarios!$F$8+Scenarios!$G$8+SYN_NPV-(ERO_SHARES*(ERO_PRICE_CAD*(1+$B10))*DEAL_CASH_PCT*FX_SPOT+DEAL_TXN_COSTS))/(CG_SHARES+(ERO_SHARES*(ERO_PRICE_CAD*(1+$B10))*(1-DEAL_CASH_PCT)/CG_PRICE_CAD))/(Scenarios!$F$8/CG_SHARES)-1,"n/a") -> -0.5537805 | D10: =IFERROR((Scenarios!$F$9+Scenarios!$G$9+SYN_NPV-(ERO_SHARES*(ERO_PRICE_CAD*(1+$B10))*DEAL_CASH_PCT*FX_SPOT+DEAL_TXN_COSTS))/(CG_SHARES+(ERO_SHARES*(ERO_PRICE_CAD*(1+$B10))*(1-DEAL_CASH_PCT)/CG_PRICE_CAD))/(Scenarios!$F$9/CG_SHARES)-1,"n/a") -> -0.35838685 | E10: =IFERROR((Scenarios!$F$10+Scenarios!$G$10+SYN_NPV-(ERO_SHARES*(ERO_PRICE_CAD*(1+$B10))*DEAL_CASH_PCT*FX_SPOT+DEAL_TXN_COSTS))/(CG_SHARES+(ERO_SHARES*(ERO_PRICE_CAD*(1+$B10))*(1-DEAL_CASH_PCT)/CG_PRICE_CAD))/(Scenarios!$F$10/CG_SHARES)-1,"n/a") -> -0.21179946 | F10: =IFERROR((Scenarios!$F$11+Scenarios!$G$11+SYN_NPV-(ERO_SHARES*(ERO_PRICE_CAD*(1+$B10))*DEAL_CASH_PCT*FX_SPOT+DEAL_TXN_COSTS))/(CG_SHARES+(ERO_SHARES*(ERO_PRICE_CAD*(1+$B10))*(1-DEAL_CASH_PCT)/CG_PRICE_CAD))/(Scenarios!$F$11/CG_SHARES)-1,"n/a") -> -0.097392248 | G10: =IFERROR((Scenarios!$F$12+Scenarios!$G$12+SYN_NPV-(ERO_SHARES*(ERO_PRICE_CAD*(1+$B10))*DEAL_CASH_PCT*FX_SPOT+DEAL_TXN_COSTS))/(CG_SHARES+(ERO_SHARES*(ERO_PRICE_CAD*(1+$B10))*(1-DEAL_CASH_PCT)/CG_PRICE_CAD))/(Scenarios!$F$12/CG_SHARES)-1,"n/a") -> -0.0056165857 | H10: =IFERROR((Scenarios!$F$13+Scenarios!$G$13+SYN_NPV-(ERO_SHARES*(ERO_PRICE_CAD*(1+$B10))*DEAL_CASH_PCT*FX_SPOT+DEAL_TXN_COSTS))/(CG_SHARES+(ERO_SHARES*(ERO_PRICE_CAD*(1+$B10))*(1-DEAL_CASH_PCT)/CG_PRICE_CAD))/(Scenarios!$F$13/CG_SHARES)-1,"n/a") -> 0.069638426
B11: 0.4 | C11: =IFERROR((Scenarios!$F$8+Scenarios!$G$8+SYN_NPV-(ERO_SHARES*(ERO_PRICE_CAD*(1+$B11))*DEAL_CASH_PCT*FX_SPOT+DEAL_TXN_COSTS))/(CG_SHARES+(ERO_SHARES*(ERO_PRICE_CAD*(1+$B11))*(1-DEAL_CASH_PCT)/CG_PRICE_CAD))/(Scenarios!$F$8/CG_SHARES)-1,"n/a") -> -0.57838407 | D11: =IFERROR((Scenarios!$F$9+Scenarios!$G$9+SYN_NPV-(ERO_SHARES*(ERO_PRICE_CAD*(1+$B11))*DEAL_CASH_PCT*FX_SPOT+DEAL_TXN_COSTS))/(CG_SHARES+(ERO_SHARES*(ERO_PRICE_CAD*(1+$B11))*(1-DEAL_CASH_PCT)/CG_PRICE_CAD))/(Scenarios!$F$9/CG_SHARES)-1,"n/a") -> -0.38367973 | E11: =IFERROR((Scenarios!$F$10+Scenarios!$G$10+SYN_NPV-(ERO_SHARES*(ERO_PRICE_CAD*(1+$B11))*DEAL_CASH_PCT*FX_SPOT+DEAL_TXN_COSTS))/(CG_SHARES+(ERO_SHARES*(ERO_PRICE_CAD*(1+$B11))*(1-DEAL_CASH_PCT)/CG_PRICE_CAD))/(Scenarios!$F$10/CG_SHARES)-1,"n/a") -> -0.23760166 | F11: =IFERROR((Scenarios!$F$11+Scenarios!$G$11+SYN_NPV-(ERO_SHARES*(ERO_PRICE_CAD*(1+$B11))*DEAL_CASH_PCT*FX_SPOT+DEAL_TXN_COSTS))/(CG_SHARES+(ERO_SHARES*(ERO_PRICE_CAD*(1+$B11))*(1-DEAL_CASH_PCT)/CG_PRICE_CAD))/(Scenarios!$F$11/CG_SHARES)-1,"n/a") -> -0.12359195 | G11: =IFERROR((Scenarios!$F$12+Scenarios!$G$12+SYN_NPV-(ERO_SHARES*(ERO_PRICE_CAD*(1+$B11))*DEAL_CASH_PCT*FX_SPOT+DEAL_TXN_COSTS))/(CG_SHARES+(ERO_SHARES*(ERO_PRICE_CAD*(1+$B11))*(1-DEAL_CASH_PCT)/CG_PRICE_CAD))/(Scenarios!$F$12/CG_SHARES)-1,"n/a") -> -0.032135165 | H11: =IFERROR((Scenarios!$F$13+Scenarios!$G$13+SYN_NPV-(ERO_SHARES*(ERO_PRICE_CAD*(1+$B11))*DEAL_CASH_PCT*FX_SPOT+DEAL_TXN_COSTS))/(CG_SHARES+(ERO_SHARES*(ERO_PRICE_CAD*(1+$B11))*(1-DEAL_CASH_PCT)/CG_PRICE_CAD))/(Scenarios!$F$13/CG_SHARES)-1,"n/a") -> 0.042858374
B13: 2028E EPS accretion / (dilution): run-rate synergies, US$M (rows) vs cash portion of offer (columns)
B14: Synergies \ Cash % | C14: 0 | D14: 0.15 | E14: 0.25 | F14: 0.35 | G14: 0.5
B15: 0 | C15: =IFERROR((CG_NI_2028+ERO_NI_2028+$B15*DEAL_PHASE_Y2*(1-DEAL_TAX)-((DEAL_EQUITY_USD*C$14+DEAL_TXN_COSTS)-MIN((DEAL_EQUITY_USD*C$14+DEAL_TXN_COSTS),MAX(0,CG_CASH+ERO_CASH-DEAL_MIN_CASH)))*DEAL_DEBT_RATE*(1-DEAL_TAX)-MIN((DEAL_EQUITY_USD*C$14+DEAL_TXN_COSTS),MAX(0,CG_CASH+ERO_CASH-DEAL_MIN_CASH))*DEAL_CASH_YIELD*(1-DEAL_TAX))/(CG_SHARES+(ERO_SHARES*DEAL_OFFER_CAD*(1-C$14)/CG_PRICE_CAD))/CG_EPS_2028-1,"n/a") -> 0.16954709 | D15: =IFERROR((CG_NI_2028+ERO_NI_2028+$B15*DEAL_PHASE_Y2*(1-DEAL_TAX)-((DEAL_EQUITY_USD*D$14+DEAL_TXN_COSTS)-MIN((DEAL_EQUITY_USD*D$14+DEAL_TXN_COSTS),MAX(0,CG_CASH+ERO_CASH-DEAL_MIN_CASH)))*DEAL_DEBT_RATE*(1-DEAL_TAX)-MIN((DEAL_EQUITY_USD*D$14+DEAL_TXN_COSTS),MAX(0,CG_CASH+ERO_CASH-DEAL_MIN_CASH))*DEAL_CASH_YIELD*(1-DEAL_TAX))/(CG_SHARES+(ERO_SHARES*DEAL_OFFER_CAD*(1-D$14)/CG_PRICE_CAD))/CG_EPS_2028-1,"n/a") -> 0.18940123 | E15: =IFERROR((CG_NI_2028+ERO_NI_2028+$B15*DEAL_PHASE_Y2*(1-DEAL_TAX)-((DEAL_EQUITY_USD*E$14+DEAL_TXN_COSTS)-MIN((DEAL_EQUITY_USD*E$14+DEAL_TXN_COSTS),MAX(0,CG_CASH+ERO_CASH-DEAL_MIN_CASH)))*DEAL_DEBT_RATE*(1-DEAL_TAX)-MIN((DEAL_EQUITY_USD*E$14+DEAL_TXN_COSTS),MAX(0,CG_CASH+ERO_CASH-DEAL_MIN_CASH))*DEAL_CASH_YIELD*(1-DEAL_TAX))/(CG_SHARES+(ERO_SHARES*DEAL_OFFER_CAD*(1-E$14)/CG_PRICE_CAD))/CG_EPS_2028-1,"n/a") -> 0.19383995 | F15: =IFERROR((CG_NI_2028+ERO_NI_2028+$B15*DEAL_PHASE_Y2*(1-DEAL_TAX)-((DEAL_EQUITY_USD*F$14+DEAL_TXN_COSTS)-MIN((DEAL_EQUITY_USD*F$14+DEAL_TXN_COSTS),MAX(0,CG_CASH+ERO_CASH-DEAL_MIN_CASH)))*DEAL_DEBT_RATE*(1-DEAL_TAX)-MIN((DEAL_EQUITY_USD*F$14+DEAL_TXN_COSTS),MAX(0,CG_CASH+ERO_CASH-DEAL_MIN_CASH))*DEAL_CASH_YIELD*(1-DEAL_TAX))/(CG_SHARES+(ERO_SHARES*DEAL_OFFER_CAD*(1-F$14)/CG_PRICE_CAD))/CG_EPS_2028-1,"n/a") -> 0.198821 | G15: =IFERROR((CG_NI_2028+ERO_NI_2028+$B15*DEAL_PHASE_Y2*(1-DEAL_TAX)-((DEAL_EQUITY_USD*G$14+DEAL_TXN_COSTS)-MIN((DEAL_EQUITY_USD*G$14+DEAL_TXN_COSTS),MAX(0,CG_CASH+ERO_CASH-DEAL_MIN_CASH)))*DEAL_DEBT_RATE*(1-DEAL_TAX)-MIN((DEAL_EQUITY_USD*G$14+DEAL_TXN_COSTS),MAX(0,CG_CASH+ERO_CASH-DEAL_MIN_CASH))*DEAL_CASH_YIELD*(1-DEAL_TAX))/(CG_SHARES+(ERO_SHARES*DEAL_OFFER_CAD*(1-G$14)/CG_PRICE_CAD))/CG_EPS_2028-1,"n/a") -> 0.20754884
B16: 50 | C16: =IFERROR((CG_NI_2028+ERO_NI_2028+$B16*DEAL_PHASE_Y2*(1-DEAL_TAX)-((DEAL_EQUITY_USD*C$14+DEAL_TXN_COSTS)-MIN((DEAL_EQUITY_USD*C$14+DEAL_TXN_COSTS),MAX(0,CG_CASH+ERO_CASH-DEAL_MIN_CASH)))*DEAL_DEBT_RATE*(1-DEAL_TAX)-MIN((DEAL_EQUITY_USD*C$14+DEAL_TXN_COSTS),MAX(0,CG_CASH+ERO_CASH-DEAL_MIN_CASH))*DEAL_CASH_YIELD*(1-DEAL_TAX))/(CG_SHARES+(ERO_SHARES*DEAL_OFFER_CAD*(1-C$14)/CG_PRICE_CAD))/CG_EPS_2028-1,"n/a") -> 0.28418143 | D16: =IFERROR((CG_NI_2028+ERO_NI_2028+$B16*DEAL_PHASE_Y2*(1-DEAL_TAX)-((DEAL_EQUITY_USD*D$14+DEAL_TXN_COSTS)-MIN((DEAL_EQUITY_USD*D$14+DEAL_TXN_COSTS),MAX(0,CG_CASH+ERO_CASH-DEAL_MIN_CASH)))*DEAL_DEBT_RATE*(1-DEAL_TAX)-MIN((DEAL_EQUITY_USD*D$14+DEAL_TXN_COSTS),MAX(0,CG_CASH+ERO_CASH-DEAL_MIN_CASH))*DEAL_CASH_YIELD*(1-DEAL_TAX))/(CG_SHARES+(ERO_SHARES*DEAL_OFFER_CAD*(1-D$14)/CG_PRICE_CAD))/CG_EPS_2028-1,"n/a") -> 0.31339664 | E16: =IFERROR((CG_NI_2028+ERO_NI_2028+$B16*DEAL_PHASE_Y2*(1-DEAL_TAX)-((DEAL_EQUITY_USD*E$14+DEAL_TXN_COSTS)-MIN((DEAL_EQUITY_USD*E$14+DEAL_TXN_COSTS),MAX(0,CG_CASH+ERO_CASH-DEAL_MIN_CASH)))*DEAL_DEBT_RATE*(1-DEAL_TAX)-MIN((DEAL_EQUITY_USD*E$14+DEAL_TXN_COSTS),MAX(0,CG_CASH+ERO_CASH-DEAL_MIN_CASH))*DEAL_CASH_YIELD*(1-DEAL_TAX))/(CG_SHARES+(ERO_SHARES*DEAL_OFFER_CAD*(1-E$14)/CG_PRICE_CAD))/CG_EPS_2028-1,"n/a") -> 0.32497434 | F16: =IFERROR((CG_NI_2028+ERO_NI_2028+$B16*DEAL_PHASE_Y2*(1-DEAL_TAX)-((DEAL_EQUITY_USD*F$14+DEAL_TXN_COSTS)-MIN((DEAL_EQUITY_USD*F$14+DEAL_TXN_COSTS),MAX(0,CG_CASH+ERO_CASH-DEAL_MIN_CASH)))*DEAL_DEBT_RATE*(1-DEAL_TAX)-MIN((DEAL_EQUITY_USD*F$14+DEAL_TXN_COSTS),MAX(0,CG_CASH+ERO_CASH-DEAL_MIN_CASH))*DEAL_CASH_YIELD*(1-DEAL_TAX))/(CG_SHARES+(ERO_SHARES*DEAL_OFFER_CAD*(1-F$14)/CG_PRICE_CAD))/CG_EPS_2028-1,"n/a") -> 0.33796664 | G16: =IFERROR((CG_NI_2028+ERO_NI_2028+$B16*DEAL_PHASE_Y2*(1-DEAL_TAX)-((DEAL_EQUITY_USD*G$14+DEAL_TXN_COSTS)-MIN((DEAL_EQUITY_USD*G$14+DEAL_TXN_COSTS),MAX(0,CG_CASH+ERO_CASH-DEAL_MIN_CASH)))*DEAL_DEBT_RATE*(1-DEAL_TAX)-MIN((DEAL_EQUITY_USD*G$14+DEAL_TXN_COSTS),MAX(0,CG_CASH+ERO_CASH-DEAL_MIN_CASH))*DEAL_CASH_YIELD*(1-DEAL_TAX))/(CG_SHARES+(ERO_SHARES*DEAL_OFFER_CAD*(1-G$14)/CG_PRICE_CAD))/CG_EPS_2028-1,"n/a") -> 0.36073184
B17: 100 | C17: =IFERROR((CG_NI_2028+ERO_NI_2028+$B17*DEAL_PHASE_Y2*(1-DEAL_TAX)-((DEAL_EQUITY_USD*C$14+DEAL_TXN_COSTS)-MIN((DEAL_EQUITY_USD*C$14+DEAL_TXN_COSTS),MAX(0,CG_CASH+ERO_CASH-DEAL_MIN_CASH)))*DEAL_DEBT_RATE*(1-DEAL_TAX)-MIN((DEAL_EQUITY_USD*C$14+DEAL_TXN_COSTS),MAX(0,CG_CASH+ERO_CASH-DEAL_MIN_CASH))*DEAL_CASH_YIELD*(1-DEAL_TAX))/(CG_SHARES+(ERO_SHARES*DEAL_OFFER_CAD*(1-C$14)/CG_PRICE_CAD))/CG_EPS_2028-1,"n/a") -> 0.39881577 | D17: =IFERROR((CG_NI_2028+ERO_NI_2028+$B17*DEAL_PHASE_Y2*(1-DEAL_TAX)-((DEAL_EQUITY_USD*D$14+DEAL_TXN_COSTS)-MIN((DEAL_EQUITY_USD*D$14+DEAL_TXN_COSTS),MAX(0,CG_CASH+ERO_CASH-DEAL_MIN_CASH)))*DEAL_DEBT_RATE*(1-DEAL_TAX)-MIN((DEAL_EQUITY_USD*D$14+DEAL_TXN_COSTS),MAX(0,CG_CASH+ERO_CASH-DEAL_MIN_CASH))*DEAL_CASH_YIELD*(1-DEAL_TAX))/(CG_SHARES+(ERO_SHARES*DEAL_OFFER_CAD*(1-D$14)/CG_PRICE_CAD))/CG_EPS_2028-1,"n/a") -> 0.43739205 | E17: =IFERROR((CG_NI_2028+ERO_NI_2028+$B17*DEAL_PHASE_Y2*(1-DEAL_TAX)-((DEAL_EQUITY_USD*E$14+DEAL_TXN_COSTS)-MIN((DEAL_EQUITY_USD*E$14+DEAL_TXN_COSTS),MAX(0,CG_CASH+ERO_CASH-DEAL_MIN_CASH)))*DEAL_DEBT_RATE*(1-DEAL_TAX)-MIN((DEAL_EQUITY_USD*E$14+DEAL_TXN_COSTS),MAX(0,CG_CASH+ERO_CASH-DEAL_MIN_CASH))*DEAL_CASH_YIELD*(1-DEAL_TAX))/(CG_SHARES+(ERO_SHARES*DEAL_OFFER_CAD*(1-E$14)/CG_PRICE_CAD))/CG_EPS_2028-1,"n/a") -> 0.45610873 | F17: =IFERROR((CG_NI_2028+ERO_NI_2028+$B17*DEAL_PHASE_Y2*(1-DEAL_TAX)-((DEAL_EQUITY_USD*F$14+DEAL_TXN_COSTS)-MIN((DEAL_EQUITY_USD*F$14+DEAL_TXN_COSTS),MAX(0,CG_CASH+ERO_CASH-DEAL_MIN_CASH)))*DEAL_DEBT_RATE*(1-DEAL_TAX)-MIN((DEAL_EQUITY_USD*F$14+DEAL_TXN_COSTS),MAX(0,CG_CASH+ERO_CASH-DEAL_MIN_CASH))*DEAL_CASH_YIELD*(1-DEAL_TAX))/(CG_SHARES+(ERO_SHARES*DEAL_OFFER_CAD*(1-F$14)/CG_PRICE_CAD))/CG_EPS_2028-1,"n/a") -> 0.47711228 | G17: =IFERROR((CG_NI_2028+ERO_NI_2028+$B17*DEAL_PHASE_Y2*(1-DEAL_TAX)-((DEAL_EQUITY_USD*G$14+DEAL_TXN_COSTS)-MIN((DEAL_EQUITY_USD*G$14+DEAL_TXN_COSTS),MAX(0,CG_CASH+ERO_CASH-DEAL_MIN_CASH)))*DEAL_DEBT_RATE*(1-DEAL_TAX)-MIN((DEAL_EQUITY_USD*G$14+DEAL_TXN_COSTS),MAX(0,CG_CASH+ERO_CASH-DEAL_MIN_CASH))*DEAL_CASH_YIELD*(1-DEAL_TAX))/(CG_SHARES+(ERO_SHARES*DEAL_OFFER_CAD*(1-G$14)/CG_PRICE_CAD))/CG_EPS_2028-1,"n/a") -> 0.51391484
B18: 155 | C18: =IFERROR((CG_NI_2028+ERO_NI_2028+$B18*DEAL_PHASE_Y2*(1-DEAL_TAX)-((DEAL_EQUITY_USD*C$14+DEAL_TXN_COSTS)-MIN((DEAL_EQUITY_USD*C$14+DEAL_TXN_COSTS),MAX(0,CG_CASH+ERO_CASH-DEAL_MIN_CASH)))*DEAL_DEBT_RATE*(1-DEAL_TAX)-MIN((DEAL_EQUITY_USD*C$14+DEAL_TXN_COSTS),MAX(0,CG_CASH+ERO_CASH-DEAL_MIN_CASH))*DEAL_CASH_YIELD*(1-DEAL_TAX))/(CG_SHARES+(ERO_SHARES*DEAL_OFFER_CAD*(1-C$14)/CG_PRICE_CAD))/CG_EPS_2028-1,"n/a") -> 0.52491354 | D18: =IFERROR((CG_NI_2028+ERO_NI_2028+$B18*DEAL_PHASE_Y2*(1-DEAL_TAX)-((DEAL_EQUITY_USD*D$14+DEAL_TXN_COSTS)-MIN((DEAL_EQUITY_USD*D$14+DEAL_TXN_COSTS),MAX(0,CG_CASH+ERO_CASH-DEAL_MIN_CASH)))*DEAL_DEBT_RATE*(1-DEAL_TAX)-MIN((DEAL_EQUITY_USD*D$14+DEAL_TXN_COSTS),MAX(0,CG_CASH+ERO_CASH-DEAL_MIN_CASH))*DEAL_CASH_YIELD*(1-DEAL_TAX))/(CG_SHARES+(ERO_SHARES*DEAL_OFFER_CAD*(1-D$14)/CG_PRICE_CAD))/CG_EPS_2028-1,"n/a") -> 0.573787 | E18: =IFERROR((CG_NI_2028+ERO_NI_2028+$B18*DEAL_PHASE_Y2*(1-DEAL_TAX)-((DEAL_EQUITY_USD*E$14+DEAL_TXN_COSTS)-MIN((DEAL_EQUITY_USD*E$14+DEAL_TXN_COSTS),MAX(0,CG_CASH+ERO_CASH-DEAL_MIN_CASH)))*DEAL_DEBT_RATE*(1-DEAL_TAX)-MIN((DEAL_EQUITY_USD*E$14+DEAL_TXN_COSTS),MAX(0,CG_CASH+ERO_CASH-DEAL_MIN_CASH))*DEAL_CASH_YIELD*(1-DEAL_TAX))/(CG_SHARES+(ERO_SHARES*DEAL_OFFER_CAD*(1-E$14)/CG_PRICE_CAD))/CG_EPS_2028-1,"n/a") -> 0.60035656 | F18: =IFERROR((CG_NI_2028+ERO_NI_2028+$B18*DEAL_PHASE_Y2*(1-DEAL_TAX)-((DEAL_EQUITY_USD*F$14+DEAL_TXN_COSTS)-MIN((DEAL_EQUITY_USD*F$14+DEAL_TXN_COSTS),MAX(0,CG_CASH+ERO_CASH-DEAL_MIN_CASH)))*DEAL_DEBT_RATE*(1-DEAL_TAX)-MIN((DEAL_EQUITY_USD*F$14+DEAL_TXN_COSTS),MAX(0,CG_CASH+ERO_CASH-DEAL_MIN_CASH))*DEAL_CASH_YIELD*(1-DEAL_TAX))/(CG_SHARES+(ERO_SHARES*DEAL_OFFER_CAD*(1-F$14)/CG_PRICE_CAD))/CG_EPS_2028-1,"n/a") -> 0.63017248 | G18: =IFERROR((CG_NI_2028+ERO_NI_2028+$B18*DEAL_PHASE_Y2*(1-DEAL_TAX)-((DEAL_EQUITY_USD*G$14+DEAL_TXN_COSTS)-MIN((DEAL_EQUITY_USD*G$14+DEAL_TXN_COSTS),MAX(0,CG_CASH+ERO_CASH-DEAL_MIN_CASH)))*DEAL_DEBT_RATE*(1-DEAL_TAX)-MIN((DEAL_EQUITY_USD*G$14+DEAL_TXN_COSTS),MAX(0,CG_CASH+ERO_CASH-DEAL_MIN_CASH))*DEAL_CASH_YIELD*(1-DEAL_TAX))/(CG_SHARES+(ERO_SHARES*DEAL_OFFER_CAD*(1-G$14)/CG_PRICE_CAD))/CG_EPS_2028-1,"n/a") -> 0.68241613
B19: 200 | C19: =IFERROR((CG_NI_2028+ERO_NI_2028+$B19*DEAL_PHASE_Y2*(1-DEAL_TAX)-((DEAL_EQUITY_USD*C$14+DEAL_TXN_COSTS)-MIN((DEAL_EQUITY_USD*C$14+DEAL_TXN_COSTS),MAX(0,CG_CASH+ERO_CASH-DEAL_MIN_CASH)))*DEAL_DEBT_RATE*(1-DEAL_TAX)-MIN((DEAL_EQUITY_USD*C$14+DEAL_TXN_COSTS),MAX(0,CG_CASH+ERO_CASH-DEAL_MIN_CASH))*DEAL_CASH_YIELD*(1-DEAL_TAX))/(CG_SHARES+(ERO_SHARES*DEAL_OFFER_CAD*(1-C$14)/CG_PRICE_CAD))/CG_EPS_2028-1,"n/a") -> 0.62808444 | D19: =IFERROR((CG_NI_2028+ERO_NI_2028+$B19*DEAL_PHASE_Y2*(1-DEAL_TAX)-((DEAL_EQUITY_USD*D$14+DEAL_TXN_COSTS)-MIN((DEAL_EQUITY_USD*D$14+DEAL_TXN_COSTS),MAX(0,CG_CASH+ERO_CASH-DEAL_MIN_CASH)))*DEAL_DEBT_RATE*(1-DEAL_TAX)-MIN((DEAL_EQUITY_USD*D$14+DEAL_TXN_COSTS),MAX(0,CG_CASH+ERO_CASH-DEAL_MIN_CASH))*DEAL_CASH_YIELD*(1-DEAL_TAX))/(CG_SHARES+(ERO_SHARES*DEAL_OFFER_CAD*(1-D$14)/CG_PRICE_CAD))/CG_EPS_2028-1,"n/a") -> 0.68538287 | E19: =IFERROR((CG_NI_2028+ERO_NI_2028+$B19*DEAL_PHASE_Y2*(1-DEAL_TAX)-((DEAL_EQUITY_USD*E$14+DEAL_TXN_COSTS)-MIN((DEAL_EQUITY_USD*E$14+DEAL_TXN_COSTS),MAX(0,CG_CASH+ERO_CASH-DEAL_MIN_CASH)))*DEAL_DEBT_RATE*(1-DEAL_TAX)-MIN((DEAL_EQUITY_USD*E$14+DEAL_TXN_COSTS),MAX(0,CG_CASH+ERO_CASH-DEAL_MIN_CASH))*DEAL_CASH_YIELD*(1-DEAL_TAX))/(CG_SHARES+(ERO_SHARES*DEAL_OFFER_CAD*(1-E$14)/CG_PRICE_CAD))/CG_EPS_2028-1,"n/a") -> 0.71837751 | F19: =IFERROR((CG_NI_2028+ERO_NI_2028+$B19*DEAL_PHASE_Y2*(1-DEAL_TAX)-((DEAL_EQUITY_USD*F$14+DEAL_TXN_COSTS)-MIN((DEAL_EQUITY_USD*F$14+DEAL_TXN_COSTS),MAX(0,CG_CASH+ERO_CASH-DEAL_MIN_CASH)))*DEAL_DEBT_RATE*(1-DEAL_TAX)-MIN((DEAL_EQUITY_USD*F$14+DEAL_TXN_COSTS),MAX(0,CG_CASH+ERO_CASH-DEAL_MIN_CASH))*DEAL_CASH_YIELD*(1-DEAL_TAX))/(CG_SHARES+(ERO_SHARES*DEAL_OFFER_CAD*(1-F$14)/CG_PRICE_CAD))/CG_EPS_2028-1,"n/a") -> 0.75540356 | G19: =IFERROR((CG_NI_2028+ERO_NI_2028+$B19*DEAL_PHASE_Y2*(1-DEAL_TAX)-((DEAL_EQUITY_USD*G$14+DEAL_TXN_COSTS)-MIN((DEAL_EQUITY_USD*G$14+DEAL_TXN_COSTS),MAX(0,CG_CASH+ERO_CASH-DEAL_MIN_CASH)))*DEAL_DEBT_RATE*(1-DEAL_TAX)-MIN((DEAL_EQUITY_USD*G$14+DEAL_TXN_COSTS),MAX(0,CG_CASH+ERO_CASH-DEAL_MIN_CASH))*DEAL_CASH_YIELD*(1-DEAL_TAX))/(CG_SHARES+(ERO_SHARES*DEAL_OFFER_CAD*(1-G$14)/CG_PRICE_CAD))/CG_EPS_2028-1,"n/a") -> 0.82028083
B21: Table 1 holds gold at the analyst deck and uses the Merger tab's cash portion. Table 2 holds the offer premium at the Merger tab input.

Sheet Football_Field
B1: Valuation football field — Ero Copper (C$ per share)
B2: Each bar is a low–high range. The offer price line comes from the Merger tab.
B4: Method | C4: Low | D4: High | E4: Offer | F4: Basis
B5: 52-week trading range | C5: =Market!$M$6 -> 27.22 | D5: =Market!$N$6 -> 56.62 | E5: =DEAL_OFFER_CAD -> 54.639 | F5: Market tab
B6: Analyst price targets | C6: =Market!$O$6 -> 47 | D6: =Market!$Q$6 -> 68 | E6: =DEAL_OFFER_CAD -> 54.639 | F6: Low and high street targets (yfinance)
B7: Trading comps: EV / EBITDA (TTM) | C7: =((COMPS_EV_EBITDA_Q1*Market!$J$6)-DEAL_NET_DEBT)/ERO_SHARES/FX_SPOT -> 25.431253 | D7: =((COMPS_EV_EBITDA_Q3*Market!$J$6)-DEAL_NET_DEBT)/ERO_SHARES/FX_SPOT -> 51.097782 | E7: =DEAL_OFFER_CAD -> 54.639 | F7: Peer 25th–75th percentile x Ero TTM EBITDA, less net debt
B8: Trading comps: P / CF (TTM) | C8: =COMPS_PCF_Q1*Market!$K$6/ERO_SHARES/FX_SPOT -> 37.631752 | D8: =COMPS_PCF_Q3*Market!$K$6/ERO_SHARES/FX_SPOT -> 69.846703 | E8: =DEAL_OFFER_CAD -> 54.639 | F8: Peer 25th–75th percentile x Ero TTM operating cash flow
B9: Trading comps: EV / lb CuEq reserve | C9: =((COMPS_EVLB_Q1*Comps!$L$6*2204.62)-DEAL_NET_DEBT)/ERO_SHARES/FX_SPOT -> 15.191024 | D9: =((COMPS_EVLB_Q3*Comps!$L$6*2204.62)-DEAL_NET_DEBT)/ERO_SHARES/FX_SPOT -> 28.5875 | E9: =DEAL_OFFER_CAD -> 54.639 | F9: Peer 25th–75th percentile x Ero P&P reserves (CuEq), less net debt
B10: Precedent premiums | C10: =DEAL_UNAFFECTED*(1+PREC_PREM_Q1) -> 54.639 | D10: =DEAL_UNAFFECTED*(1+PREC_PREM_Q3) -> 57.5811 | E10: =DEAL_OFFER_CAD -> 54.639 | F10: 25th–75th percentile premium applied to the unaffected price
B11: NAV at Centerra's P/NAV (deck to spot) | C11: =MIN(Scenarios!$I$6*Scenarios!$J$6,Scenarios!$I$7*Scenarios!$J$7) -> 42.40207 | D11: =MAX(Scenarios!$I$6*Scenarios!$J$6,Scenarios!$I$7*Scenarios!$J$7) -> 47.798484 | E11: =DEAL_OFFER_CAD -> 54.639 | F11: Relative value in a share deal: Ero NAVPS x the multiple Centerra's own stock trades at
B12: NAV at 1.0x (deck to spot) | C12: =MIN(Scenarios!$I$6,Scenarios!$I$7) -> 17.803026 | D12: =MAX(Scenarios!$I$6,Scenarios!$I$7) -> 34.482456 | E12: =DEAL_OFFER_CAD -> 54.639 | F12: Reserve-only NAV; excludes resources outside the mine plan
B14: Offer price (C$) | C14: =DEAL_OFFER_CAD -> 54.639
B15: Unaffected price (C$) | C15: =DEAL_UNAFFECTED -> 42.03

Sheet Sources
B1: Sources
B2: Every input traces to one of these documents. Status flags anything estimated or calibrated rather than read directly from a filing.
B4: source_id | C4: company | D4: document | E4: doc_type | F4: effective_date | G4: url | H4: used_for | I4: verification_status
B5: CG-MRMR-2025 | C5: Centerra Gold | D5: Year-end 2025 Mineral Reserves and Resources tables and footnotes | E5: MRMR table | F5: 2025-12-31 | G5: https://s205.q4cdn.com/276554285/files/doc_earnings/2025/q4/generic/MRMR-Tables-and-Footnotes.pdf | H5: Mount Milligan, Öksüt and Goldfield P&P tonnes and gold grades | I5: verified (gold tonnes and grades)
B6: CG-MTM-PFS-2025 | C6: Centerra Gold | D6: Mount Milligan Pre-Feasibility Study (NI 43-101) — life of mine to 2045 | E6: NI 43-101 technical report | F6: 2025-09-11 | G6: https://s205.q4cdn.com/276554285/files/doc_downloads/2025/09/Centerra-Gold-Mount-Milligan-PFS.pdf | H6: Mine life, ~10% throughput expansion in 2029, US$186M growth capital | I6: verified (headline figures); copper grade estimated
B7: CG-Q2-2026 | C7: Centerra Gold | D7: Q2 2026 results and MD&A (Form 6-K) | E7: MD&A | F7: 2026-06-30 | G7: https://www.sec.gov/Archives/edgar/data/0001854640/000162828026050229/exh992_20260630.htm | H7: 2026 production and AISC guidance used to calibrate unit costs | I7: verified (guidance ranges)
B8: CG-RGLD-STREAM | C8: Royal Gold / Centerra Gold | D8: Mount Milligan streaming agreement (summarised in Centerra MD&A) | E8: Contract summary | F8: 2024-02-13 | G8: https://www.sec.gov/cgi-bin/browse-edgar?action=getcompany&CIK=0001854640 | H8: 35% gold at US$435/oz and 18.75% copper at 15% of spot | I8: verified (headline terms)
B9: ERO-AIF-2025 | C9: Ero Copper | D9: Annual Information Form FY2025 (Form 40-F) | E9: AIF | F9: 2025-12-31 | G9: https://www.sec.gov/Archives/edgar/data/1853860/000162828026022073/a991-2026aif.htm | H9: 2025 tonnes processed, copper and gold produced; reserve tables | I9: verified (2025 production)
B10: ERO-CARAIBA-OPS | C10: Ero Copper | D10: Caraíba Operations mineral reserves (company website) | E10: MRMR table | F10: 2024-12-31 | G10: https://ero-copper.com/operations/caraiba-operations/index.htm | H10: Caraíba UG 30.9 Mt @ 1.38% Cu and OP 42.2 Mt @ 0.54% Cu | I10: verified
B11: ERO-TUCUMA-TR | C11: Ero Copper | D11: Tucumã Project NI 43-101 technical report reserves | E11: NI 43-101 technical report | F11: 2021-09-30 | G11: https://minedocs.com/23/Ero-Copper-CP-Oct2022.pdf | H11: Tucumã P&P 43.1 Mt @ 0.83% Cu (pre-depletion) | I11: verified (pre-2024 depletion; depleted in model)
B12: ERO-XAV-2025 | C12: Ero Copper | D12: Xavantina Operations updated mineral reserve and resource estimate | E12: Press release | F12: 2025-10-31 | G12: https://erocopper.com/site/assets/files/6663/ero-copper-press-release-2025-q3.pdf | H12: Xavantina reserve tonnes and grade | I12: estimate (reserve tonnes/grade back-solved from 2025 production; replace with technical report table)
B13: ERO-MDA-2025Q4 | C13: Ero Copper | D13: FY2025 MD&A and 2026 guidance (Form 40-F) | E13: MD&A | F13: 2025-12-31 | G13: https://www.sec.gov/Archives/edgar/data/1853860/000162828026022073/erocopper-mdax2025q4.htm | H13: 2026 copper/gold guidance, C1 cash cost and AISC used to calibrate unit costs | I13: verified (guidance ranges)
B14: ERO-Q2-2026 | C14: Ero Copper | D14: Q2 2026 operating and financial results | E14: Press release | F14: 2026-06-30 | G14: https://www.barchart.com/story/news/3675711/ero-copper-reports-second-quarter-2026-operating-and-financial-results | H14: Reaffirmed copper guidance; revised Xavantina AISC US$2,200–2,700/oz | I14: verified (guidance ranges)
B15: MKT-YF | C15: Yahoo Finance | D15: Market data via yfinance (prices, shares, cash, debt, TTM EBITDA and cash flow) | E15: Market data | F15: see snapshot timestamp | G15: https://finance.yahoo.com | H15: Share prices, shares outstanding, balance sheet, TTM multiples, commodity futures, CAD/USD | I15: automated (scripts/fetch_market_data.py)
B18: Asset assumption status (data/asset_assumption_notes.csv)
B19: asset | C19: field | D19: status | E19: note
B20: MtMilligan | C20: reserve_mt|au_gpt | D20: verified | E20: Year-end 2025 P&P 470.3 Mt @ 0.28 g/t Au (CG-MRMR-2025)
B21: MtMilligan | C21: cu_grade_pct | D21: estimate | E21: Copper grade not captured from the MRMR table; 0.16% Cu calibrated to 50–60 Mlb/yr 2026 guidance
B22: MtMilligan | C22: expansion_mtpa|expansion_year|growth_capex_usd_m | D22: verified | E22: PFS: ~10% throughput increase in 2029 and US$186M growth capital
B23: MtMilligan | C23: recoveries|opex_usd_t|sustaining_usd_m | D23: calibrated | E23: Set so 2027 AISC lands in the US$1.2–1.3k/oz guidance range
B24: MtMilligan | C24: stream_* | D24: verified | E24: Royal Gold stream: 35% of gold at US$435/oz; 18.75% of copper at 15% of spot
B25: MtMilligan | C25: depleted_mt | D25: estimate | E25: 2026 ore processed (~59 ktpd)
B26: Oksut | C26: reserve_mt|au_gpt | D26: verified | E26: Year-end 2025 P&P 15.4 Mt @ 1.02 g/t Au
B27: Oksut | C27: nsr_royalty|opex_usd_t | D27: calibrated | E27: Set so AISC lands in the US$1,850–1,950/oz 2026 guidance range (includes state royalty)
B28: Goldfield | C28: reserve_mt|au_gpt | D28: verified | E28: Year-end 2025 P&P 33.3 Mt @ 0.66 g/t Au (maiden reserve)
B29: Goldfield | C29: growth_capex_usd_m|start_year|throughput_mtpa | D29: estimate | E29: Development schedule and capex are analyst estimates pending a construction decision
B30: Caraiba | C30: reserve_mt|cu_grade_pct | D30: verified | E30: Dec 2024 P&P: UG 30.9 Mt @ 1.38% + OP 42.2 Mt @ 0.54% = 73.1 Mt @ 0.90% Cu
... B39: Xavantina | C39: opex_usd_t|sustaining_usd_m | D39: calibrated | E39: Set so AISC lands in the revised US$2,200–2,700/oz guidance range
